Workbook

Sheet P&L 4 years
A4: Company Name: | B4: Sample Company Name | F4: Job Number: | G4: 100507-01 | I4: Date: | J4: 40922
A6: YEAR: | B6: 2011 | D6: 2010 | F6: 2009 | H6: 2008
A7: # Months | B7: 11 | D7: 12 | F7: 12 | H7: 12
A8: Ending | B8: November | D8: December | F8: December | H8: December | J8: TOTAL
A9: SALES
B10: 750000 | C10: =SUM(B10/B$13) -> 0.88235294 | D10: 424761 | E10: =SUM(D10/D$13) -> 0.67987759 | F10: 398292 | G10: =SUM(F10/F$13) -> 0.66571507 | H10: 421524 | I10: =SUM(H10/H$13) -> 0.67821033 | J10: =SUM(B10:I10) -> 1994579.9 | K10: =SUM(J10/J$13) -> 0.74021895
B11: 100000 | C11: =SUM(B11/B$13) -> 0.11764706 | D11: 100000 | E11: =SUM(D11/D$13) -> 0.16006121 | F11: 100000 | G11: =SUM(F11/F$13) -> 0.16714247 | H11: 100000 | I11: =SUM(H11/H$13) -> 0.16089483 | J11: =SUM(B11:I11) -> 400000.61 | K11: =SUM(J11/J$13) -> 0.14844631
B12: 0 | C12: =SUM(B12/B$13) -> 0 | D12: 100000 | E12: =SUM(D12/D$13) -> 0.16006121 | F12: 100000 | G12: =SUM(F12/F$13) -> 0.16714247 | H12: 100000 | I12: =SUM(H12/H$13) -> 0.16089483 | J12: =SUM(B12:I12) -> 300000.49 | K12: =SUM(J12/J$13) -> 0.11133474
A13: TOTAL SALES | B13: =SUM(B10:B12) -> 850000 | C13: =SUM(B13/B$13) -> 1 | D13: =SUM(D10:D12) -> 624761 | E13: =SUM(D13/D$13) -> 1 | F13: =SUM(F10:F12) -> 598292 | G13: =SUM(F13/F$13) -> 1 | H13: =SUM(H10:H12) -> 621524 | I13: =SUM(H13/H$13) -> 1 | J13: =SUM(B13:I13) -> 2694581 | K13: =SUM(J13/J$13) -> 1
A14: Cost of Goods Sold
A15: Purchases | B15: 49150 | C15: =SUM(B15/B$13) -> 0.057823529 | D15: 223973 | E15: =SUM(D15/D$13) -> 0.35849389 | F15: 219177 | G15: =SUM(F15/F$13) -> 0.36633784 | H15: 213686 | I15: =SUM(H15/H$13) -> 0.34380973 | J15: =SUM(B15:I15) -> 705987.13 | K15: =SUM(J15/J$13) -> 0.26200256
A16: Direct Labor | B16: 17202 | C16: =SUM(B16/B$13) -> 0.020237647 | D16: 68808 | E16: =SUM(D16/D$13) -> 0.11013492 | F16: 65532 | G16: =SUM(F16/F$13) -> 0.1095318 | H16: 63723 | I16: =SUM(H16/H$13) -> 0.10252701 | J16: =SUM(B16:I16) -> 215265.34 | K16: =SUM(J16/J$13) -> 0.079888243
A17: Sub Contractor | B17: 20000 | C17: =SUM(B17/B$13) -> 0.023529412 | D17: 10000 | E17: =SUM(D17/D$13) -> 0.016006121 | F17: 20000 | G17: =SUM(F17/F$13) -> 0.033428493 | H17: 10000 | I17: =SUM(H17/H$13) -> 0.016089483 | J17: =SUM(B17:I17) -> 60000.089 | K17: =SUM(J17/J$13) -> 0.022266946
A18: Other Direct | B18: 20000 | C18: =SUM(B18/B$13) -> 0.023529412 | D18: 10000 | E18: =SUM(D18/D$13) -> 0.016006121 | F18: 20000 | G18: =SUM(F18/F$13) -> 0.033428493 | H18: 10000 | I18: =SUM(H18/H$13) -> 0.016089483 | J18: =SUM(B18:I18) -> 60000.089 | K18: =SUM(J18/J$13) -> 0.022266946
A19: TOTAL COGS | B19: =SUM(B15:B18) -> 106352 | C19: =SUM(B19/B$13) -> 0.12512 | D19: =SUM(D15:D18) -> 312781 | E19: =SUM(D19/D$13) -> 0.50064105 | F19: =SUM(F15:F18) -> 324709 | G19: =SUM(F19/F$13) -> 0.54272663 | H19: =SUM(H15:H18) -> 297409 | I19: =SUM(H19/H$13) -> 0.47851571 | J19: =SUM(B19:I19) -> 1041252.6 | K19: =SUM(J19/J$13) -> 0.3864247
A20: Gross Profit | B20: =SUM(B13-B19) -> 743648 | C20: =SUM(B20/B$13) -> 0.87488 | D20: =SUM(D13-D19) -> 311980 | E20: =SUM(D20/D$13) -> 0.49935895 | F20: =SUM(F13-F19) -> 273583 | G20: =SUM(F20/F$13) -> 0.45727337 | H20: =SUM(H13-H19) -> 324115 | I20: =SUM(H20/H$13) -> 0.52148429 | J20: =SUM(B20:I20) -> 1653328.4 | K20: =SUM(J20/J$13) -> 0.6135753
A21: EXPENSES
A22: Selling Costs
A23: Advertising | B23: 639 | C23: =SUM(B23/B$13) -> 0.00075176471 | D23: 2546 | E23: =SUM(D23/D$13) -> 0.0040751583 | F23: 2425 | G23: =SUM(F23/F$13) -> 0.0040532048 | H23: 3633 | I23: =SUM(H23/H$13) -> 0.0058453093 | J23: =SUM(B23:I23) -> 9243.0147 | K23: =SUM(J23/J$13) -> 0.0034302234
A24: Other Selling Costs | B24: 7008 | C24: =SUM(B24/B$13) -> 0.0082447059 | D24: 28033 | E24: =SUM(D24/D$13) -> 0.044869958 | F24: 10591 | G24: =SUM(F24/F$13) -> 0.017702059 | H24: 26699 | I24: =SUM(H24/H$13) -> 0.042957311 | J24: =SUM(B24:I24) -> 72331.114 | K24: =SUM(J24/J$13) -> 0.026843177
A25: TOTAL SELLING COSTS | B25: =SUM(B23:B24) -> 7647 | C25: =SUM(B25/B$13) -> 0.0089964706 | D25: =SUM(D23:D24) -> 30579 | E25: =SUM(D25/D$13) -> 0.048945117 | F25: =SUM(F23:F24) -> 13016 | G25: =SUM(F25/F$13) -> 0.021755263 | H25: =SUM(H23:H24) -> 30332 | I25: =SUM(H25/H$13) -> 0.048802621 | J25: =SUM(B25:I25) -> 81574.128 | K25: =SUM(J25/J$13) -> 0.0302734
A27: Officers Salaries | B27: 12999 | C27: =SUM(B27/B$13) -> 0.015292941 | D27: 52000 | E27: =SUM(D27/D$13) -> 0.083231828 | F27: 52000 | G27: =SUM(F27/F$13) -> 0.086914082 | H27: 52000 | I27: =SUM(H27/H$13) -> 0.083665313 | J27: =SUM(B27:I27) -> 168999.27 | K27: =SUM(J27/J$13) -> 0.0627182
A28: Admin Salaries & Wages | B28: 10000 | C28: =SUM(B28/B$13) -> 0.011764706 | D28: 100 | E28: =SUM(D28/D$13) -> 0.00016006121 | F28: 100 | G28: =SUM(F28/F$13) -> 0.00016714247 | H28: 100 | I28: =SUM(H28/H$13) -> 0.00016089483 | J28: =SUM(B28:I28) -> 10300.012 | K28: =SUM(J28/J$13) -> 0.0038224912
A29: Other Administrative Costs | B29: =SUM(B31-B25-B27-B28) -> 714094 | C29: =SUM(B29/B$13) -> 0.84011059 | D29: =SUM(D31-D25-D27-D28) -> 240964 | E29: =SUM(D29/D$13) -> 0.38568989 | F29: =SUM(F31-F25-F27-F28) -> 231687 | G29: =SUM(F29/F$13) -> 0.38724736 | H29: =SUM(H31-H25-H27-H28) -> 241682 | I29: =SUM(H29/H$13) -> 0.38885385 | J29: =SUM(B29:I29) -> 1428429 | K29: =SUM(J29/J$13) -> 0.53011173
A31: TTL OP EXPENSES | B31: =SUM(B20-B32) -> 744740 | C31: =SUM(B31/B$13) -> 0.87616471 | D31: =SUM(D20-D32) -> 323643 | E31: =SUM(D31/D$13) -> 0.51802689 | F31: =SUM(F20-F32) -> 296803 | G31: =SUM(F31/F$13) -> 0.49608385 | H31: =SUM(H20-H32) -> 324114 | I31: =SUM(H31/H$13) -> 0.52148268 | J31: =SUM(B31:I31) -> 1689302.4 | K31: =SUM(J31/J$13) -> 0.62692582
A32: NET OP PROFIT | B32: -1092 | C32: =SUM(B32/B$13) -> -0.0012847059 | D32: -11663 | E32: =SUM(D32/D$13) -> -0.018667939 | F32: -23220 | G32: =SUM(F32/F$13) -> -0.038810481 | H32: 1 | I32: =SUM(H32/H$13) -> 1.6089483e-06 | J32: =SUM(B32:I32) -> -35974.059 | K32: =SUM(J32/J$13) -> -0.01335052
A33: TOTAL OWNERSHIP RETURN | B33: =SUM(B27+B32) -> 11907 | C33: =SUM(B33/B$13) -> 0.014008235 | D33: =SUM(D27+D32) -> 40337 | E33: =SUM(D33/D$13) -> 0.064563889 | F33: =SUM(F27+F32) -> 28780 | G33: =SUM(F33/F$13) -> 0.048103602 | H33: =SUM(H27+H32) -> 52001 | I33: =SUM(H33/H$13) -> 0.083666922 | J33: =SUM(J27+J32) -> 133025.21 | K33: =SUM(J33/J$13) -> 0.049367679

Sheet OPTIMAL
B1: CLIENT: | C1: Sample Company Name
B2: JOB #: | C2: 100507-01
B3: DATE: | C3: 40922
B5: YEAR: | C5: 2012
B6: # Months | C6: 12
B7: Ending | C7: March
B8: TOTAL SALES | C8: =SUM('P&L 4 years'!B13) -> 850000 | D8: =SUM(C8/C$8) -> 1
B10: Cost of Goods Sold
B11: Purchases | C11: =SUM(C$8*D11) -> 187000 | D11: 0.22
B12: Direct Labor | C12: =SUM(C$8*D12) -> 194650 | D12: 0.229
B13: Sub Contractor | C13: =SUM(C$8*D13) -> 22950 | D13: 0.027
B14: Other Direct | C14: =SUM(C$8*D14) -> 1700 | D14: 0.002
B15: TOTAL COGS | C15: =SUM(C11:C14) -> 406300 | D15: =SUM(C15/C$8) -> 0.478
B17: Gross Profit | C17: =SUM(C8-C15) -> 443700 | D17: =SUM(C17/C$8) -> 0.522
B18: EXPENSES
B19: Selling Costs
B20: Advertising | C20: =SUM(C$8*D20) -> 2550 | D20: 0.003
B21: Other Selling Costs | C21: =SUM(C$8*D21) -> 7650 | D21: 0.009
B22: TOTAL SELLING COSTS | C22: =SUM(C20:C21) -> 10200 | D22: =SUM(C22/C$8) -> 0.012
B24: Officers Salaries | C24: =SUM(C8*D24) -> 88400 | D24: 0.104
B25: Admin Salaries & Wages | C25: =SUM(C$8*D25) -> 18700 | D25: 0.022
B26: Other Administrative Costs | C26: =SUM(C$8*D26) -> 170850 | D26: 0.201
B28: TTL OP EXPENSES | C28: =SUM(C22:C26) -> 288150 | D28: =SUM(C28/C$8) -> 0.339
B30: NET OP PROFIT | C30: =SUM(C17-C28) -> 155550 | D30: =SUM(C30/C$8) -> 0.183
B32: TOTAL OWNERSHIP RETURN | C32: =SUM(C24+C30) -> 243950 | D32: =SUM(C32/C$8) -> 0.287
B34: ACTUAL OWNERSHIP RETURN | C34: =SUM('P&L 4 years'!B33) -> 11907 | D34: =SUM(C34/C$8) -> 0.014008235
B36: TOTAL LOST POTENTIAL | C36: =SUM(C34-C32) -> -232043 | D36: =SUM(C36/C$8) -> -0.27299176

Sheet 4 YEAR LOSS
A1: CLIENT: | B1: Sample Company Name
A2: JOB #: | B2: 100507-01
A3: DATE: | B3: 40922
A4: YEAR: | B4: 2010 | D4: 2009 | F4: 2008 | H4: 2007
A5: # Months | B5: 12 | D5: 12 | F5: 12 | H5: 12 | J5: TOTAL
A6: Ending | B6: December | D6: December | F6: December | H6: December
A7: TOTAL SALES | B7: =SUM('P&L 4 years'!B13) -> 850000 | C7: =SUM(B7/B$7) -> 1 | D7: =SUM('P&L 4 years'!D13) -> 624761 | E7: =SUM(D7/D$7) -> 1 | F7: =SUM('P&L 4 years'!F13) -> 598292 | G7: =SUM(F7/F$7) -> 1 | H7: =SUM('P&L 4 years'!H13) -> 621524 | I7: =SUM(H7/H$7) -> 1 | J7: =SUM(B7:I7) -> 2694581 | K7: =SUM(J7/J$7) -> 1
A9: Cost of Goods Sold
A10: Purchases | B10: =SUM(B$7*C10) -> 187000 | C10: =SUM(OPTIMAL!D11) -> 0.22 | D10: =SUM(D$7*E10) -> 137447.42 | E10: =SUM(C10) -> 0.22 | F10: =SUM(F$7*G10) -> 131624.24 | G10: =SUM(E10) -> 0.22 | H10: =SUM(H$7*I10) -> 136735.28 | I10: =SUM(G10) -> 0.22 | J10: =SUM(B10:I10) -> 592807.82 | K10: =SUM(J10/J$7) -> 0.22
A11: Direct Labor | B11: =SUM(B$7*C11) -> 194650 | C11: =SUM(OPTIMAL!D12) -> 0.229 | D11: =SUM(D$7*E11) -> 143070.27 | E11: =SUM(C11) -> 0.229 | F11: =SUM(F$7*G11) -> 137008.87 | G11: =SUM(E11) -> 0.229 | H11: =SUM(H$7*I11) -> 142329 | I11: =SUM(G11) -> 0.229 | J11: =SUM(B11:I11) -> 617059.05 | K11: =SUM(J11/J$7) -> 0.229
A12: Sub Contractor | B12: =SUM(B$7*C12) -> 22950 | C12: =SUM(OPTIMAL!D13) -> 0.027 | D12: =SUM(D$7*E12) -> 16868.547 | E12: =SUM(C12) -> 0.027 | F12: =SUM(F$7*G12) -> 16153.884 | G12: =SUM(E12) -> 0.027 | H12: =SUM(H$7*I12) -> 16781.148 | I12: =SUM(G12) -> 0.027 | J12: =SUM(B12:I12) -> 72753.687 | K12: =SUM(J12/J$7) -> 0.027
A13: Other Direct | B13: =SUM(B$7*C13) -> 1700 | C13: =SUM(OPTIMAL!D14) -> 0.002 | D13: =SUM(D$7*E13) -> 1249.522 | E13: =SUM(C13) -> 0.002 | F13: =SUM(F$7*G13) -> 1196.584 | G13: =SUM(E13) -> 0.002 | H13: =SUM(H$7*I13) -> 1243.048 | I13: =SUM(G13) -> 0.002 | J13: =SUM(B13:I13) -> 5389.162 | K13: =SUM(J13/J$7) -> 0.002
A14: TOTAL COGS | B14: =SUM(B10:B13) -> 406300 | C14: =SUM(B14/B$7) -> 0.478 | D14: =SUM(D10:D13) -> 298635.76 | E14: =SUM(D14/D$7) -> 0.478 | F14: =SUM(F10:F13) -> 285983.58 | G14: =SUM(F14/F$7) -> 0.478 | H14: =SUM(H10:H13) -> 297088.47 | I14: =SUM(H14/H$7) -> 0.478 | J14: =SUM(B14:I14) -> 1288009.7 | K14: =SUM(J14/J$7) -> 0.478
A16: Gross Profit | B16: =SUM(B7-B14) -> 443700 | C16: =SUM(B16/B$7) -> 0.522 | D16: =SUM(D7-D14) -> 326125.24 | E16: =SUM(D16/D$7) -> 0.522 | F16: =SUM(F7-F14) -> 312308.42 | G16: =SUM(F16/F$7) -> 0.522 | H16: =SUM(H7-H14) -> 324435.53 | I16: =SUM(H16/H$7) -> 0.522 | J16: =SUM(B16:I16) -> 1406571.3 | K16: =SUM(J16/J$7) -> 0.522
A17: EXPENSES
A18: Selling Costs
A19: Advertising | B19: =SUM(B$7*C19) -> 2550 | C19: =SUM(OPTIMAL!D20) -> 0.003 | D19: =SUM(D$7*E19) -> 1874.283 | E19: =SUM(C19) -> 0.003 | F19: =SUM(F$7*G19) -> 1794.876 | G19: =SUM(E19) -> 0.003 | H19: =SUM(H$7*I19) -> 1864.572 | I19: =SUM(G19) -> 0.003 | J19: =SUM(B19:I19) -> 8083.743 | K19: =SUM(J19/J$7) -> 0.003
A20: Other Selling Costs | B20: =SUM(B$7*C20) -> 7650 | C20: =SUM(OPTIMAL!D21) -> 0.009 | D20: =SUM(D$7*E20) -> 5622.849 | E20: =SUM(C20) -> 0.009 | F20: =SUM(F$7*G20) -> 5384.628 | G20: =SUM(E20) -> 0.009 | H20: =SUM(H$7*I20) -> 5593.716 | I20: =SUM(G20) -> 0.009 | J20: =SUM(B20:I20) -> 24251.229 | K20: =SUM(J20/J$7) -> 0.009
A21: TOTAL SELLING COSTS | B21: =SUM(B19:B20) -> 10200 | C21: =SUM(B21/B$7) -> 0.012 | D21: =SUM(D19:D20) -> 7497.132 | E21: =SUM(D21/D$7) -> 0.012 | F21: =SUM(F19:F20) -> 7179.504 | G21: =SUM(F21/F$7) -> 0.012 | H21: =SUM(H19:H20) -> 7458.288 | I21: =SUM(H21/H$7) -> 0.012 | J21: =SUM(B21:I21) -> 32334.972 | K21: =SUM(J21/J$7) -> 0.012
A23: Officers Salaries | B23: =SUM(B$7*C23) -> 88400 | C23: =SUM(OPTIMAL!D24) -> 0.104 | D23: =SUM(D$7*E23) -> 64975.144 | E23: =SUM(C23) -> 0.104 | F23: =SUM(F$7*G23) -> 62222.368 | G23: =SUM(E23) -> 0.104 | H23: =SUM(H$7*I23) -> 64638.496 | I23: =SUM(G23) -> 0.104 | J23: =SUM(B23:I23) -> 280236.42 | K23: =SUM(J23/J$7) -> 0.104
A24: Admin Salaries & Wages | B24: =SUM(B$7*C24) -> 18700 | C24: =SUM(OPTIMAL!D25) -> 0.022 | D24: =SUM(D$7*E24) -> 13744.742 | E24: =SUM(C24) -> 0.022 | F24: =SUM(F$7*G24) -> 13162.424 | G24: =SUM(E24) -> 0.022 | H24: =SUM(H$7*I24) -> 13673.528 | I24: =SUM(G24) -> 0.022 | J24: =SUM(B24:I24) -> 59280.782 | K24: =SUM(J24/J$7) -> 0.022
A25: Other Administrative Costs | B25: =SUM(B$7*C25) -> 170850 | C25: =SUM(OPTIMAL!D26) -> 0.201 | D25: =SUM(D$7*E25) -> 125576.96 | E25: =SUM(C25) -> 0.201 | F25: =SUM(F$7*G25) -> 120256.69 | G25: =SUM(E25) -> 0.201 | H25: =SUM(H$7*I25) -> 124926.32 | I25: =SUM(G25) -> 0.201 | J25: =SUM(B25:I25) -> 541610.78 | K25: =SUM(J25/J$7) -> 0.201
A27: TTL OP EXPENSES | B27: =SUM(B21:B25) -> 288150 | C27: =SUM(B27/B$7) -> 0.339 | D27: =SUM(D21:D25) -> 211793.98 | E27: =SUM(D27/D$7) -> 0.339 | F27: =SUM(F21:F25) -> 202820.99 | G27: =SUM(F27/F$7) -> 0.339 | H27: =SUM(H21:H25) -> 210696.64 | I27: =SUM(H27/H$7) -> 0.339 | J27: =SUM(B27:I27) -> 913462.96 | K27: =SUM(J27/J$7) -> 0.339
A29: NET OP PROFIT | B29: =SUM(B16-B27) -> 155550 | C29: =SUM(B29/B$7) -> 0.183 | D29: =SUM(D16-D27) -> 114331.26 | E29: =SUM(D29/D$7) -> 0.183 | F29: =SUM(F16-F27) -> 109487.44 | G29: =SUM(F29/F$7) -> 0.183 | H29: =SUM(H16-H27) -> 113738.89 | I29: =SUM(H29/H$7) -> 0.183 | J29: =SUM(B29:I29) -> 493108.32 | K29: =SUM(J29/J$7) -> 0.183
A31: TOTAL OWNERSHIP RETURN | B31: =SUM(B23+B29) -> 243950 | C31: =SUM(B31/B$7) -> 0.287 | D31: =SUM(D23+D29) -> 179306.41 | E31: =SUM(D31/D$7) -> 0.287 | F31: =SUM(F23+F29) -> 171709.8 | G31: =SUM(F31/F$7) -> 0.287 | H31: =SUM(H23+H29) -> 178377.39 | I31: =SUM(H31/H$7) -> 0.287 | J31: =SUM(J23+J29) -> 773344.75 | K31: =SUM(J31/J$7) -> 0.287
A33: ACTUAL OWNERSHIP RETURN | B33: =SUM('P&L 4 years'!B33) -> 11907 | C33: =SUM(B33/B$7) -> 0.014008235 | D33: =SUM('P&L 4 years'!D33) -> 40337 | E33: =SUM(D33/D$7) -> 0.064563889 | F33: =SUM('P&L 4 years'!F33) -> 28780 | G33: =SUM(F33/F$7) -> 0.048103602 | H33: =SUM('P&L 4 years'!H33) -> 52001 | I33: =SUM(H33/H$7) -> 0.083666922 | J33: =SUM('P&L 4 years'!J33) -> 133025.21 | K33: =SUM(J33/J$7) -> 0.049367679
A35: TOTAL LOST POTENTIAL | B35: =SUM(B33-B31) -> -232043 | C35: =SUM(B35/B$7) -> -0.27299176 | D35: =SUM(D33-D31) -> -138969.41 | E35: =SUM(D35/D$7) -> -0.22243611 | F35: =SUM(F33-F31) -> -142929.8 | G35: =SUM(F35/F$7) -> -0.2388964 | H35: =SUM(H33-H31) -> -126376.39 | I35: =SUM(H35/H$7) -> -0.20333308 | J35: =SUM(J33-J31) -> -640319.54 | K35: =SUM(J35/J$7) -> -0.23763232
