Workbook

Sheet Title 

Sheet 1. Cash Flow Summary
B1: Each week is dated to end on Saturday
A2: Weekly Forecast | B2: 1st Week | D2: 2nd Week | E2: 3rd Week | F2: 4th Week | G2: 5th Week
B3: 44254 | D3: =B3+7 -> 44261 | E3: =D3+7 -> 44268 | F3: =E3+7 -> 44275 | G3: =F3+7 -> 44282
B4: Estimated | C4: Actual | D4: Estimated | E4: Estimated | F4: Estimated | G4: Estimated
A5: CASH RECEIPTS:
A6: Beginning Balance | B6: =+C6 -> 0 | C6: 0 | D6: 0 | E6: 0 | F6: 0 | G6: 0
A7: Accounts Receivable- from separate schedule | B7: =+'2. Accounts Receivable'!C13 -> 0 | C7: =+'2. Accounts Receivable'!D13 -> 0 | D7: =+'2. Accounts Receivable'!E13 -> 0 | E7: =+'2. Accounts Receivable'!F13 -> 0 | F7: =+'2. Accounts Receivable'!G13 -> 0 | G7: =+'2. Accounts Receivable'!H13 -> 0
A8: Transfer from: LOC | B8: 0 | C8: 0 | D8: 0 | E8: 0 | F8: 0 | G8: 0
A9: Transfer from: Money Market | B9: 0 | C9: 0 | D9: 0 | E9: 0 | F9: 0 | G9: 0
A10: Total Available | B10: =SUM(B6:B9) -> 0 | C10: =SUM(C6:C9) -> 0 | D10: =SUM(D6:D9) -> 0 | E10: =SUM(E6:E9) -> 0 | F10: =SUM(F6:F9) -> 0 | G10: =SUM(G6:G9) -> 0
A11: DISBURSEMENTS:
A12: Payroll | B12: 0 | C12: 0 | D12: 0 | E12: 0 | F12: 0 | G12: 0
A13: C.O.D. | B13: 0 | C13: 0 | D13: 0 | E13: 0 | F13: 0 | G13: 0
A14: L.O.C. | B14: 0 | C14: 0 | D14: 0 | E14: 0 | F14: 0 | G14: 0
A15: Accounts Payable- from separate schedule | B15: =+'3. Accounts Payable'!C13 -> 0 | C15: =+'3. Accounts Payable'!D13 -> 0 | D15: =+'3. Accounts Payable'!E13 -> 0 | E15: =+'3. Accounts Payable'!F13 -> 0 | F15: =+'3. Accounts Payable'!G13 -> 0 | G15: =+'3. Accounts Payable'!H13 -> 0
A16: Total Expenses | B16: =SUM(B12:B15) -> 0 | C16: =SUM(C12:C15) -> 0 | D16: =SUM(D12:D15) -> 0 | E16: =SUM(E12:E15) -> 0 | F16: =SUM(F12:F15) -> 0 | G16: =SUM(G12:G15) -> 0
A17: Transfer to: Money Market | B17: 20000 | C17: 0 | D17: 0 | E17: 0 | F17: 0 | G17: 0
A18: ENDING BALANCE | B18: =(+B10-+B16)-+B17 -> -20000 | C18: =(+C10-+C16)-+C17 -> 0 | D18: =(+D10-+D16)-+D17 -> 0 | E18: =(+E10-+E16)-+E17 -> 0 | F18: =(+F10-+F16)-+F17 -> 0 | G18: =(+G10-+G16)-+G17 -> 0
A20: Shaded $ and date cells require no data entry.

Sheet 2. Accounts Receivable
C2: Each week is dated to end on Saturday
A3: Weekly Forecast | C3: 1st Week | E3: 2nd Week | F3: 3rd Week | G3: 4th Week | H3: 5th Week
A4: Accounts | B4: Account | C4: =+'1. Cash Flow Summary'!B3 -> 44254 | E4: =C4+7 -> 44261 | F4: =E4+7 -> 44268 | G4: =F4+7 -> 44275 | H4: =G4+7 -> 44282
A5: Receivable | B5: Balance | C5: Estimated | D5: Actual | E5: Estimated | F5: Estimated | G5: Estimated | H5: Estimated
A6: Account # 1 | B6: 0 | C6: 0 | D6: 0 | E6: 0 | F6: 0 | G6: 0 | H6: 0
A7: Account # 2 | B7: 0 | C7: 0 | D7: 0 | E7: 0 | F7: 0 | G7: 0 | H7: 0
B8: 0 | C8: 0 | D8: 0 | E8: 0 | F8: 0 | G8: 0 | H8: 0
B9: 0 | C9: 0 | D9: 0 | E9: 0 | F9: 0 | G9: 0 | H9: 0
B10: 0 | C10: 0 | D10: 0 | E10: 0 | F10: 0 | G10: 0 | H10: 0
B11: 0 | C11: 0 | D11: 0 | E11: 0 | F11: 0 | G11: 0 | H11: 0
B12: 0 | C12: 0 | D12: 0 | E12: 0 | F12: 0 | G12: 0 | H12: 0
A13: TOTAL CARRY FORWARD | B13: =SUM(B6:B12) -> 0 | C13: =SUM(C6:C12) -> 0 | D13: =SUM(D6:D12) -> 0 | E13: =SUM(E6:E12) -> 0 | F13: =SUM(F6:F12) -> 0 | G13: =SUM(G6:G12) -> 0 | H13: =SUM(H6:H12) -> 0

Sheet 3. Accounts Payable
C2: Each week is dated to end on Saturday
A3: Weekly Forecast | C3: 1st Week | E3: 2nd Week | F3: 3rd Week | G3: 4th Week | H3: 5th Week
A4: Accounts | B4: Account | C4: =+'1. Cash Flow Summary'!B3 -> 44254 | E4: =C4+7 -> 44261 | F4: =E4+7 -> 44268 | G4: =F4+7 -> 44275 | H4: =G4+7 -> 44282
A5: Payable | B5: Balance | C5: Estimated | D5: Actual | E5: Estimated | F5: Estimated | G5: Estimated | H5: Estimated
A6: Vendor #1 | B6: 0 | C6: 0 | D6: 0 | E6: 0 | F6: 0 | G6: 0 | H6: 0
A7: Vendor #2 | B7: 0 | C7: 0 | D7: 0 | E7: 0 | G7: 0 | H7: 0
B8: 0 | C8: 0 | D8: 0 | E8: 0 | F8: 0 | G8: 0 | H8: 0
B9: 0 | C9: 0 | D9: 0 | E9: 0 | F9: 0 | G9: 0 | H9: 0
B10: 0 | C10: 0 | D10: 0 | E10: 0 | F10: 0 | G10: 0 | H10: 0
B11: 0 | C11: 0 | D11: 0 | E11: 0 | F11: 0 | G11: 0 | H11: 0
B12: 0 | C12: 0 | D12: 0 | E12: 0 | F12: 0 | G12: 0 | H12: 0
A13: TOTAL CARRY FORWARD | B13: =SUM(B6:B12) -> 0 | C13: =SUM(C6:C12) -> 0 | D13: =SUM(D6:D12) -> 0 | E13: =SUM(E6:E12) -> 0 | F13: =SUM(F6:F12) -> 0 | G13: =SUM(G6:G12) -> 0 | H13: =SUM(H6:H12) -> 0
