Workbook

Sheet FE Sales YR 1
B1: FRONT END SALES FORECAST | P1: **Green boxes can be changed to modify forecast
B2: 44734 | C2: 44764 | D2: 44795 | E2: 44826 | F2: 44856 | G2: 44887 | H2: 44948 | I2: 44980 | J2: 45008 | K2: 45039 | L2: 45067 | M2: 45098
A3: Month # | B3: 1 | C3: 2 | D3: 3 | E3: 4 | F3: 5 | G3: 6 | H3: 7 | I3: 8 | J3: 9 | K3: 10 | L3: 11 | M3: 12 | N3: TOTAL | P3: SALES TEAM
A4: FE SALES HEAD COUNT | P4: Position | Q4: Salary | R4: Comm %* | S4: Survey Fee%
N5: =SUM(M5) -> 0 | Q5: 0
A6: Business Coordinator | B6: 4 | C6: 4 | D6: 6 | E6: 6 | F6: 1 | G6: 6 | H6: 6 | I6: 3 | J6: 3 | K6: 3 | L6: 3 | M6: 3 | N6: =SUM(M6) -> 3 | P6: BC | Q6: 4000 | R6: 0.0125 | S6: 0
A7: Marketing Manager | B7: 1 | C7: 1 | D7: 1 | E7: 1 | F7: 1 | G7: 1 | H7: 1 | I7: 1 | J7: 1 | K7: 1 | L7: 1 | M7: 1 | N7: =SUM(M7) -> 1 | P7: Marketig Manager | Q7: 0 | R7: 0.01 | S7: 0.01
A8: Regional Marketing Director | B8: 3 | C8: 3 | D8: 4 | E8: 4 | F8: 4 | G8: 4 | H8: 6 | I8: 6 | J8: 6 | K8: 6 | L8: 6 | M8: 6 | N8: =SUM(M8) -> 6 | P8: RMD | Q8: 2000 | R8: 0.04 | S8: 0.5
A9: RSM | B9: 0 | C9: 0 | D9: 0 | E9: 0 | F9: 1 | G9: 0 | H9: 0 | I9: 0 | J9: 0 | K9: 0 | L9: 0 | M9: 0 | Q9: 0
A10: TOTAL | B10: =SUM(B5:B9) -> 8 | C10: =SUM(C5:C9) -> 8 | D10: =SUM(D5:D9) -> 11 | E10: =SUM(E5:E9) -> 11 | F10: 1 | G10: =SUM(G5:G9) -> 11 | H10: =SUM(H5:H9) -> 13 | I10: =SUM(I5:I9) -> 10 | J10: =SUM(J5:J9) -> 10 | K10: =SUM(K5:K9) -> 10 | L10: =SUM(L5:L9) -> 10 | M10: =SUM(M5:M9) -> 10 | N10: =SUM(N5:N9) -> 10 | R10: =SUM(R5:R9) -> 0.0625 | S10: =SUM(S5:S9) -> 0.51
A12: REVENUE | P12: ASSUMPTIONS
A13: Survey Fees | B13: =B8*$Q$13*$Q$14 -> 27000 | C13: =C8*$Q$13*$Q$14*50% -> 13500 | D13: =D8*$Q$13*$Q$14*75% -> 27000 | E13: =E8*$Q$13*$Q$14 -> 36000 | F13: =F8*$Q$13*$Q$14 -> 36000 | G13: =G8*$Q$13*$Q$14 -> 36000 | H13: =H8*$Q$13*$Q$14*75% -> 40500 | I13: =I8*$Q$13*$Q$14 -> 54000 | J13: =J8*$Q$13*$Q$14 -> 54000 | K13: =K8*$Q$13*$Q$14 -> 54000 | L13: =L8*$Q$13*$Q$14 -> 54000 | M13: =M8*$Q$13*$Q$14 -> 54000 | N13: =SUM(B13:M13) -> 486000 | P13: # Mo Sales per RMD | Q13: 5
A14: Cash Collect | B14: 0 | C14: =C6*$Q$13*$Q$15*$Q$16*$Q$17*40% -> 558400 | D14: =D6*$Q$13*$Q$15*$Q$16*$Q$17*60% -> 1256400 | E14: =E6*$Q$13*$Q$15*$Q$16*$Q$17*85% -> 1779900 | F14: =F6*$Q$13*$Q$15*$Q$16*$Q$17 -> 349000 | G14: =G6*$Q$13*$Q$15*$Q$16*$Q$17 -> 2094000 | H14: =H6*$Q$13*$Q$15*$Q$16*$Q$17*70% -> 1465800 | I14: =I6*$Q$13*$Q$15*$Q$16*$Q$17 -> 1047000 | J14: =J6*$Q$13*$Q$15*$Q$16*$Q$17 -> 1047000 | K14: =K6*$Q$13*$Q$15*$Q$16*$Q$17 -> 1047000 | L14: =L6*$Q$13*$Q$15*$Q$16*$Q$17 -> 1047000 | M14: =M6*$Q$13*$Q$15*$Q$16*$Q$17 -> 1047000 | N14: =SUM(B14:M14) -> 12738500 | P14: Avg Survey Fee | Q14: 1800
A15: TOTAL | B15: =SUM(B13:B14) -> 27000 | C15: =SUM(C13:C14) -> 571900 | D15: =SUM(D13:D14) -> 1283400 | E15: =SUM(E13:E14) -> 1815900 | F15: =SUM(F13:F14) -> 385000 | G15: =SUM(G13:G14) -> 2130000 | H15: =SUM(H13:H14) -> 1506300 | I15: =SUM(I13:I14) -> 1101000 | ... M15: =SUM(M13:M14) -> 1101000 | N15: =SUM(B15:M15) -> 13224500 | P15: Survey Closing % | Q15: 0.8
P16: Avg Hrs per Go | Q16: 250
A17: COST OF SALES | P17: Avg Rate per Hr | Q17: 349
A18: Salaries | B18: =SUM(B5*$Q$5+B6*$Q$6+C7*$Q$7+B8*$Q$8+B9*$Q$9+B13*S5+B13*S6+B13*S7+B13*S8+B13*S9)*50% -> 17885 | C18: =C5*$Q$5+C6*$Q$6+D7*$Q$7+C8*$Q$8+C9*$Q$9+C13*T5+C13*T6+C13*T7+C13*T8+C13*T9 -> 22000 | D18: =D5*$Q$5+D6*$Q$6+E7*$Q$7+D8*$Q$8+D9*$Q$9+D13*U5+D13*U6+D13*U7+D13*U8+D13*U9 -> 32000 | E18: =E5*$Q$5+E6*$Q$6+F7*$Q$7+E8*$Q$8+E9*$Q$9+E13*V5+E13*V6+E13*V7+E13*V8+E13*V9 -> 32000 | F18: =F5*$Q$5+F6*$Q$6+G7*$Q$7+F8*$Q$8+F9*$Q$9+F13*W5+F13*W6+F13*W7+F13*W8+F13*W9 -> 12000 | G18: =G5*$Q$5+G6*$Q$6+H7*$Q$7+G8*$Q$8+G9*$Q$9+G13*X5+G13*X6+G13*X7+G13*X8+G13*X9 -> 32000 | H18: =H5*$Q$5+H6*$Q$6+I7*$Q$7+H8*$Q$8+H9*$Q$9+H13*Y5+H13*Y6+H13*Y7+H13*Y8+H13*Y9 -> 36000 | I18: =I5*$Q$5+I6*$Q$6+J7*$Q$7+I8*$Q$8+I9*$Q$9+I13*Z5+I13*Z6+I13*Z7+I13*Z8+I13*Z9 -> 24000 | J18: =J5*$Q$5+J6*$Q$6+K7*$Q$7+J8*$Q$8+J9*$Q$9+J13*AA5+J13*AA6+J13*AA7+J13*AA8+J13*AA9 -> 24000 | ... M18: =M5*$Q$5+M6*$Q$6+N7*$Q$7+M8*$Q$8+M9*$Q$9+M13*AD5+M13*AD6+M13*AD7+M13*AD8+M13*AD9 -> 24000 | N18: =SUM(B18:M18) -> 303885 | P18: Est. Sale Bonuses | Q18: =IF(Q13>5,(Q13-4)*300,0) -> 0
A19: Commission | B19: =IF(B5>0,$R$5*B$14,0) -> 0 | C19: =IF(C5>0,$R$5*C$14,0) -> 0 | D19: =IF(D5>0,$R$5*D$14,0) -> 0 | E19: =IF(E5>0,$R$5*E$14,0) -> 0 | F19: =IF(F5>0,$R$5*F$14,0) -> 0 | G19: =IF(G5>0,$R$5*G$14,0) -> 0 | H19: =IF(H5>0,$R$5*H$14,0) -> 0 | I19: =IF(I5>0,$R$5*I$14,0) -> 0 | ... M19: =IF(M5>0,$R$5*M$14,0) -> 0 | N19: =SUM(B19:M19) -> 0 | P19: Est. Srvy Fee Bonus | Q19: =IF($Q$14>995,($Q$14-995)*0.5*$Q$13,0) -> 2012.5
A20: Bonus | B20: =IF(B8>0,B8*$Q$18+B8*$Q$19,0) -> 6037.5 | C20: =IF(C8>0,C8*$Q$18+C8*$Q$19,0) -> 6037.5 | D20: =IF(D8>0,D8*$Q$18+D8*$Q$19,0) -> 8050 | E20: =IF(E8>0,E8*$Q$18+E8*$Q$19,0) -> 8050 | F20: =IF(F8>0,F8*$Q$18+F8*$Q$19,0) -> 8050 | G20: =IF(G8>0,G8*$Q$18+G8*$Q$19,0) -> 8050 | H20: =IF(H8>0,H8*$Q$18+H8*$Q$19,0) -> 12075 | I20: =IF(I8>0,I8*$Q$18+I8*$Q$19,0) -> 12075 | ... M20: =IF(M8>0,M8*$Q$18+M8*$Q$19,0) -> 12075 | N20: =SUM(B20:M20) -> 116725
A21: FE Sales (Survey Fee %) | B21: =SUM(B13)*$S10 -> 13770 | C21: =SUM(C13)*$S10 -> 6885 | D21: =SUM(D13)*$S10 -> 13770 | E21: =SUM(E13)*$S10 -> 18360 | F21: =SUM(F13)*$S10 -> 18360 | G21: =SUM(G13)*$S10 -> 18360 | H21: =SUM(H13)*$S10 -> 20655 | I21: =SUM(I13)*$S10 -> 27540 | ... M21: =SUM(M13)*$S10 -> 27540 | N21: =SUM(B21:M21) -> 247860
A22: Payroll Burden (7.65%) | B22: =(B18+B19+B20)*0.0765 -> 1830.0712 | C22: =(C18+C19+C20)*0.0765 -> 2144.8688 | D22: =(D18+D19+D20)*0.0765 -> 3063.825 | E22: =(E18+E19+E20)*0.0765 -> 3063.825 | F22: =(F18+F19+F20)*0.0765 -> 1533.825 | G22: =(G18+G19+G20)*0.0765 -> 3063.825 | H22: =(H18+H19+H20)*0.0765 -> 3677.7375 | I22: =(I18+I19+I20)*0.0765 -> 2759.7375 | ... M22: =(M18+M19+M20)*0.0765 -> 2759.7375 | N22: =SUM(B22:M22) -> 32176.665
A23: Benefit Pkg ($700/emp) | H23: =SUM(H10)*700 -> 9100 | I23: =SUM(I10)*700 -> 7000 | J23: =SUM(J10)*700 -> 7000 | K23: =SUM(K10)*700 -> 7000 | L23: =SUM(L10)*700 -> 7000 | M23: =SUM(M10)*700 -> 7000 | N23: =SUM(B23:M23) -> 44100
A24: 401 K (Matching 3%) | H24: =SUM(H18:H21)*3% -> 2061.9 | I24: =SUM(I18:I21)*3% -> 1908.45 | J24: =SUM(J18:J21)*3% -> 1908.45 | K24: =SUM(K18:K21)*3% -> 1908.45 | L24: =SUM(L18:L21)*3% -> 1908.45 | M24: =SUM(M18:M21)*3% -> 1908.45 | N24: =SUM(B24:M24) -> 11604.15
A25: Leads | B25: 800 | C25: 800 | E25: =SUM(500*E8) -> 2000 | F25: =SUM(500*F8) -> 2000 | G25: =SUM(500*G8) -> 2000 | H25: =SUM(500*H8) -> 3000 | I25: =SUM(500*I8) -> 3000 | J25: =SUM(500*J8) -> 3000 | K25: =SUM(500*K8) -> 3000 | L25: =SUM(500*L8) -> 3000 | M25: =SUM(500*M8) -> 3000 | N25: =SUM(B25:M25) -> 25600
A26: CRM | B26: =39*B10+39 -> 351 | C26: =39*C10 -> 312 | D26: =39*D10 -> 429 | E26: =39*E10 -> 429 | F26: =39*F10 -> 39 | G26: =39*G10 -> 429 | H26: =39*H10 -> 507 | I26: =39*I10 -> 390 | J26: =39*J10 -> 390 | ... M26: =39*M10 -> 390 | N26: =SUM(B26:M26) -> 4446
A27: Phone (Phone, Voicemail, Video) | B27: =SUM(28*B6)+(52*B7)+52 -> 216 | C27: =SUM(28*C6)+(52*C7)+52 -> 216 | D27: =SUM(28*D6)+(52*D7)+52 -> 272 | E27: =SUM(28*E6)+(52*E7)+52 -> 272 | F27: =SUM(28*F6)+(52*F7)+52 -> 132 | G27: =SUM(28*G6)+(52*G7)+52 -> 272 | H27: =SUM(28*H6)+(52*H7)+52 -> 272 | I27: =SUM(28*I6)+(52*I7)+52 -> 188 | ... M27: =SUM(28*M6)+(52*M7)+52 -> 188 | N27: =SUM(B27:M27) -> 2592
A28: Recruiting Ads | B28: 850 | C28: 0 | D28: 0 | E28: 0 | F28: 0 | G28: 850 | H28: 850 | I28: 850 | J28: 850 | K28: 850 | L28: 850 | M28: 850 | N28: =SUM(B28:M28) -> 6800
A29: TSR Field Training | B29: =SUM(B8*500) -> 1500 | C29: 1800 | D29: 1800 | E29: =SUM(E8*750) -> 3000 | F29: =SUM(F8*750) -> 3000 | G29: =SUM(G8*750) -> 3000 | H29: =SUM(H8*750) -> 4500 | I29: =SUM(I8*750) -> 4500 | J29: =SUM(J8*750) -> 4500 | K29: =SUM(K8*750) -> 4500 | L29: =SUM(L8*750) -> 4500 | M29: =SUM(M8*750) -> 4500 | N29: =SUM(B29:M29) -> 41100
A30: TSR Per Diem | B30: =500*B8 -> 1500 | C30: =500*C8 -> 1500 | D30: =500*D8 -> 2000 | E30: =500*E8 -> 2000 | F30: =500*F8 -> 2000 | G30: =500*G8 -> 2000 | H30: =500*H8 -> 3000 | I30: =500*I8 -> 3000 | ... M30: =500*M8 -> 3000 | N30: =SUM(B30:M30) -> 29000
A31: TSR Car/Fuel Allowance | B31: =600*B8 -> 1800 | C31: =600*C8 -> 1800 | D31: =600*D8 -> 2400 | E31: =600*E8 -> 2400 | F31: =600*F8 -> 2400 | G31: =600*G8 -> 2400 | H31: =600*H8 -> 3600 | I31: =600*I8 -> 3600 | ... M31: =600*M8 -> 3600 | N31: =SUM(B31:M31) -> 34800
A32: TSR Phone Allowance | B32: =25*B8 -> 75 | C32: 40 | D32: =25*D8 -> 100 | E32: =25*E8 -> 100 | F32: =25*F8 -> 100 | G32: =25*G8 -> 100 | H32: =25*H8 -> 150 | I32: =25*I8 -> 150 | J32: =25*J8 -> 150 | K32: =25*K8 -> 150 | ... M32: =25*M8 -> 150 | N32: =SUM(B32:M32) -> 1415
A33: TSR Hotel-2wk/mo travel | B33: =1800*B8 -> 5400 | C33: =1800*C8 -> 5400 | D33: =1800*D8 -> 7200 | E33: =1800*E8 -> 7200 | F33: =1800*F8 -> 7200 | G33: =1800*G8 -> 7200 | H33: =1800*H8 -> 10800 | I33: =1800*I8 -> 10800 | ... M33: =1800*M8 -> 10800 | N33: =SUM(B33:M33) -> 104400
A34: CC Fees (Square/In-Field) | B34: =SUM(B13*4%) -> 1080 | C34: =SUM(C13*4%) -> 540 | D34: =SUM(D13*4%) -> 1080 | E34: =SUM(E13*4%) -> 1440 | F34: =SUM(F13*4%) -> 1440 | G34: =SUM(G13*4%) -> 1440 | H34: =SUM(H13*4%) -> 1620 | I34: =SUM(I13*4%) -> 2160 | ... M34: =SUM(M13*4%) -> 2160 | N34: =SUM(B34:M34) -> 19440
A35: Printing
A36: Brochures (Leave Behinds) | B36: 500 | C36: =SUM(C8)*50 -> 150 | D36: =SUM(D8)*50 -> 200 | E36: =SUM(E8)*50 -> 200 | F36: =SUM(F8)*50 -> 200 | G36: =SUM(G8)*50 -> 200 | H36: =SUM(H8)*50 -> 300 | I36: =SUM(I8)*50 -> 300 | J36: =SUM(J8)*50 -> 300 | ... M36: =SUM(M8)*50 -> 300 | N36: =SUM(B36:M36) -> 3250
A37: Agreements (2-part) | B37: 500 | C37: 0 | D37: 0 | E37: 0 | F37: 0 | G37: 0 | H37: 500 | I37: 0 | J37: 0 | K37: 0 | N37: =SUM(B37:M37) -> 1000
A38: Business Cards: TSR | B38: =SUM(B8*50) -> 150 | C38: =SUM(C8*105) -> 315 | D38: 0 | E38: 0 | F38: 0 | G38: 0 | H38: =SUM(H8*105) -> 630 | I38: 0 | J38: 0 | K38: 0 | L38: 0 | M38: 0 | N38: =SUM(B38:M38) -> 1095
A39: Business Cards: RSM | B39: =SUM(B9*50) -> 0 | C39: =SUM(C9*50) -> 0 | D39: =SUM(D9*50) -> 0 | E39: =SUM(E9*50) -> 0 | F39: =SUM(F9*50) -> 50 | G39: =SUM(G9*50) -> 0 | H39: =SUM(H9*105) -> 0 | I39: 0 | J39: 0 | K39: 0 | L39: 0 | M39: 0 | N39: =SUM(B39:M39) -> 50
A40: Business Cards: CSO | B40: =SUM(B5*105) -> 0 | C40: 0 | D40: 0 | E40: 0 | F40: 0 | G40: 0 | H40: 0 | I40: 0 | J40: 0 | K40: 0 | L40: 0 | M40: 0 | N40: =SUM(B40:M40) -> 0
A41: TOTAL | B41: =SUM(B18:B34) -> 53094.571 | C41: =SUM(C18:C34) -> 49475.369 | D41: =SUM(D18:D34) -> 72164.825 | E41: =SUM(E18:E34) -> 80314.825 | F41: =SUM(F18:F34) -> 58254.825 | G41: =SUM(G18:G34) -> 81164.825 | H41: =SUM(H18:H34) -> 111868.64 | I41: =SUM(I18:I34) -> 103921.19 | ... M41: =SUM(M18:M34) -> 103921.19 | N41: =SUM(B41:M41) -> 1025943.8
A43: GROSS SALES PROFIT/(LOSS) | B43: =B15-B41 -> -26094.571 | C43: =C15-C41 -> 522424.63 | D43: =D15-D41 -> 1211235.2 | E43: =E15-E41 -> 1735585.2 | F43: =F15-F41 -> 326745.17 | G43: =G15-G41 -> 2048835.2 | H43: =H15-H41 -> 1394431.4 | I43: =I15-I41 -> 997078.81 | ... M43: =M15-M41 -> 997078.81 | N43: =SUM(B43:M43) -> 12198556
A46: CASH FLOW
A47: Balance Fwd | B47: 0 | C47: =B51 -> -42092.071 | D47: =C51 -> 141481.81 | E47: =D51 -> 592302.49 | F47: =E51 -> 1251966.9 | G47: =F51 -> 1350599.6 | H47: =G51 -> 2137409.8 | I47: =H51 -> 2639358.4 | J47: =I51 -> 2984094.7 | ... M47: =L51 -> 4018303.6
A48: Ending Balance | B48: =SUM(B43) -> -26094.571 | C48: =C43+C47 -> 480332.56 | D48: =D43+D47 -> 1352717 | E48: =E43+E47 -> 2327887.7 | F48: =F43+F47 -> 1578712.1 | G48: =G43+G47 -> 3399434.8 | H48: =H43+H47 -> 3531841.1 | I48: =I43+I47 -> 3636437.2 | J48: =J43+J47 -> 3981173.5 | ... M48: =M43+M47 -> 5015382.4
A49: (-) Estimated Company | B49: =SUM(B76:B80) -> 15997.5 | C49: =SUM(C76:C80) -> 338850.75 | D49: =SUM(D76:D80) -> 760414.5 | E49: =SUM(E76:E80) -> 1075920.8 | F49: =SUM(F76:F80) -> 228112.5 | G49: =SUM(G76:G80) -> 1262025 | H49: =SUM(H76:H80) -> 892482.75 | I49: =SUM(I76:I80) -> 652342.5 | ... M49: =SUM(M76:M80) -> 652342.5
A50: (-) Ownership Options % | B50: 0 | C50: 0 | D50: 0 | E50: 0 | F50: 0 | G50: 0 | H50: 0 | I50: 0 | J50: 0 | K50: 0 | L50: 0 | M50: 0
A51: (-) Estimated Retained | B51: =SUM(B48)-B49-B50 -> -42092.071 | C51: =SUM(C48)-C49-C50 -> 141481.81 | D51: =SUM(D48)-D49-D50 -> 592302.49 | E51: =SUM(E48)-E49-E50 -> 1251966.9 | F51: =SUM(F48)-F49-F50 -> 1350599.6 | G51: =SUM(G48)-G49-G50 -> 2137409.8 | H51: =SUM(H48)-H49-H50 -> 2639358.4 | I51: =SUM(I48)-I49-I50 -> 2984094.7 | ... M51: =SUM(M48)-M49-M50 -> 4363039.9 | Q51: 1st Year (Staggered) | R51: Benefits | S51: 401K Match | T51: Monthly Avg
P52: CSO | Q52: =SUM(N65)/1 -> 0 | R52: 4200 | S52: =SUM(N65*3%)/N5 -> #DIV/0! | T52: =SUM(Q52:S52)/12 -> #DIV/0!
P53: BC | Q53: =SUM(N66)/2.5 -> 140492.5 | R53: 4200 | S53: =SUM(N66*3%)/N6 -> 3512.3125 | T53: =SUM(Q53:S53)/12 -> 12350.401
P54: TMM | Q54: =SUM(N67)/1 -> 70113 | R54: 4200 | S54: =SUM(N67*3%)/N7 -> 2103.39 | T54: =SUM(Q54:S54)/12 -> 6368.0325
A55: Payroll As Percent | P55: TSR | Q55: =SUM(N68)/5 -> 169808 | R55: 4200 | S55: =SUM(N68*3%)/N8 -> 4245.2 | T55: =SUM(Q55:S55)/12 -> 14854.433
A56: CSO | B56: =SUM(B65)/B15 -> 0 | C56: =SUM(C65)/C15 -> 0 | D56: =SUM(D65)/D15 -> 0 | E56: =SUM(E65)/E15 -> 0 | F56: =SUM(F65)/F15 -> 0 | G56: =SUM(G65)/G15 -> 0 | H56: =SUM(H65)/H15 -> 0 | I56: =SUM(I65)/I15 -> 0 | ... M56: =SUM(M65)/M15 -> 0 | P56: RSM | Q56: =SUM(N69)/N9 -> #DIV/0! | R56: 4200 | S56: =SUM(N69*3%)/N9 -> #DIV/0! | T56: =SUM(Q56:S56)/12 -> #DIV/0!
A57: BC | B57: =SUM(B66)/B15 -> 0.59259259 | C57: =SUM(C66)/C15 -> 0.04018185 | D57: =SUM(D66)/D15 -> 0.030937354 | E57: =SUM(E66)/E15 -> 0.025468776 | F57: =SUM(F66)/F15 -> 0.021720779 | G57: =SUM(G66)/G15 -> 0.023556338 | H57: =SUM(H66)/H15 -> 0.028096993 | I57: =SUM(I66)/I15 -> 0.022786104 | ... M57: =SUM(M66)/M15 -> 0.022786104
A58: TMM | B58: =SUM(B67)/B$15 -> 0 | C58: =SUM(C67)/C$15 -> 0 | D58: =SUM(D67)/D$15 -> 0 | E58: =SUM(E67)/E$15 -> 0 | F58: =SUM(F67)/F$15 -> 0 | G58: =SUM(G67)/G$15 -> 0 | H58: =SUM(H67)/H$15 -> 0.01 | I58: =SUM(I67)/I$15 -> 0.01 | ... M58: =SUM(M67)/M$15 -> 0.01
A59: TSR | B59: =SUM(B68)/B$15 -> 0 | C59: =SUM(C68)/C$15 -> 0.061349886 | D59: =SUM(D68)/D$15 -> 0.055910862 | E59: =SUM(E68)/E$15 -> 0.053524974 | F59: =SUM(F68)/F$15 -> 0.10379221 | G59: =SUM(G68)/G$15 -> 0.051530516 | H59: =SUM(H68)/H$15 -> 0.060334595 | I59: =SUM(I68)/I$15 -> 0.07346049 | ... M59: =SUM(M68)/M$15 -> 0.07346049
A60: RSM | B60: =SUM(B69)/B$15 -> 0 | C60: =SUM(C69)/C$15 -> 0 | D60: =SUM(D69)/D$15 -> 0 | E60: =SUM(E69)/E$15 -> 0 | F60: =SUM(F69)/F$15 -> 0 | G60: =SUM(G69)/G$15 -> 0 | H60: =SUM(H69)/H$15 -> 0 | I60: =SUM(I69)/I$15 -> 0 | ... M60: =SUM(M69)/M$15 -> 0
A61: TOTAL | B61: =SUM(B56:B60) -> 0.59259259 | C61: =SUM(C56:C60) -> 0.10153174 | D61: =SUM(D56:D60) -> 0.086848216 | E61: =SUM(E56:E60) -> 0.07899375 | F61: =SUM(F56:F60) -> 0.12551299 | G61: =SUM(G56:G60) -> 0.075086854 | H61: =SUM(H56:H60) -> 0.098431587 | I61: =SUM(I56:I60) -> 0.10624659 | ... M61: =SUM(M56:M60) -> 0.10624659
A64: Headcount Earnings
A65: CSO | B65: =SUM(B5*$Q5)+(B14*$R5)+(B13*$S5) -> 0 | C65: =SUM(C5*$Q5)+(C14*$R5)+(C13*$S5) -> 0 | D65: =SUM(D5*$Q5)+(D14*$R5)+(D13*$S5) -> 0 | E65: =SUM(E5*$Q5)+(E14*$R5)+(E13*$S5) -> 0 | F65: =SUM(F5*$Q5)+(F14*$R5)+(F13*$S5) -> 0 | G65: =SUM(G5*$Q5)+(G14*$R5)+(G13*$S5) -> 0 | H65: =SUM(H5*$Q5)+(H14*$R5)+(H13*$S5) -> 0 | I65: =SUM(I5*$Q5)+(I14*$R5)+(I13*$S5) -> 0 | ... M65: =SUM(M5*$Q5)+(M14*$R5)+(M13*$S5) -> 0 | N65: =SUM(B65:M65) -> 0
A66: BC | B66: =SUM(B6*$Q6)+(B$13*$S6)+(B$14*$R6) -> 16000 | C66: =SUM(C6*$Q6)+(C$13*$S6)+(C$14*$R6) -> 22980 | D66: =SUM(D6*$Q6)+(D$13*$S6)+(D$14*$R6) -> 39705 | E66: =SUM(E6*$Q6)+(E$13*$S6)+(E$14*$R6) -> 46248.75 | F66: =SUM(F6*$Q6)+(F$13*$S6)+(F$14*$R6) -> 8362.5 | G66: =SUM(G6*$Q6)+(G$13*$S6)+(G$14*$R6) -> 50175 | H66: =SUM(H6*$Q6)+(H$13*$S6)+(H$14*$R6) -> 42322.5 | I66: =SUM(I6*$Q6)+(I$13*$S6)+(I$14*$R6) -> 25087.5 | ... M66: =SUM(M6*$Q6)+(M$13*$S6)+(M$14*$R6) -> 25087.5 | N66: =SUM(B66:M66) -> 351231.25
A67: TMM | C67: 0 | D67: 0 | E67: 0 | F67: 0 | G67: 0 | H67: =SUM(H7*$Q7)+(H$13*$S7)+(H$14*$R7) -> 15063 | I67: =SUM(I7*$Q7)+(I$13*$S7)+(I$14*$R7) -> 11010 | J67: =SUM(J7*$Q7)+(J$13*$S7)+(J$14*$R7) -> 11010 | K67: =SUM(K7*$Q7)+(K$13*$S7)+(K$14*$R7) -> 11010 | L67: =SUM(L7*$Q7)+(L$13*$S7)+(L$14*$R7) -> 11010 | M67: =SUM(M7*$Q7)+(M$13*$S7)+(M$14*$R7) -> 11010 | N67: =SUM(B67:M67) -> 70113
A68: TSR | B68: 0 | C68: =SUM(C8*$Q8)+(C$13*$S8)+(C$14*$R8) -> 35086 | D68: =SUM(D8*$Q8)+(D$13*$S8)+(D$14*$R8) -> 71756 | E68: =SUM(E8*$Q8)+(E$13*$S8)+(E$14*$R8) -> 97196 | F68: =SUM(F8*$Q8)+(F$13*$S8)+(F$14*$R8) -> 39960 | G68: =SUM(G8*$Q8)+(G$13*$S8)+(G$14*$R8) -> 109760 | H68: =SUM(H8*$Q8)+(H$13*$S8)+(H$14*$R8) -> 90882 | I68: =SUM(I8*$Q8)+(I$13*$S8)+(I$14*$R8) -> 80880 | J68: =SUM(J8*$Q8)+(J$13*$S8)+(J$14*$R8) -> 80880 | ... M68: =SUM(M8*$Q8)+(M$13*$S8)+(M$14*$R8) -> 80880 | N68: =SUM(B68:M68) -> 849040
A69: RSM | B69: 0 | C69: 0 | D69: 0 | E69: 0 | F69: 0 | G69: 0 | H69: =SUM(H9*$Q9)+(H$13*$S9)+(H$14*$R9) -> 0 | I69: =SUM(I9*$Q9)+(I$13*$S9)+(I$14*$R9) -> 0 | J69: =SUM(J9*$Q9)+(J$13*$S9)+(J$14*$R9) -> 0 | K69: =SUM(K9*$Q9)+(K$13*$S9)+(K$14*$R9) -> 0 | L69: =SUM(L9*$Q9)+(L$13*$S9)+(L$14*$R9) -> 0 | M69: =SUM(M9*$Q9)+(M$13*$S9)+(M$14*$R9) -> 0 | N69: =SUM(B69:M69) -> 0
A70: All Payroll Burden | B70: =SUM(B22:B24) -> 1830.0712 | C70: =SUM(C22:C24) -> 2144.8688 | D70: =SUM(D22:D24) -> 3063.825 | E70: =SUM(E22:E24) -> 3063.825 | F70: =SUM(F22:F24) -> 1533.825 | G70: =SUM(G22:G24) -> 3063.825 | H70: =SUM(H22:H24) -> 14839.637 | I70: =SUM(I22:I24) -> 11668.188 | ... M70: =SUM(M22:M24) -> 11668.188 | N70: =SUM(B70:M70) -> 87880.815
A71: TOTAL | B71: =SUM(B65:B70) -> 17830.071 | C71: =SUM(C65:C70) -> 60210.869 | D71: =SUM(D65:D70) -> 114524.82 | E71: =SUM(E65:E70) -> 146508.58 | F71: =SUM(F65:F70) -> 49856.325 | G71: =SUM(G65:G70) -> 162998.83 | H71: =SUM(H65:H70) -> 163107.14 | I71: =SUM(I65:I70) -> 128645.69 | ... M71: =SUM(M65:M70) -> 128645.69 | N71: =SUM(B71:M71) -> 1358265.1 | P71: =SUM(100%-O81) -> 0.32951302 | Q71: Net
P72: =SUM(N15)*P71 -> 4357644.9 | Q72: $ Net
A74: Budget Snapshot (Estimated Company) | O74: % | Q74: Ownership Options | R74: % | S74: $ Annual
A75: Sales (includes Travel 25%) | B75: =SUM( B18:B40) -> 54244.571 | C75: =SUM( C18:C40) -> 49940.369 | D75: =SUM( D18:D40) -> 72364.825 | E75: =SUM( E18:E40) -> 80514.825 | F75: =SUM( F18:F40) -> 58504.825 | G75: =SUM( G18:G40) -> 81364.825 | H75: =SUM( H18:H40) -> 113298.64 | I75: =SUM( I18:I40) -> 104221.19 | ... M75: =SUM( M18:M40) -> 104221.19 | N75: =SUM(B75:M75) -> 1031338.8 | O75: =SUM(N75)/N15 -> 0.07798698 | Q75: Total | R75: =SUM(P71) -> 0.32951302 | S75: =SUM(P72)*R75 -> 1435900.7
A76: Survey (includes Travel 25%) | B76: =SUM(B15)*25% -> 6750 | C76: =SUM(C15)*25% -> 142975 | D76: =SUM(D15)*25% -> 320850 | E76: =SUM(E15)*25% -> 453975 | F76: =SUM(F15)*25% -> 96250 | G76: =SUM(G15)*25% -> 532500 | H76: =SUM(H15)*25% -> 376575 | I76: =SUM(I15)*25% -> 275250 | ... N76: =SUM(N15)*25% -> 3306125 | O76: =SUM(N76)/N15 -> 0.25
A77: Consulting (25%) | B77: =SUM(B15)*25% -> 6750 | C77: =SUM(C15)*25% -> 142975 | D77: =SUM(D15)*25% -> 320850 | E77: =SUM(E15)*25% -> 453975 | F77: =SUM(F15)*25% -> 96250 | G77: =SUM(G15)*25% -> 532500 | H77: =SUM(H15)*25% -> 376575 | I77: =SUM(I15)*25% -> 275250 | ... M77: =SUM(M15)*25% -> 275250 | N77: =SUM(B77:M77) -> 3306125 | O77: =SUM(N77)/N15 -> 0.25 | Q77: Retained Belfield | R77: % | S77: $ Annual
A78: Admin/Operations (5.0%) | B78: =SUM(B15)*5% -> 1350 | C78: =SUM(C15)*5% -> 28595 | D78: =SUM(D15)*5% -> 64170 | E78: =SUM(E15)*5% -> 90795 | F78: =SUM(F15)*5% -> 19250 | G78: =SUM(G15)*5% -> 106500 | H78: =SUM(H15)*5% -> 75315 | I78: =SUM(I15)*5% -> 55050 | ... M78: =SUM(M15)*5% -> 55050 | N78: =SUM(B78:M78) -> 661225 | O78: =SUM(N78)/N15 -> 0.05 | Q78: Total | R78: =100%-R75 -> 0.67048698 | S78: =SUM(P72)*R78 -> 2921744.2
A79: President Salary (3%) | B79: =SUM(B15)*3% -> 810 | C79: =SUM(C15)*3% -> 17157 | D79: =SUM(D15)*3% -> 38502 | E79: =SUM(E15)*3% -> 54477 | F79: =SUM(F15)*3% -> 11550 | G79: =SUM(G15)*3% -> 63900 | H79: =SUM(H15)*3% -> 45189 | I79: =SUM(I15)*3% -> 33030 | ... M79: =SUM(M15)*3% -> 33030 | N79: =SUM(B79:M79) -> 396735 | O79: =SUM(N79)/N15 -> 0.03
A80: CFO Salary (1.25%) | B80: =SUM(B15)*1.25% -> 337.5 | C80: =SUM(C15)*1.25% -> 7148.75 | D80: =SUM(D15)*1.25% -> 16042.5 | E80: =SUM(E15)*1.25% -> 22698.75 | F80: =SUM(F15)*1.25% -> 4812.5 | G80: =SUM(G15)*1.25% -> 26625 | H80: =SUM(H15)*1.25% -> 18828.75 | I80: =SUM(I15)*1.25% -> 13762.5 | ... M80: =SUM(M15)*1.25% -> 13762.5 | N80: =SUM(B80:M80) -> 165306.25 | O80: =SUM(N80)/N15 -> 0.0125
A81: TOTAL | B81: =SUM(B75:B80) -> 70242.071 | C81: =SUM(C75:C80) -> 388791.12 | D81: =SUM(D75:D80) -> 832779.32 | E81: =SUM(E75:E80) -> 1156435.6 | F81: =SUM(F75:F80) -> 286617.33 | G81: =SUM(G75:G80) -> 1343389.8 | H81: =SUM(H75:H80) -> 1005781.4 | I81: =SUM(I75:I80) -> 756563.69 | ... O81: =SUM(O75:O80) -> 0.67048698

Sheet FE Sales YR 2
B1: FRONT END SALES FORECAST | P1: **Green boxes can be changed to modify forecast
B2: 45108 | C2: 45139 | D2: 45190 | E2: 45220 | F2: 45251 | G2: 45281 | H2: 45312 | I2: 45343 | J2: 45372 | K2: 45403 | L2: 45433 | M2: 45464
A3: Month # | B3: 1 | C3: 2 | D3: 3 | E3: 4 | F3: 5 | G3: 6 | H3: 7 | I3: 8 | J3: 9 | K3: 10 | L3: 11 | M3: 12 | N3: TOTAL | P3: SALES TEAM
A4: FE SALES HEAD COUNT | P4: Position | Q4: Salary | R4: Comm %* | S4: Survey Fee%
A5: CSO | B5: =SUM('FE Sales YR 1'!M5) -> 0 | C5: 1 | D5: 1 | E5: 1 | F5: 1 | G5: 1 | H5: 1 | I5: 1 | J5: 1 | K5: 1 | L5: 1 | M5: 1 | N5: =SUM(M5) -> 1 | P5: CSO | Q5: 0 | R5: 0.025 | S5: 0.025
A6: Business Coordinator | B6: =SUM('FE Sales YR 1'!M6) -> 3 | C6: 3 | D6: 3 | E6: 3 | F6: 3 | G6: 3 | H6: 6 | I6: 6 | J6: 6 | K6: 6 | L6: 6 | M6: 6 | N6: =SUM(M6) -> 6 | P6: BC | Q6: 2500 | R6: 0.0125 | S6: 0.0125
A7: Marketing Manager | B7: =SUM('FE Sales YR 1'!M7) -> 1 | C7: 1 | D7: 1 | E7: 1 | F7: 1 | G7: 1 | H7: 2 | I7: 2 | J7: 2 | K7: 2 | L7: 2 | M7: 2 | N7: =SUM(M7) -> 2 | P7: TMM | Q7: 0 | R7: 0.01 | S7: 0.01
A8: Regional Marketing Director | B8: =SUM('FE Sales YR 1'!M8) -> 6 | C8: 6 | D8: 6 | E8: 6 | F8: 6 | G8: 6 | H8: 12 | I8: 12 | J8: 12 | K8: 12 | L8: 12 | M8: 12 | N8: =SUM(M8) -> 12 | P8: TSR | Q8: 2500 | R8: 0.04 | S8: 0.5
A9: RSM | B9: =SUM('FE Sales YR 1'!M9) -> 0 | C9: 1 | D9: 1 | E9: 1 | F9: 1 | G9: 1 | H9: 2 | I9: 2 | J9: 2 | K9: 2 | L9: 2 | M9: 2 | N9: =SUM(M9) -> 2 | P9: RSM | Q9: 0 | R9: 0.0175 | S9: 0.05
A10: TOTAL | B10: =SUM(B5:B9) -> 10 | C10: =SUM(C5:C9) -> 12 | D10: =SUM(D5:D9) -> 12 | E10: =SUM(E5:E9) -> 12 | F10: =SUM(F5:F9) -> 12 | G10: =SUM(G5:G9) -> 12 | H10: =SUM(H5:H9) -> 23 | I10: =SUM(I5:I9) -> 23 | ... N10: =SUM(N5:N9) -> 23 | R10: =SUM(R5:R9) -> 0.105 | S10: =SUM(S5:S9) -> 0.5975
A12: REVENUE | P12: ASSUMPTIONS
A13: Survey Fees | B13: =B8*$Q$13*$Q$14 -> 29850 | C13: =C8*$Q$13*$Q$14 -> 29850 | D13: =D8*$Q$13*$Q$14 -> 29850 | E13: =E8*$Q$13*$Q$14 -> 29850 | F13: =F8*$Q$13*$Q$14 -> 29850 | G13: =G8*$Q$13*$Q$14 -> 29850 | H13: =H8*$Q$13*$Q$14*65% -> 38805 | I13: =I8*$Q$13*$Q$14*85% -> 50745 | J13: =J8*$Q$13*$Q$14 -> 59700 | K13: =K8*$Q$13*$Q$14 -> 59700 | L13: =L8*$Q$13*$Q$14 -> 59700 | M13: =M8*$Q$13*$Q$14 -> 59700 | N13: =SUM(B13:M13) -> 507450 | P13: # Mo Sales per TSR | Q13: 5
A14: Cash Collect | B14: =B8*$Q$13*$Q$15*$Q$16*$Q$17 -> 708000 | C14: =C8*$Q$13*$Q$15*$Q$16*$Q$17 -> 708000 | D14: =D8*$Q$13*$Q$15*$Q$16*$Q$17 -> 708000 | E14: =E8*$Q$13*$Q$15*$Q$16*$Q$17 -> 708000 | F14: =F8*$Q$13*$Q$15*$Q$16*$Q$17 -> 708000 | G14: =G8*$Q$13*$Q$15*$Q$16*$Q$17 -> 708000 | H14: =H8*$Q$13*$Q$15*$Q$16*$Q$17*65% -> 920400 | I14: =I8*$Q$13*$Q$15*$Q$16*$Q$17*85% -> 1203600 | J14: =J8*$Q$13*$Q$15*$Q$16*$Q$17 -> 1416000 | K14: =K8*$Q$13*$Q$15*$Q$16*$Q$17 -> 1416000 | L14: =L8*$Q$13*$Q$15*$Q$16*$Q$17 -> 1416000 | M14: =M8*$Q$13*$Q$15*$Q$16*$Q$17 -> 1416000 | N14: =SUM(B14:M14) -> 12036000 | P14: Avg Survey Fee | Q14: 995
A15: TOTAL | B15: =SUM(B13:B14) -> 737850 | C15: =SUM(C13:C14) -> 737850 | D15: =SUM(D13:D14) -> 737850 | E15: =SUM(E13:E14) -> 737850 | F15: =SUM(F13:F14) -> 737850 | G15: =SUM(G13:G14) -> 737850 | H15: =SUM(H13:H14) -> 959205 | I15: =SUM(I13:I14) -> 1254345 | ... M15: =SUM(M13:M14) -> 1475700 | N15: =SUM(B15:M15) -> 12543450 | P15: Survey Closing % | Q15: 0.5
P16: Avg Hrs per Go | Q16: 160
A17: COST OF SALES | P17: Avg Rate per Hr | Q17: 295
A18: Salaries | B18: =B5*$Q$5+B6*$Q$6+C7*$Q$7+B8*$Q$8+B9*$Q$9+B13*S5+B13*S6+B13*S7+B13*S8+B13*S9 -> 40335.375 | C18: =C5*$Q$5+C6*$Q$6+D7*$Q$7+C8*$Q$8+C9*$Q$9+C13*T5+C13*T6+C13*T7+C13*T8+C13*T9 -> 22500 | D18: =D5*$Q$5+D6*$Q$6+E7*$Q$7+D8*$Q$8+D9*$Q$9+D13*U5+D13*U6+D13*U7+D13*U8+D13*U9 -> 22500 | E18: =E5*$Q$5+E6*$Q$6+F7*$Q$7+E8*$Q$8+E9*$Q$9+E13*V5+E13*V6+E13*V7+E13*V8+E13*V9 -> 22500 | F18: =F5*$Q$5+F6*$Q$6+G7*$Q$7+F8*$Q$8+F9*$Q$9+F13*W5+F13*W6+F13*W7+F13*W8+F13*W9 -> 22500 | G18: =G5*$Q$5+G6*$Q$6+H7*$Q$7+G8*$Q$8+G9*$Q$9+G13*X5+G13*X6+G13*X7+G13*X8+G13*X9 -> 22500 | H18: =H5*$Q$5+H6*$Q$6+I7*$Q$7+H8*$Q$8+H9*$Q$9+H13*Y5+H13*Y6+H13*Y7+H13*Y8+H13*Y9 -> 45000 | I18: =I5*$Q$5+I6*$Q$6+J7*$Q$7+I8*$Q$8+I9*$Q$9+I13*Z5+I13*Z6+I13*Z7+I13*Z8+I13*Z9 -> 45000 | ... M18: =M5*$Q$5+M6*$Q$6+N7*$Q$7+M8*$Q$8+M9*$Q$9+M13*AD5+M13*AD6+M13*AD7+M13*AD8+M13*AD9 -> 45000 | N18: =SUM(B18:M18) -> 422835.38 | P18: Est. Sale Bonuses | Q18: =IF(Q13>5,(Q13-4)*300,0) -> 0
A19: Commission | B19: =IF(B5>0,$R$5*B$14,0) -> 0 | C19: =IF(C5>0,$R$5*C$14,0) -> 17700 | D19: =IF(D5>0,$R$5*D$14,0) -> 17700 | E19: =IF(E5>0,$R$5*E$14,0) -> 17700 | F19: =IF(F5>0,$R$5*F$14,0) -> 17700 | G19: =IF(G5>0,$R$5*G$14,0) -> 17700 | H19: =IF(H5>0,$R$5*H$14,0) -> 23010 | I19: =IF(I5>0,$R$5*I$14,0) -> 30090 | ... M19: =IF(M5>0,$R$5*M$14,0) -> 35400 | N19: =SUM(B19:M19) -> 283200 | P19: Est. Srvy Fee Bonus | Q19: =IF($Q$14>995,($Q$14-995)*0.5*$Q$13,0) -> 0
A20: Bonus | B20: =IF(B8>0,B8*$Q$18+B8*$Q$19,0) -> 0 | C20: =IF(C8>0,C8*$Q$18+C8*$Q$19,0) -> 0 | D20: =IF(D8>0,D8*$Q$18+D8*$Q$19,0) -> 0 | E20: =IF(E8>0,E8*$Q$18+E8*$Q$19,0) -> 0 | F20: =IF(F8>0,F8*$Q$18+F8*$Q$19,0) -> 0 | G20: =IF(G8>0,G8*$Q$18+G8*$Q$19,0) -> 0 | H20: =IF(H8>0,H8*$Q$18+H8*$Q$19,0) -> 0 | I20: =IF(I8>0,I8*$Q$18+I8*$Q$19,0) -> 0 | ... M20: =IF(M8>0,M8*$Q$18+M8*$Q$19,0) -> 0 | N20: =SUM(B20:M20) -> 0
A21: FE Sales (Survey Fee %) | B21: =SUM(B13)*$S10 -> 17835.375 | C21: =SUM(C13)*$S10 -> 17835.375 | D21: =SUM(D13)*$S10 -> 17835.375 | E21: =SUM(E13)*$S10 -> 17835.375 | F21: =SUM(F13)*$S10 -> 17835.375 | G21: =SUM(G13)*$S10 -> 17835.375 | H21: =SUM(H13)*$S10 -> 23185.988 | I21: =SUM(I13)*$S10 -> 30320.138 | ... M21: =SUM(M13)*$S10 -> 35670.75 | N21: =SUM(B21:M21) -> 303201.38
A22: Payroll Burden (7.65%) | B22: =(B18+B19+B20)*0.0765 -> 3085.6562 | C22: =(C18+C19+C20)*0.0765 -> 3075.3 | D22: =(D18+D19+D20)*0.0765 -> 3075.3 | E22: =(E18+E19+E20)*0.0765 -> 3075.3 | F22: =(F18+F19+F20)*0.0765 -> 3075.3 | G22: =(G18+G19+G20)*0.0765 -> 3075.3 | H22: =(H18+H19+H20)*0.0765 -> 5202.765 | I22: =(I18+I19+I20)*0.0765 -> 5744.385 | ... M22: =(M18+M19+M20)*0.0765 -> 6150.6 | N22: =SUM(B22:M22) -> 54011.706
A23: Benefit Pkg ($700/emp) | B23: =SUM(B10)*700 -> 7000 | C23: =SUM(C10)*700 -> 8400 | D23: =SUM(D10)*700 -> 8400 | E23: =SUM(E10)*700 -> 8400 | F23: =SUM(F10)*700 -> 8400 | G23: =SUM(G10)*700 -> 8400 | H23: =SUM(H10)*700 -> 16100 | I23: =SUM(I10)*700 -> 16100 | ... M23: =SUM(M10)*700 -> 16100 | N23: =SUM(B23:M23) -> 145600
A24: 401 K (Matching 3%) | B24: =SUM(B18:B21)*3% -> 1745.1225 | C24: =SUM(C18:C21)*3% -> 1741.0612 | D24: =SUM(D18:D21)*3% -> 1741.0612 | E24: =SUM(E18:E21)*3% -> 1741.0612 | F24: =SUM(F18:F21)*3% -> 1741.0612 | G24: =SUM(G18:G21)*3% -> 1741.0612 | H24: =SUM(H18:H21)*3% -> 2735.8796 | I24: =SUM(I18:I21)*3% -> 3162.3041 | ... M24: =SUM(M18:M21)*3% -> 3482.1225 | N24: =SUM(B24:M24) -> 30277.103
A25: Leads | B25: 800 | C25: 800 | D25: =SUM(500*D8) -> 3000 | E25: =SUM(500*E8) -> 3000 | F25: =SUM(500*F8) -> 3000 | G25: =SUM(500*G8) -> 3000 | H25: =SUM(500*H8) -> 6000 | I25: =SUM(500*I8) -> 6000 | J25: =SUM(500*J8) -> 6000 | K25: =SUM(500*K8) -> 6000 | ... M25: =SUM(500*M8) -> 6000 | N25: =SUM(B25:M25) -> 49600
A26: CRM | B26: =39*B10+39 -> 429 | C26: =39*C10 -> 468 | D26: =39*D10 -> 468 | E26: =39*E10 -> 468 | F26: =39*F10 -> 468 | G26: =39*G10 -> 468 | H26: =39*H10 -> 897 | I26: =39*I10 -> 897 | J26: =39*J10 -> 897 | ... M26: =39*M10 -> 897 | N26: =SUM(B26:M26) -> 8151
A27: Phone (Phone, Voicemail, Video) | B27: =SUM(28*B6)+(52*B7)+52 -> 188 | C27: =SUM(28*C6)+(52*C7)+52 -> 188 | D27: =SUM(28*D6)+(52*D7)+52 -> 188 | E27: =SUM(28*E6)+(52*E7)+52 -> 188 | F27: =SUM(28*F6)+(52*F7)+52 -> 188 | G27: =SUM(28*G6)+(52*G7)+52 -> 188 | H27: =SUM(28*H6)+(52*H7)+52 -> 324 | I27: =SUM(28*I6)+(52*I7)+52 -> 324 | ... M27: =SUM(28*M6)+(52*M7)+52 -> 324 | N27: =SUM(B27:M27) -> 3072
A28: Recruiting Ads | B28: 850 | C28: 850 | D28: 850 | E28: 850 | F28: 850 | G28: 850 | H28: 850 | I28: 850 | J28: 850 | K28: 850 | L28: 850 | M28: 850 | N28: =SUM(B28:M28) -> 10200
A29: TSR Field Training | B29: =SUM(B8*500) -> 3000 | C29: 1800 | D29: 1800 | E29: =SUM(E8*750) -> 4500 | F29: =SUM(F8*750) -> 4500 | G29: =SUM(G8*750) -> 4500 | H29: =SUM(H8*750) -> 9000 | I29: =SUM(I8*750) -> 9000 | J29: =SUM(J8*750) -> 9000 | K29: =SUM(K8*750) -> 9000 | L29: =SUM(L8*750) -> 9000 | M29: =SUM(M8*750) -> 9000 | N29: =SUM(B29:M29) -> 74100
A30: TSR Per Diem | B30: =500*B8 -> 3000 | C30: =500*C8 -> 3000 | D30: =500*D8 -> 3000 | E30: =500*E8 -> 3000 | F30: =500*F8 -> 3000 | G30: =500*G8 -> 3000 | H30: =500*H8 -> 6000 | I30: =500*I8 -> 6000 | ... M30: =500*M8 -> 6000 | N30: =SUM(B30:M30) -> 54000
A31: TSR Car/Fuel Allowance | B31: =600*B8 -> 3600 | C31: =600*C8 -> 3600 | D31: =600*D8 -> 3600 | E31: =600*E8 -> 3600 | F31: =600*F8 -> 3600 | G31: =600*G8 -> 3600 | H31: =600*H8 -> 7200 | I31: =600*I8 -> 7200 | ... M31: =600*M8 -> 7200 | N31: =SUM(B31:M31) -> 64800
A32: TSR Phone Allowance | B32: =25*B8 -> 150 | C32: =25*C8 -> 150 | D32: =25*D8 -> 150 | E32: =25*E8 -> 150 | F32: =25*F8 -> 150 | G32: =25*G8 -> 150 | H32: =25*H8 -> 300 | I32: =25*I8 -> 300 | ... M32: =25*M8 -> 300 | N32: =SUM(B32:M32) -> 2700
A33: TSR Hotel-2wk/mo travel | B33: =1800*B8 -> 10800 | C33: =1800*C8 -> 10800 | D33: =1800*D8 -> 10800 | E33: =1800*E8 -> 10800 | F33: =1800*F8 -> 10800 | G33: =1800*G8 -> 10800 | H33: =1800*H8 -> 21600 | I33: =1800*I8 -> 21600 | ... M33: =1800*M8 -> 21600 | N33: =SUM(B33:M33) -> 194400
A34: CC Fees (Square/In-Field) | B34: =SUM(B13*4%) -> 1194 | C34: =SUM(C13*4%) -> 1194 | D34: =SUM(D13*4%) -> 1194 | E34: =SUM(E13*4%) -> 1194 | F34: =SUM(F13*4%) -> 1194 | G34: =SUM(G13*4%) -> 1194 | H34: =SUM(H13*4%) -> 1552.2 | I34: =SUM(I13*4%) -> 2029.8 | ... M34: =SUM(M13*4%) -> 2388 | N34: =SUM(B34:M34) -> 20298
A35: Printing
A36: Brochures (Leave Behinds) | B36: 500 | C36: =SUM(C8)*50 -> 300 | D36: =SUM(D8)*50 -> 300 | E36: =SUM(E8)*50 -> 300 | F36: =SUM(F8)*50 -> 300 | G36: =SUM(G8)*50 -> 300 | H36: =SUM(H8)*50 -> 600 | I36: =SUM(I8)*50 -> 600 | J36: =SUM(J8)*50 -> 600 | ... M36: =SUM(M8)*50 -> 600 | N36: =SUM(B36:M36) -> 5600
A37: Agreements (2-part) | C37: 0 | D37: 0 | E37: 0 | F37: 0 | G37: 0 | H37: 750 | I37: 0 | J37: 0 | K37: 0 | N37: =SUM(B37:M37) -> 750
A38: Business Cards: TSR | C38: =SUM(C8*105) -> 630 | D38: 0 | E38: 0 | F38: 0 | G38: 0 | H38: =SUM(H8*105) -> 1260 | I38: 0 | J38: 0 | K38: 0 | L38: 0 | M38: 0 | N38: =SUM(B38:M38) -> 1890
A39: Business Cards: RSM | B39: =SUM(B9*56) -> 0 | H39: =SUM(H9*105) -> 210 | I39: 0 | J39: 0 | K39: 0 | L39: 0 | M39: 0 | N39: =SUM(B39:M39) -> 210
A40: Business Cards: CSO | B40: =SUM(B5*105) -> 0 | C40: 0 | D40: 0 | E40: 0 | F40: 0 | G40: 0 | H40: 0 | I40: 0 | J40: 0 | K40: 0 | L40: 0 | M40: 0 | N40: =SUM(B40:M40) -> 0
A41: TOTAL | B41: =SUM(B18:B34) -> 94012.529 | C41: =SUM(C18:C34) -> 94101.736 | D41: =SUM(D18:D34) -> 96301.736 | E41: =SUM(E18:E34) -> 99001.736 | F41: =SUM(F18:F34) -> 99001.736 | G41: =SUM(G18:G34) -> 99001.736 | H41: =SUM(H18:H34) -> 168957.83 | I41: =SUM(I18:I34) -> 184617.63 | ... M41: =SUM(M18:M34) -> 196362.47 | N41: =SUM(B41:M41) -> 1720446.6
A43: GROSS SALES PROFIT/(LOSS) | B43: =B15-B41 -> 643837.47 | C43: =C15-C41 -> 643748.26 | D43: =D15-D41 -> 641548.26 | E43: =E15-E41 -> 638848.26 | F43: =F15-F41 -> 638848.26 | G43: =G15-G41 -> 638848.26 | H43: =H15-H41 -> 790247.17 | I43: =I15-I41 -> 1069727.4 | ... N43: =N15-N41 -> 10823003
A46: CASH FLOW
A47: Balance Fwd | B47: =SUM('FE Sales YR 1'!M51) -> 4363039.9 | C47: =B51 -> 4570074.4 | D47: =C51 -> 4777019.7 | E47: =D51 -> 4981764.9 | F47: =E51 -> 5183810.2 | G47: =F51 -> 5385855.5 | H47: =G51 -> 5587900.7 | I47: =H51 -> 5810304 | J47: =I51 -> 6137466.3 | ... M47: =L51 -> 7354660.8
A48: Ending Balance | B48: =B43+B47 -> 5006877.4 | C48: =C43+C47 -> 5213822.7 | D48: =D43+D47 -> 5418567.9 | E48: =E43+E47 -> 5620613.2 | F48: =F43+F47 -> 5822658.5 | G48: =G43+G47 -> 6024703.7 | H48: =H43+H47 -> 6378147.9 | I48: =I43+I47 -> 6880031.4 | ... M48: =M43+M47 -> 8633998.4
A49: (-) Estimated Company | B49: =SUM(B76:B80) -> 436803 | C49: =SUM(C76:C80) -> 436803 | D49: =SUM(D76:D80) -> 436803 | E49: =SUM(E76:E80) -> 436803 | F49: =SUM(F76:F80) -> 436803 | G49: =SUM(G76:G80) -> 436803 | H49: =SUM(H76:H80) -> 567843.9 | I49: =SUM(I76:I80) -> 742565.1 | ... L49: =SUM(L76:L80) -> 873606 | M49: =SUM(M75:M79) -> 1052868.5
A50: (-) Ownership Options % | B50: 0 | C50: 0 | D50: 0 | E50: =SUM('FE Sales YR 1'!S75) -> 1435900.7 | F50: 0 | G50: 0 | H50: 0 | I50: 0 | J50: 0 | K50: 0 | L50: 0 | M50: 0 | Q50: 12 Month Avg | R50: Benefits | S50: 401K Match | T50: Monthly Avg
A51: (-) Estimated Retained | B51: =SUM(B48)-B49 -> 4570074.4 | C51: =SUM(C48)-C49 -> 4777019.7 | D51: =SUM(D48)-D49 -> 4981764.9 | E51: =SUM(E48)-E49 -> 5183810.2 | F51: =SUM(F48)-F49 -> 5385855.5 | G51: =SUM(G48)-G49 -> 5587900.7 | H51: =SUM(H48)-H49 -> 5810304 | I51: =SUM(I48)-I49 -> 6137466.3 | ... M51: =SUM(M48)-M49 -> 7581129.9 | P51: CSO | Q51: =SUM(N65)/1 -> 313586.25 | R51: 8400 | S51: =SUM(N65*3%)/N5 -> 9407.5875 | T51: =SUM(Q51:S51)/12 -> 27616.153
P52: BC | Q52: =SUM(N66)/4.5 -> 64842.917 | R52: 8400 | S52: =SUM(N66*3%)/N6 -> 1458.9656 | T52: =SUM(Q52:S52)/12 -> 6225.1569
P53: TMM | Q53: =SUM(N67)/1.5 -> 83623 | R53: 8400 | S53: =SUM(N67*3%)/N7 -> 1881.5175 | T53: =SUM(Q53:S53)/12 -> 7825.3765
P54: TSR | Q54: =SUM(N68)/9.5 -> 105806.84 | R54: 8400 | S54: =SUM(N68*3%)/N8 -> 2512.9125 | T54: =SUM(Q54:S54)/12 -> 9726.6462
A55: Payroll As Percent | P55: RSM | Q55: =SUM(N69)/1.5 -> 157335 | R55: 8400 | S55: =SUM(N69*3%)/N9 -> 3540.0375 | T55: =SUM(Q55:S55)/12 -> 14106.253
A56: CSO | B56: =SUM(B65)/B15 -> 0.025 | C56: =SUM(C65)/C15 -> 0.025 | D56: =SUM(D65)/D15 -> 0.025 | E56: =SUM(E65)/E15 -> 0.025 | F56: =SUM(F65)/F15 -> 0.025 | G56: =SUM(G65)/G15 -> 0.025 | H56: =SUM(H65)/H15 -> 0.025 | I56: =SUM(I65)/I15 -> 0.025 | ... M56: =SUM(M65)/M15 -> 0.025
A57: BC | B57: =SUM(B66)/B15 -> 0.022664668 | C57: =SUM(C66)/C15 -> 0.022664668 | D57: =SUM(D66)/D15 -> 0.022664668 | E57: =SUM(E66)/E15 -> 0.022664668 | F57: =SUM(F66)/F15 -> 0.022664668 | G57: =SUM(G66)/G15 -> 0.022664668 | H57: =SUM(H66)/H15 -> 0.02813795 | I57: =SUM(I66)/I15 -> 0.024458432 | ... M57: =SUM(M66)/M15 -> 0.022664668
A58: TMM | B58: =SUM(B67)/B$15 -> 0.01 | C58: =SUM(C67)/C$15 -> 0.01 | D58: =SUM(D67)/D$15 -> 0.01 | E58: =SUM(E67)/E$15 -> 0.01 | F58: =SUM(F67)/F$15 -> 0.01 | G58: =SUM(G67)/G$15 -> 0.01 | H58: =SUM(H67)/H$15 -> 0.01 | I58: =SUM(I67)/I$15 -> 0.01 | ... M58: =SUM(M67)/M$15 -> 0.01
A59: TSR | B59: =SUM(B68)/B$15 -> 0.078938809 | C59: =SUM(C68)/C$15 -> 0.078938809 | D59: =SUM(D68)/D$15 -> 0.078938809 | E59: =SUM(E68)/E$15 -> 0.078938809 | F59: =SUM(F68)/F$15 -> 0.078938809 | G59: =SUM(G68)/G$15 -> 0.078938809 | H59: =SUM(H68)/H$15 -> 0.089885374 | I59: =SUM(I68)/I$15 -> 0.082526338 | ... M59: =SUM(M68)/M$15 -> 0.078938809
A60: RSM | B60: =SUM(B69)/B$15 -> 0.0188148 | C60: =SUM(C69)/C$15 -> 0.0188148 | D60: =SUM(D69)/D$15 -> 0.0188148 | E60: =SUM(E69)/E$15 -> 0.0188148 | F60: =SUM(F69)/F$15 -> 0.0188148 | G60: =SUM(G69)/G$15 -> 0.0188148 | H60: =SUM(H69)/H$15 -> 0.0188148 | I60: =SUM(I69)/I$15 -> 0.0188148 | ... M60: =SUM(M69)/M$15 -> 0.0188148
A61: TOTAL | B61: =SUM(B56:B60) -> 0.15541828 | C61: =SUM(C56:C60) -> 0.15541828 | D61: =SUM(D56:D60) -> 0.15541828 | E61: =SUM(E56:E60) -> 0.15541828 | F61: =SUM(F56:F60) -> 0.15541828 | G61: =SUM(G56:G60) -> 0.15541828 | H61: =SUM(H56:H60) -> 0.17183812 | I61: =SUM(I56:I60) -> 0.16079957 | ... M61: =SUM(M56:M60) -> 0.15541828
A64: Headcount Earnings
A65: CSO | B65: =SUM(B5*$Q5)+(B14*$R5)+(B13*$S5) -> 18446.25 | C65: =SUM(C5*$Q5)+(C14*$R5)+(C13*$S5) -> 18446.25 | D65: =SUM(D5*$Q5)+(D14*$R5)+(D13*$S5) -> 18446.25 | E65: =SUM(E5*$Q5)+(E14*$R5)+(E13*$S5) -> 18446.25 | F65: =SUM(F5*$Q5)+(F14*$R5)+(F13*$S5) -> 18446.25 | G65: =SUM(G5*$Q5)+(G14*$R5)+(G13*$S5) -> 18446.25 | H65: =SUM(H5*$Q5)+(H14*$R5)+(H13*$S5) -> 23980.125 | I65: =SUM(I5*$Q5)+(I14*$R5)+(I13*$S5) -> 31358.625 | ... M65: =SUM(M5*$Q5)+(M14*$R5)+(M13*$S5) -> 36892.5 | N65: =SUM(B65:M65) -> 313586.25
A66: BC | B66: =SUM(B6*$Q6)+(B$13*$S6)+(B$14*$R6) -> 16723.125 | C66: =SUM(C6*$Q6)+(C$13*$S6)+(C$14*$R6) -> 16723.125 | D66: =SUM(D6*$Q6)+(D$13*$S6)+(D$14*$R6) -> 16723.125 | E66: =SUM(E6*$Q6)+(E$13*$S6)+(E$14*$R6) -> 16723.125 | F66: =SUM(F6*$Q6)+(F$13*$S6)+(F$14*$R6) -> 16723.125 | G66: =SUM(G6*$Q6)+(G$13*$S6)+(G$14*$R6) -> 16723.125 | H66: =SUM(H6*$Q6)+(H$13*$S6)+(H$14*$R6) -> 26990.062 | I66: =SUM(I6*$Q6)+(I$13*$S6)+(I$14*$R6) -> 30679.312 | ... M66: =SUM(M6*$Q6)+(M$13*$S6)+(M$14*$R6) -> 33446.25 | N66: =SUM(B66:M66) -> 291793.12
A67: TMM | B67: =SUM(B7*$Q7)+(B$13*$S7)+(B$14*$R7) -> 7378.5 | C67: =SUM(C7*$Q7)+(C$13*$S7)+(C$14*$R7) -> 7378.5 | D67: =SUM(D7*$Q7)+(D$13*$S7)+(D$14*$R7) -> 7378.5 | E67: =SUM(E7*$Q7)+(E$13*$S7)+(E$14*$R7) -> 7378.5 | F67: =SUM(F7*$Q7)+(F$13*$S7)+(F$14*$R7) -> 7378.5 | G67: =SUM(G7*$Q7)+(G$13*$S7)+(G$14*$R7) -> 7378.5 | H67: =SUM(H7*$Q7)+(H$13*$S7)+(H$14*$R7) -> 9592.05 | I67: =SUM(I7*$Q7)+(I$13*$S7)+(I$14*$R7) -> 12543.45 | ... M67: =SUM(M7*$Q7)+(M$13*$S7)+(M$14*$R7) -> 14757 | N67: =SUM(B67:M67) -> 125434.5
A68: TSR | B68: =SUM(B8*$Q8)+(B$13*$S8)+(B$14*$R8) -> 58245 | C68: =SUM(C8*$Q8)+(C$13*$S8)+(C$14*$R8) -> 58245 | D68: =SUM(D8*$Q8)+(D$13*$S8)+(D$14*$R8) -> 58245 | E68: =SUM(E8*$Q8)+(E$13*$S8)+(E$14*$R8) -> 58245 | F68: =SUM(F8*$Q8)+(F$13*$S8)+(F$14*$R8) -> 58245 | G68: =SUM(G8*$Q8)+(G$13*$S8)+(G$14*$R8) -> 58245 | H68: =SUM(H8*$Q8)+(H$13*$S8)+(H$14*$R8) -> 86218.5 | I68: =SUM(I8*$Q8)+(I$13*$S8)+(I$14*$R8) -> 103516.5 | ... M68: =SUM(M8*$Q8)+(M$13*$S8)+(M$14*$R8) -> 116490 | N68: =SUM(B68:M68) -> 1005165
A69: RSM | B69: =SUM(B9*$Q9)+(B$13*$S9)+(B$14*$R9) -> 13882.5 | C69: =SUM(C9*$Q9)+(C$13*$S9)+(C$14*$R9) -> 13882.5 | D69: =SUM(D9*$Q9)+(D$13*$S9)+(D$14*$R9) -> 13882.5 | E69: =SUM(E9*$Q9)+(E$13*$S9)+(E$14*$R9) -> 13882.5 | F69: =SUM(F9*$Q9)+(F$13*$S9)+(F$14*$R9) -> 13882.5 | G69: =SUM(G9*$Q9)+(G$13*$S9)+(G$14*$R9) -> 13882.5 | H69: =SUM(H9*$Q9)+(H$13*$S9)+(H$14*$R9) -> 18047.25 | I69: =SUM(I9*$Q9)+(I$13*$S9)+(I$14*$R9) -> 23600.25 | ... M69: =SUM(M9*$Q9)+(M$13*$S9)+(M$14*$R9) -> 27765 | N69: =SUM(B69:M69) -> 236002.5
A70: All Payroll Burden | B70: =SUM(B22:B24) -> 11830.779 | C70: =SUM(C22:C24) -> 13216.361 | D70: =SUM(D22:D24) -> 13216.361 | E70: =SUM(E22:E24) -> 13216.361 | F70: =SUM(F22:F24) -> 13216.361 | G70: =SUM(G22:G24) -> 13216.361 | H70: =SUM(H22:H24) -> 24038.645 | I70: =SUM(I22:I24) -> 25006.689 | ... M70: =SUM(M22:M24) -> 25732.722 | N70: =SUM(B70:M70) -> 229888.81
A71: TOTAL | B71: =SUM(B65:B70) -> 126506.15 | C71: =SUM(C65:C70) -> 127891.74 | D71: =SUM(D65:D70) -> 127891.74 | E71: =SUM(E65:E70) -> 127891.74 | F71: =SUM(F65:F70) -> 127891.74 | G71: =SUM(G65:G70) -> 127891.74 | H71: =SUM(H65:H70) -> 188866.63 | I71: =SUM(I65:I70) -> 226704.83 | ... N71: =SUM(N65:N70) -> 2201870.2 | P71: =SUM(100%-O81) -> 0.27017307 | Q71: Net
P72: =SUM(N15)*P71 -> 3388902.4 | Q72: $ Net
A74: Budget Snapshot (Estimated Company) | O74: % | Q74: Ownership Options | R74: % | S74: $ Annual
A75: Sales (includes Travel 25%) | B75: =SUM(B18:B40) -> 94512.529 | C75: =SUM(C18:C40) -> 95031.736 | D75: =SUM(D18:D40) -> 96601.736 | E75: =SUM(E18:E40) -> 99301.736 | F75: =SUM(F18:F40) -> 99301.736 | G75: =SUM(G18:G40) -> 99301.736 | H75: =SUM(H18:H40) -> 171777.83 | I75: =SUM(I18:I40) -> 185217.63 | ... M75: =SUM(M18:M40) -> 196962.47 | N75: =SUM(B75:M75) -> 1728896.6 | O75: =SUM(N75)/N15 -> 0.13783262 | Q75: Total | R75: =SUM(P71) -> 0.27017307 | S75: =SUM(P72)*R75 -> 915590.19
A76: Survey (includes Travel 25%) | B76: =SUM(B15)*25% -> 184462.5 | C76: =SUM(C15)*25% -> 184462.5 | D76: =SUM(D15)*25% -> 184462.5 | E76: =SUM(E15)*25% -> 184462.5 | F76: =SUM(F15)*25% -> 184462.5 | G76: =SUM(G15)*25% -> 184462.5 | H76: =SUM(H15)*25% -> 239801.25 | I76: =SUM(I15)*25% -> 313586.25 | ... M76: =SUM(M15)*25% -> 368925 | N76: =SUM(B76:M76) -> 3135862.5 | O76: =SUM(N76)/N15 -> 0.25
A77: Consulting (25%) | B77: =SUM(B15)*25% -> 184462.5 | C77: =SUM(C15)*25% -> 184462.5 | D77: =SUM(D15)*25% -> 184462.5 | E77: =SUM(E15)*25% -> 184462.5 | F77: =SUM(F15)*25% -> 184462.5 | G77: =SUM(G15)*25% -> 184462.5 | H77: =SUM(H15)*25% -> 239801.25 | I77: =SUM(I15)*25% -> 313586.25 | ... M77: =SUM(M15)*25% -> 368925 | N77: =SUM(B77:M77) -> 3135862.5 | O77: =SUM(N77)/N15 -> 0.25 | Q77: Retained Belfield | R77: % | S77: $ Annual
A78: Admin/Operations (4.75%) | B78: =SUM(B15)*4.75% -> 35047.875 | C78: =SUM(C15)*4.75% -> 35047.875 | D78: =SUM(D15)*4.75% -> 35047.875 | E78: =SUM(E15)*4.75% -> 35047.875 | F78: =SUM(F15)*4.75% -> 35047.875 | G78: =SUM(G15)*4.75% -> 35047.875 | H78: =SUM(H15)*4.75% -> 45562.238 | I78: =SUM(I15)*4.75% -> 59581.387 | ... M78: =SUM(M15)*4.75% -> 70095.75 | N78: =SUM(B78:M78) -> 595813.88 | O78: =SUM(N78)/N15 -> 0.0475 | Q78: Total | R78: =100%-R75 -> 0.72982693 | S78: =SUM(P72)*R78 -> 2473312.3
A79: President Salary (3.25%) | B79: =SUM(B15)*3.25% -> 23980.125 | C79: =SUM(C15)*3.25% -> 23980.125 | D79: =SUM(D15)*3.25% -> 23980.125 | E79: =SUM(E15)*3.25% -> 23980.125 | F79: =SUM(F15)*3.25% -> 23980.125 | G79: =SUM(G15)*3.25% -> 23980.125 | H79: =SUM(H15)*3.25% -> 31174.163 | I79: =SUM(I15)*3.25% -> 40766.213 | ... M79: =SUM(M15)*3.25% -> 47960.25 | N79: =SUM(B79:M79) -> 407662.12 | O79: =SUM(N79)/N15 -> 0.0325
A80: CFO Salary (1.25%) | B80: =SUM(B14)*1.25% -> 8850 | C80: =SUM(C14)*1.25% -> 8850 | D80: =SUM(D14)*1.25% -> 8850 | E80: =SUM(E14)*1.25% -> 8850 | F80: =SUM(F14)*1.25% -> 8850 | G80: =SUM(G14)*1.25% -> 8850 | H80: =SUM(H14)*1.25% -> 11505 | I80: =SUM(I14)*1.25% -> 15045 | ... M80: =SUM(M14)*1.25% -> 17700 | N80: =SUM(B80:M80) -> 150450 | O80: =SUM(N80)/N15 -> 0.011994308
A81: TOTAL | B81: =SUM(B75:B80) -> 531315.53 | C81: =SUM(C75:C80) -> 531834.74 | D81: =SUM(D75:D80) -> 533404.74 | E81: =SUM(E75:E80) -> 536104.74 | F81: =SUM(F75:F80) -> 536104.74 | G81: =SUM(G75:G80) -> 536104.74 | H81: =SUM(H75:H80) -> 739621.73 | I81: =SUM(I75:I80) -> 927782.73 | ... O81: =SUM(O75:O80) -> 0.72982693

Sheet FE Sales YR 3
B1: FRONT END SALES FORECAST | P1: **Green boxes can be changed to modify forecast
B2: 45798 | C2: 45829 | D2: 7/21/2025 08/21/2025 08/21/252 | E2: 45921 | F2: 45951 | G2: 45982 | H2: 46012 | I2: 45678 | J2: 44702 | K2: 44825 | L2: 44855 | M2: 44886
A3: Month # | B3: 1 | C3: 2 | D3: 3 | E3: 4 | F3: 5 | G3: 6 | H3: 7 | I3: 8 | J3: 9 | K3: 10 | L3: 11 | M3: 12 | N3: TOTAL | P3: SALES TEAM
A4: FE SALES HEAD COUNT | P4: Position | Q4: Salary | R4: Comm %* | S4: Survey Fee%
A5: CSO | B5: 0 | C5: 0 | D5: 0 | E5: 0 | F5: 0 | G5: 0 | H5: 0 | I5: 0 | J5: 0 | K5: 0 | L5: 0 | M5: 0 | N5: 0 | P5: CSO | Q5: 0 | R5: 0.02 | S5: 0.02
A6: BC | B6: 8 | C6: 8 | D6: 8 | E6: 8 | F6: 8 | G6: 8 | H6: 9 | I6: 9 | J6: 9 | K6: 9 | L6: 9 | M6: 9 | N6: =SUM(M6) -> 9 | P6: BC | Q6: 2500 | R6: 0.0125 | S6: 0.0125
A7: TMM | B7: =SUM('FE Sales YR 2'!N7) -> 2 | C7: 2 | D7: 2 | E7: 2 | F7: 2 | G7: 2 | H7: 3 | I7: 3 | J7: 3 | K7: 3 | L7: 3 | M7: 3 | N7: =SUM(M7) -> 3 | P7: TMM | Q7: 0 | R7: 0.01 | S7: 0.01
A8: TSR | B8: 6 | C8: 6 | D8: 6 | E8: 6 | F8: 6 | G8: 6 | H8: 6 | I8: 6 | J8: 6 | K8: 6 | L8: 6 | M8: 6 | N8: =SUM(M8) -> 6 | P8: TSR | Q8: 2000 | R8: 0.04 | S8: 0.5
A9: RSM | B9: 0 | C9: 0 | D9: 0 | E9: 0 | F9: 0 | G9: 0 | H9: 0 | I9: 0 | J9: 0 | K9: 0 | L9: 0 | M9: 0 | N9: =SUM(M9) -> 0 | P9: RSM | Q9: 0 | R9: 0.02 | S9: 0.05
A10: TOTAL | B10: =SUM(B5:B9) -> 16 | C10: =SUM(C5:C9) -> 16 | D10: =SUM(D5:D9) -> 16 | E10: =SUM(E5:E9) -> 16 | F10: =SUM(F5:F9) -> 16 | G10: =SUM(G5:G9) -> 16 | H10: =SUM(H5:H9) -> 18 | I10: =SUM(I5:I9) -> 18 | ... N10: =SUM(N5:N9) -> 18 | R10: =SUM(R5:R9) -> 0.1025 | S10: =SUM(S5:S9) -> 0.5925
A12: REVENUE | P12: ASSUMPTIONS
A13: Survey Fees | B13: =B8*$Q$13*$Q$14 -> 29850 | C13: =C8*$Q$13*$Q$14 -> 29850 | D13: =D8*$Q$13*$Q$14 -> 29850 | E13: =E8*$Q$13*$Q$14 -> 29850 | F13: =F8*$Q$13*$Q$14 -> 29850 | G13: =G8*$Q$13*$Q$14 -> 29850 | H13: =H8*$Q$13*$Q$14*60% -> 17910 | I13: =I8*$Q$13*$Q$14*85% -> 25372.5 | J13: =J8*$Q$13*$Q$14 -> 29850 | K13: =K8*$Q$13*$Q$14 -> 29850 | L13: =L8*$Q$13*$Q$14 -> 29850 | M13: =M8*$Q$13*$Q$14 -> 29850 | N13: =SUM(B13:M13) -> 341782.5 | P13: # Mo Sales per TSR | Q13: 5
A14: Cash Collect | B14: =B8*$Q$13*$Q$15*$Q$16*$Q$17 -> 708000 | C14: =C8*$Q$13*$Q$15*$Q$16*$Q$17 -> 708000 | D14: =D8*$Q$13*$Q$15*$Q$16*$Q$17 -> 708000 | E14: =E8*$Q$13*$Q$15*$Q$16*$Q$17 -> 708000 | F14: =F8*$Q$13*$Q$15*$Q$16*$Q$17 -> 708000 | G14: =G8*$Q$13*$Q$15*$Q$16*$Q$17 -> 708000 | H14: =H8*$Q$13*$Q$15*$Q$16*$Q$17*60% -> 424800 | I14: =I8*$Q$13*$Q$15*$Q$16*$Q$17*85% -> 601800 | J14: =J8*$Q$13*$Q$15*$Q$16*$Q$17 -> 708000 | K14: =K8*$Q$13*$Q$15*$Q$16*$Q$17 -> 708000 | L14: =L8*$Q$13*$Q$15*$Q$16*$Q$17 -> 708000 | M14: =M8*$Q$13*$Q$15*$Q$16*$Q$17 -> 708000 | N14: =SUM(B14:M14) -> 8106600 | P14: Avg Survey Fee | Q14: 995
A15: TOTAL | B15: =SUM(B13:B14) -> 737850 | C15: =SUM(C13:C14) -> 737850 | D15: =SUM(D13:D14) -> 737850 | E15: =SUM(E13:E14) -> 737850 | F15: =SUM(F13:F14) -> 737850 | G15: =SUM(G13:G14) -> 737850 | H15: =SUM(H13:H14) -> 442710 | I15: =SUM(I13:I14) -> 627172.5 | ... N15: =SUM(N13:N14) -> 8448382.5 | P15: Survey Closing % | Q15: 0.5
P16: Avg Hrs per Go | Q16: 160
A17: COST OF SALES | P17: Avg Rate per Hr | Q17: 295
A18: Salaries | B18: =B5*$Q$5+B6*$Q$6+C7*$Q$7+B8*$Q$8+B9*$Q$9+B13*S5+B13*S6+B13*S7+B13*S8+B13*S9 -> 49686.125 | C18: =C5*$Q$5+C6*$Q$6+D7*$Q$7+C8*$Q$8+C9*$Q$9+C13*T5+C13*T6+C13*T7+C13*T8+C13*T9 -> 32000 | D18: =D5*$Q$5+D6*$Q$6+E7*$Q$7+D8*$Q$8+D9*$Q$9+D13*U5+D13*U6+D13*U7+D13*U8+D13*U9 -> 32000 | E18: =E5*$Q$5+E6*$Q$6+F7*$Q$7+E8*$Q$8+E9*$Q$9+E13*V5+E13*V6+E13*V7+E13*V8+E13*V9 -> 32000 | F18: =F5*$Q$5+F6*$Q$6+G7*$Q$7+F8*$Q$8+F9*$Q$9+F13*W5+F13*W6+F13*W7+F13*W8+F13*W9 -> 32000 | G18: =G5*$Q$5+G6*$Q$6+H7*$Q$7+G8*$Q$8+G9*$Q$9+G13*X5+G13*X6+G13*X7+G13*X8+G13*X9 -> 32000 | H18: =H5*$Q$5+H6*$Q$6+I7*$Q$7+H8*$Q$8+H9*$Q$9+H13*Y5+H13*Y6+H13*Y7+H13*Y8+H13*Y9 -> 34500 | I18: =I5*$Q$5+I6*$Q$6+J7*$Q$7+I8*$Q$8+I9*$Q$9+I13*Z5+I13*Z6+I13*Z7+I13*Z8+I13*Z9 -> 34500 | ... M18: =M5*$Q$5+M6*$Q$6+N7*$Q$7+M8*$Q$8+M9*$Q$9+M13*AD5+M13*AD6+M13*AD7+M13*AD8+M13*AD9 -> 34500 | N18: =SUM(B18:M18) -> 416686.12 | P18: Est. Sale Bonuses | Q18: =IF(Q13>5,(Q13-4)*300,0) -> 0
A19: Commission | B19: =IF(B5>0,$R$5*B$14,0) -> 0 | C19: =IF(C5>0,$R$5*C$14,0) -> 0 | D19: =IF(D5>0,$R$5*D$14,0) -> 0 | E19: =IF(E5>0,$R$5*E$14,0) -> 0 | F19: =IF(F5>0,$R$5*F$14,0) -> 0 | G19: =IF(G5>0,$R$5*G$14,0) -> 0 | H19: =IF(H5>0,$R$5*H$14,0) -> 0 | I19: =IF(I5>0,$R$5*I$14,0) -> 0 | ... M19: =IF(M5>0,$R$5*M$14,0) -> 0 | N19: =SUM(B19:M19) -> 0 | P19: Est. Srvy Fee Bonus | Q19: =IF($Q$14>995,($Q$14-995)*0.5*$Q$13,0) -> 0
A20: Bonus | B20: =IF(B8>0,B8*$Q$18+B8*$Q$19,0) -> 0 | C20: =IF(C8>0,C8*$Q$18+C8*$Q$19,0) -> 0 | D20: =IF(D8>0,D8*$Q$18+D8*$Q$19,0) -> 0 | E20: =IF(E8>0,E8*$Q$18+E8*$Q$19,0) -> 0 | F20: =IF(F8>0,F8*$Q$18+F8*$Q$19,0) -> 0 | G20: =IF(G8>0,G8*$Q$18+G8*$Q$19,0) -> 0 | H20: =IF(H8>0,H8*$Q$18+H8*$Q$19,0) -> 0 | I20: =IF(I8>0,I8*$Q$18+I8*$Q$19,0) -> 0 | ... M20: =IF(M8>0,M8*$Q$18+M8*$Q$19,0) -> 0 | N20: =SUM(B20:M20) -> 0
A21: FE Sales (Survey Fee %) | B21: =SUM(B13)*$S10 -> 17686.125 | C21: =SUM(C13)*$S10 -> 17686.125 | D21: =SUM(D13)*$S10 -> 17686.125 | E21: =SUM(E13)*$S10 -> 17686.125 | F21: =SUM(F13)*$S10 -> 17686.125 | G21: =SUM(G13)*$S10 -> 17686.125 | H21: =SUM(H13)*$S10 -> 10611.675 | I21: =SUM(I13)*$S10 -> 15033.206 | ... M21: =SUM(M13)*$S10 -> 17686.125 | N21: =SUM(B21:M21) -> 202506.13
A22: Payroll Burden (7.65%) | B22: =(B18+B19+B20)*0.0765 -> 3800.9886 | C22: =(C18+C19+C20)*0.0765 -> 2448 | D22: =(D18+D19+D20)*0.0765 -> 2448 | E22: =(E18+E19+E20)*0.0765 -> 2448 | F22: =(F18+F19+F20)*0.0765 -> 2448 | G22: =(G18+G19+G20)*0.0765 -> 2448 | H22: =(H18+H19+H20)*0.0765 -> 2639.25 | I22: =(I18+I19+I20)*0.0765 -> 2639.25 | ... M22: =(M18+M19+M20)*0.0765 -> 2639.25 | N22: =SUM(B22:M22) -> 31876.489
A23: Benefit Pkg ($700/emp) | B23: =SUM(B10)*700 -> 11200 | C23: =SUM(C10)*700 -> 11200 | D23: =SUM(D10)*700 -> 11200 | E23: =SUM(E10)*700 -> 11200 | F23: =SUM(F10)*700 -> 11200 | G23: =SUM(G10)*700 -> 11200 | H23: =SUM(H10)*700 -> 12600 | I23: =SUM(I10)*700 -> 12600 | ... M23: =SUM(M10)*700 -> 12600 | N23: =SUM(B23:M23) -> 142800
A24: 401 K (Matching 3%) | B24: =SUM(B18:B21)*3% -> 2021.1675 | C24: =SUM(C18:C21)*3% -> 1490.5838 | D24: =SUM(D18:D21)*3% -> 1490.5838 | E24: =SUM(E18:E21)*3% -> 1490.5838 | F24: =SUM(F18:F21)*3% -> 1490.5838 | G24: =SUM(G18:G21)*3% -> 1490.5838 | H24: =SUM(H18:H21)*3% -> 1353.3502 | I24: =SUM(I18:I21)*3% -> 1485.9962 | ... M24: =SUM(M18:M21)*3% -> 1565.5838 | N24: =SUM(B24:M24) -> 18575.768
A25: Leads | B25: 800 | C25: 800 | D25: =SUM(500*D8) -> 3000 | E25: =SUM(500*E8) -> 3000 | F25: =SUM(500*F8) -> 3000 | G25: =SUM(500*G8) -> 3000 | H25: =SUM(500*H8) -> 3000 | I25: =SUM(500*I8) -> 3000 | J25: =SUM(500*J8) -> 3000 | K25: =SUM(500*K8) -> 3000 | ... M25: =SUM(500*M8) -> 3000 | N25: =SUM(B25:M25) -> 31600
A26: CRM | B26: =39*B10+39 -> 663 | C26: =39*C10 -> 624 | D26: =39*D10 -> 624 | E26: =39*E10 -> 624 | F26: =39*F10 -> 624 | G26: =39*G10 -> 624 | H26: =39*H10 -> 702 | I26: =39*I10 -> 702 | J26: =39*J10 -> 702 | ... M26: =39*M10 -> 702 | N26: =SUM(B26:M26) -> 7995
A27: Phone (Phone, Voicemail, Video) | B27: =SUM(28*B6)+(52*B7)+52 -> 380 | C27: =SUM(28*C6)+(52*C7)+52 -> 380 | D27: =SUM(28*D6)+(52*D7)+52 -> 380 | E27: =SUM(28*E6)+(52*E7)+52 -> 380 | F27: =SUM(28*F6)+(52*F7)+52 -> 380 | G27: =SUM(28*G6)+(52*G7)+52 -> 380 | H27: =SUM(28*H6)+(52*H7)+52 -> 460 | I27: =SUM(28*I6)+(52*I7)+52 -> 460 | ... M27: =SUM(28*M6)+(52*M7)+52 -> 460 | N27: =SUM(B27:M27) -> 5040
A28: Recruiting Ads | B28: 850 | C28: 850 | D28: 850 | E28: 850 | F28: 850 | G28: 850 | H28: 850 | I28: 850 | J28: 850 | K28: 850 | L28: 850 | M28: 850 | N28: =SUM(B28:M28) -> 10200
A29: TSR Field Training | B29: =SUM(B8*500) -> 3000 | C29: 1800 | D29: 1800 | E29: =SUM(E8*750) -> 4500 | F29: =SUM(F8*750) -> 4500 | G29: =SUM(G8*750) -> 4500 | H29: =SUM(H8*750) -> 4500 | I29: =SUM(I8*750) -> 4500 | J29: =SUM(J8*750) -> 4500 | K29: =SUM(K8*750) -> 4500 | L29: =SUM(L8*750) -> 4500 | M29: =SUM(M8*750) -> 4500 | N29: =SUM(B29:M29) -> 47100
A30: TSR Per Diem | B30: =500*B8 -> 3000 | C30: =500*C8 -> 3000 | D30: =500*D8 -> 3000 | E30: =500*E8 -> 3000 | F30: =500*F8 -> 3000 | G30: =500*G8 -> 3000 | H30: =500*H8 -> 3000 | I30: =500*I8 -> 3000 | ... M30: =500*M8 -> 3000 | N30: =SUM(B30:M30) -> 36000
A31: TSR Car/Fuel Allowance | B31: =600*B8 -> 3600 | C31: =600*C8 -> 3600 | D31: =600*D8 -> 3600 | E31: =600*E8 -> 3600 | F31: =600*F8 -> 3600 | G31: =600*G8 -> 3600 | H31: =600*H8 -> 3600 | I31: =600*I8 -> 3600 | ... M31: =600*M8 -> 3600 | N31: =SUM(B31:M31) -> 43200
A32: TSR Phone Allowance | B32: =25*B8 -> 150 | C32: =25*C8 -> 150 | D32: =25*D8 -> 150 | E32: =25*E8 -> 150 | F32: =25*F8 -> 150 | G32: =25*G8 -> 150 | H32: =25*H8 -> 150 | I32: =25*I8 -> 150 | ... M32: =25*M8 -> 150 | N32: =SUM(B32:M32) -> 1800
A33: TSR Hotel-2wk/mo travel | B33: =1800*B8 -> 10800 | C33: =1800*C8 -> 10800 | D33: =1800*D8 -> 10800 | E33: =1800*E8 -> 10800 | F33: =1800*F8 -> 10800 | G33: =1800*G8 -> 10800 | H33: =1800*H8 -> 10800 | I33: =1800*I8 -> 10800 | ... M33: =1800*M8 -> 10800 | N33: =SUM(B33:M33) -> 129600
A34: CC Fees (Square/In-Field) | B34: =SUM(B13*4%) -> 1194 | C34: =SUM(C13*4%) -> 1194 | D34: =SUM(D13*4%) -> 1194 | E34: =SUM(E13*4%) -> 1194 | F34: =SUM(F13*4%) -> 1194 | G34: =SUM(G13*4%) -> 1194 | H34: =SUM(H13*4%) -> 716.4 | I34: =SUM(I13*4%) -> 1014.9 | ... M34: =SUM(M13*4%) -> 1194 | N34: =SUM(B34:M34) -> 13671.3
A35: Printing
A36: Brochures (Leave Behinds) | B36: 500 | C36: =SUM(C8)*50 -> 300 | D36: =SUM(D8)*50 -> 300 | E36: =SUM(E8)*50 -> 300 | F36: =SUM(F8)*50 -> 300 | G36: =SUM(G8)*50 -> 300 | H36: =SUM(H8)*50 -> 300 | I36: =SUM(I8)*50 -> 300 | J36: =SUM(J8)*50 -> 300 | ... M36: =SUM(M8)*50 -> 300 | N36: =SUM(B36:M36) -> 3800
A37: Agreements (2-part) | C37: 0 | D37: 0 | E37: 0 | F37: 0 | G37: 0 | H37: 750 | I37: 0 | J37: 0 | K37: 0 | N37: =SUM(B37:M37) -> 750
A38: Business Cards: TSR | C38: =SUM(C8*105) -> 630 | D38: 0 | E38: 0 | F38: 0 | G38: 0 | H38: =SUM(H8*105) -> 630 | I38: 0 | J38: 0 | K38: 0 | L38: 0 | M38: 0 | N38: =SUM(B38:M38) -> 1260
A39: Business Cards: RSM | B39: =SUM(B9*56) -> 0 | H39: =SUM(H9*105) -> 0 | I39: 0 | J39: 0 | K39: 0 | L39: 0 | M39: 0 | N39: =SUM(B39:M39) -> 0
A40: Business Cards: CSO | B40: =SUM(B5*105) -> 0 | C40: 0 | D40: 0 | E40: 0 | F40: 0 | G40: 0 | H40: 0 | I40: 0 | J40: 0 | K40: 0 | L40: 0 | M40: 0 | N40: =SUM(B40:M40) -> 0
A41: TOTAL | B41: =SUM(B18:B34) -> 108831.41 | C41: =SUM(C18:C34) -> 88022.709 | D41: =SUM(D18:D34) -> 90222.709 | E41: =SUM(E18:E34) -> 92922.709 | F41: =SUM(F18:F34) -> 92922.709 | G41: =SUM(G18:G34) -> 92922.709 | H41: =SUM(H18:H34) -> 89482.675 | I41: =SUM(I18:I34) -> 94335.352 | ... M41: =SUM(M18:M34) -> 97246.959 | N41: =SUM(B41:M41) -> 1138650.8
A43: GROSS SALES PROFIT/(LOSS) | B43: =B15-B41 -> 629018.59 | C43: =C15-C41 -> 649827.29 | D43: =D15-D41 -> 647627.29 | E43: =E15-E41 -> 644927.29 | F43: =F15-F41 -> 644927.29 | G43: =G15-G41 -> 644927.29 | H43: =H15-H41 -> 353227.32 | I43: =I15-I41 -> 532837.15 | ... N43: =N15-N41 -> 7309731.7
A46: CASH FLOW
A47: Balance Fwd | B47: =SUM('FE Sales YR 2'!M51) -> 7581129.9 | C47: =B51 -> 7778506.2 | D47: =C51 -> 7996691.3 | E47: =D51 -> 8212676.3 | F47: =E51 -> 7510371.2 | G47: =F51 -> 7723656.2 | H47: =G51 -> 7936941.3 | I47: =H51 -> 8031183.2 | J47: =I51 -> 8197124.5 | ... M47: =L51 -> 8824006.8
A48: Ending Balance | B48: =B43+B47 -> 8210148.5 | C48: =C43+C47 -> 8428333.5 | D48: =D43+D47 -> 8644318.6 | E48: =E43+E47 -> 8857603.6 | F48: =F43+F47 -> 8155298.5 | G48: =G43+G47 -> 8368583.5 | H48: =H43+H47 -> 8290168.6 | I48: =I43+I47 -> 8564020.4 | ... L48: =L43+L47 -> 9255649.1 | M48: =M15+M47 -> 9561856.8
A49: (-) Estimated Company | B49: =SUM(B76:B80) -> 431642.25 | C49: =SUM(C76:C80) -> 431642.25 | D49: =SUM(D76:D80) -> 431642.25 | E49: =SUM(E76:E80) -> 431642.25 | F49: =SUM(F76:F80) -> 431642.25 | G49: =SUM(G76:G80) -> 431642.25 | H49: =SUM(H76:H80) -> 258985.35 | I49: =SUM(I76:I80) -> 366895.91 | ... M49: =SUM(M76:M80) -> 431642.25
A50: (-) Ownership Options % | B50: 0 | C50: 0 | D50: 0 | E50: =SUM('FE Sales YR 2'!S75) -> 915590.19 | F50: 0 | G50: 0 | H50: 0 | I50: 0 | J50: 0 | K50: 0 | L50: 0 | M50: 0 | Q50: 12 Month Avg | R50: Benefits | S50: 401K Match | T50: Monthly Avg
A51: (-) Estimated Retained | B51: =SUM(B48)-B49-B50 -> 7778506.2 | C51: =SUM(C48)-C49-C50 -> 7996691.3 | D51: =SUM(D48)-D49-D50 -> 8212676.3 | E51: =SUM(E48)-E49-E50 -> 7510371.2 | F51: =SUM(F48)-F49-F50 -> 7723656.2 | G51: =SUM(G48)-G49-G50 -> 7936941.3 | H51: =SUM(H48)-H49-H50 -> 8031183.2 | I51: =SUM(I48)-I49-I50 -> 8197124.5 | ... M51: =SUM(M48)-M49-M50 -> 9130214.6 | P51: CSO | Q51: =SUM(N65)/N5 -> #DIV/0! | R51: 8400 | S51: =SUM(N65*3%)/N5 -> #DIV/0! | T51: =SUM(Q51:S51)/12 -> #DIV/0!
P52: BC | Q52: =SUM(N66)/7.5 -> 48080.637 | R52: 8400 | S52: =SUM(N66*3%)/N6 -> 1202.0159 | T52: =SUM(Q52:S52)/12 -> 4806.8878
P53: TMM | Q53: =SUM(N67)/2.5 -> 33793.53 | R53: 8400 | S53: =SUM(N67*3%)/N7 -> 844.83825 | T53: =SUM(Q53:S53)/12 -> 3586.5307
P54: TSR | Q54: =SUM(N68)/15 -> 42610.35 | R54: 8400 | S54: =SUM(N68*3%)/N8 -> 3195.7762 | T54: =SUM(Q54:S54)/12 -> 4517.1772
A55: Payroll As Percent | P55: RSM | Q55: =SUM(N69)/2.5 -> 71688.45 | R55: 8400 | S55: =SUM(N69*3%)/N9 -> #DIV/0! | T55: =SUM(Q55:S55)/12 -> #DIV/0!
A56: CSO | B56: =SUM(B65)/B15 -> 0.02 | C56: =SUM(C65)/C15 -> 0.02 | D56: =SUM(D65)/D15 -> 0.02 | E56: =SUM(E65)/E15 -> 0.02 | F56: =SUM(F65)/F15 -> 0.02 | G56: =SUM(G65)/G15 -> 0.02 | H56: =SUM(H65)/H15 -> 0.02 | I56: =SUM(I65)/I15 -> 0.02 | ... M56: =SUM(M65)/M15 -> 0.02
A57: BC | B57: =SUM(B66)/B15 -> 0.03960578 | C57: =SUM(C66)/C15 -> 0.03960578 | D57: =SUM(D66)/D15 -> 0.03960578 | E57: =SUM(E66)/E15 -> 0.03960578 | F57: =SUM(F66)/F15 -> 0.03960578 | G57: =SUM(G66)/G15 -> 0.03960578 | H57: =SUM(H66)/H15 -> 0.063323338 | I57: =SUM(I66)/I15 -> 0.048375297 | ... M57: =SUM(M66)/M15 -> 0.042994003
A58: TMM | B58: =SUM(B67)/B$15 -> 0.01 | C58: =SUM(C67)/C$15 -> 0.01 | D58: =SUM(D67)/D$15 -> 0.01 | E58: =SUM(E67)/E$15 -> 0.01 | F58: =SUM(F67)/F$15 -> 0.01 | G58: =SUM(G67)/G$15 -> 0.01 | H58: =SUM(H67)/H$15 -> 0.01 | I58: =SUM(I67)/I$15 -> 0.01 | ... M58: =SUM(M67)/M$15 -> 0.01
A59: TSR | B59: =SUM(B68)/B$15 -> 0.074872942 | C59: =SUM(C68)/C$15 -> 0.074872942 | D59: =SUM(D68)/D$15 -> 0.074872942 | E59: =SUM(E68)/E$15 -> 0.074872942 | F59: =SUM(F68)/F$15 -> 0.074872942 | G59: =SUM(G68)/G$15 -> 0.074872942 | H59: =SUM(H68)/H$15 -> 0.085715254 | I59: =SUM(I68)/I$15 -> 0.077742965 | ... M59: =SUM(M68)/M$15 -> 0.074872942
A60: RSM | B60: =SUM(B69)/B$15 -> 0.021213661 | C60: =SUM(C69)/C$15 -> 0.021213661 | D60: =SUM(D69)/D$15 -> 0.021213661 | E60: =SUM(E69)/E$15 -> 0.021213661 | F60: =SUM(F69)/F$15 -> 0.021213661 | G60: =SUM(G69)/G$15 -> 0.021213661 | H60: =SUM(H69)/H$15 -> 0.021213661 | I60: =SUM(I69)/I$15 -> 0.021213661 | ... M60: =SUM(M69)/M$15 -> 0.021213661
A61: TOTAL | B61: =SUM(B56:B60) -> 0.16569238 | C61: =SUM(C56:C60) -> 0.16569238 | D61: =SUM(D56:D60) -> 0.16569238 | E61: =SUM(E56:E60) -> 0.16569238 | F61: =SUM(F56:F60) -> 0.16569238 | G61: =SUM(G56:G60) -> 0.16569238 | H61: =SUM(H56:H60) -> 0.20025225 | I61: =SUM(I56:I60) -> 0.17733192 | ... M61: =SUM(M56:M60) -> 0.16908061
A64: Headcount Earnings
A65: CSO | B65: =SUM(B5*$Q5)+(B14*$R5)+(B13*$S5) -> 14757 | C65: =SUM(C5*$Q5)+(C14*$R5)+(C13*$S5) -> 14757 | D65: =SUM(D5*$Q5)+(D14*$R5)+(D13*$S5) -> 14757 | E65: =SUM(E5*$Q5)+(E14*$R5)+(E13*$S5) -> 14757 | F65: =SUM(F5*$Q5)+(F14*$R5)+(F13*$S5) -> 14757 | G65: =SUM(G5*$Q5)+(G14*$R5)+(G13*$S5) -> 14757 | H65: =SUM(H5*$Q5)+(H14*$R5)+(H13*$S5) -> 8854.2 | I65: =SUM(I5*$Q5)+(I14*$R5)+(I13*$S5) -> 12543.45 | ... M65: =SUM(M5*$Q5)+(M14*$R5)+(M13*$S5) -> 14757 | N65: =SUM(B65:M65) -> 168967.65
A66: BC | B66: =SUM(B6*$Q6)+(B$13*$S6)+(B$14*$R6) -> 29223.125 | C66: =SUM(C6*$Q6)+(C$13*$S6)+(C$14*$R6) -> 29223.125 | D66: =SUM(D6*$Q6)+(D$13*$S6)+(D$14*$R6) -> 29223.125 | E66: =SUM(E6*$Q6)+(E$13*$S6)+(E$14*$R6) -> 29223.125 | F66: =SUM(F6*$Q6)+(F$13*$S6)+(F$14*$R6) -> 29223.125 | G66: =SUM(G6*$Q6)+(G$13*$S6)+(G$14*$R6) -> 29223.125 | H66: =SUM(H6*$Q6)+(H$13*$S6)+(H$14*$R6) -> 28033.875 | I66: =SUM(I6*$Q6)+(I$13*$S6)+(I$14*$R6) -> 30339.656 | ... M66: =SUM(M6*$Q6)+(M$13*$S6)+(M$14*$R6) -> 31723.125 | N66: =SUM(B66:M66) -> 360604.78
A67: TMM | B67: =SUM(B7*$Q7)+(B$13*$S7)+(B$14*$R7) -> 7378.5 | C67: =SUM(C7*$Q7)+(C$13*$S7)+(C$14*$R7) -> 7378.5 | D67: =SUM(D7*$Q7)+(D$13*$S7)+(D$14*$R7) -> 7378.5 | E67: =SUM(E7*$Q7)+(E$13*$S7)+(E$14*$R7) -> 7378.5 | F67: =SUM(F7*$Q7)+(F$13*$S7)+(F$14*$R7) -> 7378.5 | G67: =SUM(G7*$Q7)+(G$13*$S7)+(G$14*$R7) -> 7378.5 | H67: =SUM(H7*$Q7)+(H$13*$S7)+(H$14*$R7) -> 4427.1 | I67: =SUM(I7*$Q7)+(I$13*$S7)+(I$14*$R7) -> 6271.725 | ... M67: =SUM(M7*$Q7)+(M$13*$S7)+(M$14*$R7) -> 7378.5 | N67: =SUM(B67:M67) -> 84483.825
A68: TSR | B68: =SUM(B8*$Q8)+(B$13*$S8)+(B$14*$R8) -> 55245 | C68: =SUM(C8*$Q8)+(C$13*$S8)+(C$14*$R8) -> 55245 | D68: =SUM(D8*$Q8)+(D$13*$S8)+(D$14*$R8) -> 55245 | E68: =SUM(E8*$Q8)+(E$13*$S8)+(E$14*$R8) -> 55245 | F68: =SUM(F8*$Q8)+(F$13*$S8)+(F$14*$R8) -> 55245 | G68: =SUM(G8*$Q8)+(G$13*$S8)+(G$14*$R8) -> 55245 | H68: =SUM(H8*$Q8)+(H$13*$S8)+(H$14*$R8) -> 37947 | I68: =SUM(I8*$Q8)+(I$13*$S8)+(I$14*$R8) -> 48758.25 | ... M68: =SUM(M8*$Q8)+(M$13*$S8)+(M$14*$R8) -> 55245 | N68: =SUM(B68:M68) -> 639155.25
A69: RSM | B69: =SUM(B9*$Q9)+(B$13*$S9)+(B$14*$R9) -> 15652.5 | C69: =SUM(C9*$Q9)+(C$13*$S9)+(C$14*$R9) -> 15652.5 | D69: =SUM(D9*$Q9)+(D$13*$S9)+(D$14*$R9) -> 15652.5 | E69: =SUM(E9*$Q9)+(E$13*$S9)+(E$14*$R9) -> 15652.5 | F69: =SUM(F9*$Q9)+(F$13*$S9)+(F$14*$R9) -> 15652.5 | G69: =SUM(G9*$Q9)+(G$13*$S9)+(G$14*$R9) -> 15652.5 | H69: =SUM(H9*$Q9)+(H$13*$S9)+(H$14*$R9) -> 9391.5 | I69: =SUM(I9*$Q9)+(I$13*$S9)+(I$14*$R9) -> 13304.625 | ... M69: =SUM(M9*$Q9)+(M$13*$S9)+(M$14*$R9) -> 15652.5 | N69: =SUM(B69:M69) -> 179221.12
A70: All Payroll Burden | B70: =SUM(B22:B24) -> 17022.156 | C70: =SUM(C22:C24) -> 15138.584 | D70: =SUM(D22:D24) -> 15138.584 | E70: =SUM(E22:E24) -> 15138.584 | F70: =SUM(F22:F24) -> 15138.584 | G70: =SUM(G22:G24) -> 15138.584 | H70: =SUM(H22:H24) -> 16592.6 | I70: =SUM(I22:I24) -> 16725.246 | ... M70: =SUM(M22:M24) -> 16804.834 | N70: =SUM(B70:M70) -> 193252.26
A71: TOTAL | B71: =SUM(B65:B70) -> 139278.28 | C71: =SUM(C65:C70) -> 137394.71 | D71: =SUM(D65:D70) -> 137394.71 | E71: =SUM(E65:E70) -> 137394.71 | F71: =SUM(F65:F70) -> 137394.71 | G71: =SUM(G65:G70) -> 137394.71 | H71: =SUM(H65:H70) -> 105246.28 | I71: =SUM(I65:I70) -> 127942.95 | ... M71: =SUM(M65:M70) -> 141560.96 | N71: =SUM(B71:M71) -> 1625684.9 | P71: =SUM(100%-O81) -> 0.27953492 | Q71: Net
P72: =SUM(N15)*P71 -> 2361617.9 | Q72: $ Net
A74: Budget Snapshot (Estimated Company) | O74: % | Q74: Ownership Options | R74: % | S74: $ Annual
A75: Sales (includes Travel 25%) | B75: =SUM(B18:B40) -> 109331.41 | C75: =SUM(C18:C40) -> 88952.709 | D75: =SUM(D18:D40) -> 90522.709 | E75: =SUM(E18:E40) -> 93222.709 | F75: =SUM(F18:F40) -> 93222.709 | G75: =SUM(G18:G40) -> 93222.709 | H75: =SUM(H18:H40) -> 91162.675 | I75: =SUM(I18:I40) -> 94635.352 | ... M75: =SUM(M18:M40) -> 97546.959 | N75: =SUM(B75:M75) -> 1144460.8 | O75: =SUM(N75)/N15 -> 0.13546508 | Q75: Total | R75: =SUM(P71) -> 0.27953492 | S75: =SUM(P72)*R75 -> 660154.68
A76: Survey (includes Travel 25%) | B76: =SUM(B15)*25% -> 184462.5 | C76: =SUM(C15)*25% -> 184462.5 | D76: =SUM(D15)*25% -> 184462.5 | E76: =SUM(E15)*25% -> 184462.5 | F76: =SUM(F15)*25% -> 184462.5 | G76: =SUM(G15)*25% -> 184462.5 | H76: =SUM(H15)*25% -> 110677.5 | I76: =SUM(I15)*25% -> 156793.12 | ... M76: =SUM(M15)*25% -> 184462.5 | N76: =SUM(B76:M76) -> 2112095.6 | O76: =SUM(N76)/N15 -> 0.25
A77: Consulting (25%) | B77: =SUM(B15)*25% -> 184462.5 | C77: =SUM(C15)*25% -> 184462.5 | D77: =SUM(D15)*25% -> 184462.5 | E77: =SUM(E15)*25% -> 184462.5 | F77: =SUM(F15)*25% -> 184462.5 | G77: =SUM(G15)*25% -> 184462.5 | H77: =SUM(H15)*25% -> 110677.5 | I77: =SUM(I15)*25% -> 156793.12 | ... M77: =SUM(M15)*25% -> 184462.5 | N77: =SUM(B77:M77) -> 2112095.6 | O77: =SUM(N77)/N15 -> 0.25 | Q77: Retained Belfield | R77: % | S77: $ Annual
A78: Admin/Operations (4.75%) | B78: =SUM(B15)*4.75% -> 35047.875 | C78: =SUM(C15)*4.75% -> 35047.875 | D78: =SUM(D15)*4.75% -> 35047.875 | E78: =SUM(E15)*4.75% -> 35047.875 | F78: =SUM(F15)*4.75% -> 35047.875 | G78: =SUM(G15)*4.75% -> 35047.875 | H78: =SUM(H15)*4.75% -> 21028.725 | I78: =SUM(I15)*4.75% -> 29790.694 | ... M78: =SUM(M15)*4.75% -> 35047.875 | N78: =SUM(B78:M78) -> 401298.17 | O78: =SUM(N78)/N15 -> 0.0475 | Q78: Total | R78: =100%-R75 -> 0.72046508 | S78: =SUM(P72)*R78 -> 1701463.2
A79: President Salary (2.75%) | B79: =SUM(B15)*2.75% -> 20290.875 | C79: =SUM(C15)*2.75% -> 20290.875 | D79: =SUM(D15)*2.75% -> 20290.875 | E79: =SUM(E15)*2.75% -> 20290.875 | F79: =SUM(F15)*2.75% -> 20290.875 | G79: =SUM(G15)*2.75% -> 20290.875 | H79: =SUM(H15)*2.75% -> 12174.525 | I79: =SUM(I15)*2.75% -> 17247.244 | ... M79: =SUM(M15)*2.75% -> 20290.875 | N79: =SUM(B79:M79) -> 232330.52 | O79: =SUM(N79)/N15 -> 0.0275
A80: CFO Salary (1%) | B80: =SUM(B15)*1% -> 7378.5 | C80: =SUM(C15)*1% -> 7378.5 | D80: =SUM(D15)*1% -> 7378.5 | E80: =SUM(E15)*1% -> 7378.5 | F80: =SUM(F15)*1% -> 7378.5 | G80: =SUM(G15)*1% -> 7378.5 | H80: =SUM(H15)*1% -> 4427.1 | I80: =SUM(I15)*1% -> 6271.725 | ... M80: =SUM(M15)*1% -> 7378.5 | N80: =SUM(B80:M80) -> 84483.825 | O80: =SUM(N80)/N15 -> 0.01
A81: TOTAL | B81: =SUM(B75:B80) -> 540973.66 | C81: =SUM(C75:C80) -> 520594.96 | D81: =SUM(D75:D80) -> 522164.96 | E81: =SUM(E75:E80) -> 524864.96 | F81: =SUM(F75:F80) -> 524864.96 | G81: =SUM(G75:G80) -> 524864.96 | H81: =SUM(H75:H80) -> 350148.03 | I81: =SUM(I75:I80) -> 461531.26 | ... O81: =SUM(O75:O80) -> 0.72046508

Sheet FE Sales YR 4
B1: FRONT END SALES FORECAST | P1: **Green boxes can be changed to modify forecast
B2: 44551 | C2: 44582 | D2: 44613 | E2: 44641 | F2: 44672 | G2: 44702 | H2: 44733 | I2: 44763 | J2: 44794 | K2: 44825 | L2: 44855 | M2: 44886
A3: Month # | B3: 1 | C3: 2 | D3: 3 | E3: 4 | F3: 5 | G3: 6 | H3: 7 | I3: 8 | J3: 9 | K3: 10 | L3: 11 | M3: 12 | N3: TOTAL | P3: SALES TEAM
A4: FE SALES HEAD COUNT | P4: Position | Q4: Salary | R4: Comm %* | S4: Survey Fee%
A5: CSO | B5: =SUM('FE Sales YR 3'!M5) -> 0 | C5: 1 | D5: 1 | E5: 1 | F5: 1 | G5: 1 | H5: 1 | I5: 1 | J5: 1 | K5: 1 | L5: 1 | M5: 1 | N5: =SUM(M5) -> 1 | P5: CSO | Q5: 0 | R5: 0.0175 | S5: 0.0175
A6: BC | B6: =SUM('FE Sales YR 3'!M6) -> 9 | C6: 9 | D6: 9 | E6: 9 | F6: 9 | G6: 9 | H6: 12 | I6: 12 | J6: 12 | K6: 12 | L6: 12 | M6: 12 | N6: =SUM(M6) -> 12 | P6: BC | Q6: 2500 | R6: 0.0125 | S6: 0.0125
A7: TMM | B7: =SUM('FE Sales YR 3'!M7) -> 3 | C7: 3 | D7: 3 | E7: 3 | F7: 3 | G7: 3 | H7: 4 | I7: 4 | J7: 4 | K7: 4 | L7: 4 | M7: 4 | N7: =SUM(M7) -> 4 | P7: TMM | Q7: 0 | R7: 0.01 | S7: 0.01
A8: TSR | B8: =SUM('FE Sales YR 3'!M8) -> 6 | C8: 18 | D8: 18 | E8: 18 | F8: 18 | G8: 18 | H8: 24 | I8: 24 | J8: 24 | K8: 24 | L8: 24 | M8: 24 | N8: =SUM(M8) -> 24 | P8: TSR | Q8: 2000 | R8: 0.04 | S8: 0.5
A9: RSM | B9: =SUM('FE Sales YR 3'!M9) -> 0 | C9: 3 | D9: 3 | E9: 3 | F9: 3 | G9: 3 | H9: 4 | I9: 4 | J9: 4 | K9: 4 | L9: 4 | M9: 4 | N9: =SUM(M9) -> 4 | P9: RSM | Q9: 0 | R9: 0.0175 | S9: 0.05
A10: TOTAL | B10: =SUM(B5:B9) -> 18 | C10: =SUM(C5:C9) -> 34 | D10: =SUM(D5:D9) -> 34 | E10: =SUM(E5:E9) -> 34 | F10: =SUM(F5:F9) -> 34 | G10: =SUM(G5:G9) -> 34 | H10: =SUM(H5:H9) -> 45 | I10: =SUM(I5:I9) -> 45 | ... N10: =SUM(N5:N9) -> 45 | R10: =SUM(R5:R9) -> 0.0975 | S10: =SUM(S5:S9) -> 0.59
A12: REVENUE | P12: ASSUMPTIONS
A13: Survey Fees | B13: =B8*$Q$13*$Q$14 -> 29850 | C13: =C8*$Q$13*$Q$14 -> 89550 | D13: =D8*$Q$13*$Q$14 -> 89550 | E13: =E8*$Q$13*$Q$14 -> 89550 | F13: =F8*$Q$13*$Q$14 -> 89550 | G13: =G8*$Q$13*$Q$14 -> 89550 | H13: =H8*$Q$13*$Q$14*85% -> 101490 | I13: =I8*$Q$13*$Q$14*90% -> 107460 | J13: =J8*$Q$13*$Q$14 -> 119400 | K13: =K8*$Q$13*$Q$14 -> 119400 | L13: =L8*$Q$13*$Q$14 -> 119400 | M13: =M8*$Q$13*$Q$14 -> 119400 | N13: =SUM(B13:M13) -> 1164150 | P13: # Mo Sales per TSR | Q13: 5
A14: Cash Collect | B14: =B8*$Q$13*$Q$15*$Q$16*$Q$17 -> 708000 | C14: =C8*$Q$13*$Q$15*$Q$16*$Q$17 -> 2124000 | D14: =D8*$Q$13*$Q$15*$Q$16*$Q$17 -> 2124000 | E14: =E8*$Q$13*$Q$15*$Q$16*$Q$17 -> 2124000 | F14: =F8*$Q$13*$Q$15*$Q$16*$Q$17 -> 2124000 | G14: =G8*$Q$13*$Q$15*$Q$16*$Q$17 -> 2124000 | H14: =H8*$Q$13*$Q$15*$Q$16*$Q$17*85% -> 2407200 | I14: =I8*$Q$13*$Q$15*$Q$16*$Q$17*90% -> 2548800 | J14: =J8*$Q$13*$Q$15*$Q$16*$Q$17 -> 2832000 | K14: =K8*$Q$13*$Q$15*$Q$16*$Q$17 -> 2832000 | L14: =L8*$Q$13*$Q$15*$Q$16*$Q$17 -> 2832000 | M14: =M8*$Q$13*$Q$15*$Q$16*$Q$17 -> 2832000 | N14: =SUM(B14:M14) -> 27612000 | P14: Avg Survey Fee | Q14: 995
A15: TOTAL | B15: =SUM(B13:B14) -> 737850 | C15: =SUM(C13:C14) -> 2213550 | D15: =SUM(D13:D14) -> 2213550 | E15: =SUM(E13:E14) -> 2213550 | F15: =SUM(F13:F14) -> 2213550 | G15: =SUM(G13:G14) -> 2213550 | H15: =SUM(H13:H14) -> 2508690 | I15: =SUM(I13:I14) -> 2656260 | ... M15: =SUM(M13:M14) -> 2951400 | N15: =SUM(B15:M15) -> 28776150 | P15: Survey Closing % | Q15: 0.5
P16: Avg Hrs per Go | Q16: 160
A17: COST OF SALES | P17: Avg Rate per Hr | Q17: 295
A18: Salaries | B18: =B5*$Q$5+B6*$Q$6+C7*$Q$7+B8*$Q$8+B9*$Q$9+B13*S5+B13*S6+B13*S7+B13*S8+B13*S9 -> 52111.5 | C18: =C5*$Q$5+C6*$Q$6+D7*$Q$7+C8*$Q$8+C9*$Q$9+C13*T5+C13*T6+C13*T7+C13*T8+C13*T9 -> 58500 | D18: =D5*$Q$5+D6*$Q$6+E7*$Q$7+D8*$Q$8+D9*$Q$9+D13*U5+D13*U6+D13*U7+D13*U8+D13*U9 -> 58500 | E18: =E5*$Q$5+E6*$Q$6+F7*$Q$7+E8*$Q$8+E9*$Q$9+E13*V5+E13*V6+E13*V7+E13*V8+E13*V9 -> 58500 | F18: =F5*$Q$5+F6*$Q$6+G7*$Q$7+F8*$Q$8+F9*$Q$9+F13*W5+F13*W6+F13*W7+F13*W8+F13*W9 -> 58500 | G18: =G5*$Q$5+G6*$Q$6+H7*$Q$7+G8*$Q$8+G9*$Q$9+G13*X5+G13*X6+G13*X7+G13*X8+G13*X9 -> 58500 | H18: =H5*$Q$5+H6*$Q$6+I7*$Q$7+H8*$Q$8+H9*$Q$9+H13*Y5+H13*Y6+H13*Y7+H13*Y8+H13*Y9 -> 78000 | I18: =I5*$Q$5+I6*$Q$6+J7*$Q$7+I8*$Q$8+I9*$Q$9+I13*Z5+I13*Z6+I13*Z7+I13*Z8+I13*Z9 -> 78000 | ... M18: =M5*$Q$5+M6*$Q$6+N7*$Q$7+M8*$Q$8+M9*$Q$9+M13*AD5+M13*AD6+M13*AD7+M13*AD8+M13*AD9 -> 78000 | N18: =SUM(B18:M18) -> 812611.5 | P18: Est. Sale Bonuses | Q18: =IF(Q13>5,(Q13-4)*300,0) -> 0
A19: Commission | B19: =IF(B5>0,$R$5*B$14,0) -> 0 | C19: =IF(C5>0,$R$5*C$14,0) -> 37170 | D19: =IF(D5>0,$R$5*D$14,0) -> 37170 | E19: =IF(E5>0,$R$5*E$14,0) -> 37170 | F19: =IF(F5>0,$R$5*F$14,0) -> 37170 | G19: =IF(G5>0,$R$5*G$14,0) -> 37170 | H19: =IF(H5>0,$R$5*H$14,0) -> 42126 | I19: =IF(I5>0,$R$5*I$14,0) -> 44604 | ... M19: =IF(M5>0,$R$5*M$14,0) -> 49560 | N19: =SUM(B19:M19) -> 470820 | P19: Est. Srvy Fee Bonus | Q19: =IF($Q$14>995,($Q$14-995)*0.5*$Q$13,0) -> 0
A20: Bonus | B20: =IF(B8>0,B8*$Q$18+B8*$Q$19,0) -> 0 | C20: =IF(C8>0,C8*$Q$18+C8*$Q$19,0) -> 0 | D20: =IF(D8>0,D8*$Q$18+D8*$Q$19,0) -> 0 | E20: =IF(E8>0,E8*$Q$18+E8*$Q$19,0) -> 0 | F20: =IF(F8>0,F8*$Q$18+F8*$Q$19,0) -> 0 | G20: =IF(G8>0,G8*$Q$18+G8*$Q$19,0) -> 0 | H20: =IF(H8>0,H8*$Q$18+H8*$Q$19,0) -> 0 | I20: =IF(I8>0,I8*$Q$18+I8*$Q$19,0) -> 0 | ... M20: =IF(M8>0,M8*$Q$18+M8*$Q$19,0) -> 0 | N20: =SUM(B20:M20) -> 0
A21: FE Sales (Survey Fee %) | B21: =SUM(B13)*$S10 -> 17611.5 | C21: =SUM(C13)*$S10 -> 52834.5 | D21: =SUM(D13)*$S10 -> 52834.5 | E21: =SUM(E13)*$S10 -> 52834.5 | F21: =SUM(F13)*$S10 -> 52834.5 | G21: =SUM(G13)*$S10 -> 52834.5 | H21: =SUM(H13)*$S10 -> 59879.1 | I21: =SUM(I13)*$S10 -> 63401.4 | ... M21: =SUM(M13)*$S10 -> 70446 | N21: =SUM(B21:M21) -> 686848.5
A22: Payroll Burden (7.65%) | B22: =(B18+B19+B20)*0.0765 -> 3986.5298 | C22: =(C18+C19+C20)*0.0765 -> 7318.755 | D22: =(D18+D19+D20)*0.0765 -> 7318.755 | E22: =(E18+E19+E20)*0.0765 -> 7318.755 | F22: =(F18+F19+F20)*0.0765 -> 7318.755 | G22: =(G18+G19+G20)*0.0765 -> 7318.755 | H22: =(H18+H19+H20)*0.0765 -> 9189.639 | I22: =(I18+I19+I20)*0.0765 -> 9379.206 | ... M22: =(M18+M19+M20)*0.0765 -> 9758.34 | N22: =SUM(B22:M22) -> 98182.51
A23: Benefit Pkg. ($700/emp) | B23: =SUM(B10)*700 -> 12600 | C23: =SUM(C10)*700 -> 23800 | D23: =SUM(D10)*700 -> 23800 | E23: =SUM(E10)*700 -> 23800 | F23: =SUM(F10)*700 -> 23800 | G23: =SUM(G10)*700 -> 23800 | H23: =SUM(H10)*700 -> 31500 | I23: =SUM(I10)*700 -> 31500 | ... M23: =SUM(M10)*700 -> 31500 | N23: =SUM(B23:M23) -> 320600
A24: 401 K (Matching 3%) | B24: =SUM(B18:B21)*3% -> 2091.69 | C24: =SUM(C18:C21)*3% -> 4455.135 | D24: =SUM(D18:D21)*3% -> 4455.135 | E24: =SUM(E18:E21)*3% -> 4455.135 | F24: =SUM(F18:F21)*3% -> 4455.135 | G24: =SUM(G18:G21)*3% -> 4455.135 | H24: =SUM(H18:H21)*3% -> 5400.153 | I24: =SUM(I18:I21)*3% -> 5580.162 | ... M24: =SUM(M18:M21)*3% -> 5940.18 | N24: =SUM(B24:M24) -> 59108.4
A25: Leads | B25: 800 | C25: 800 | D25: =SUM(500*D8) -> 9000 | E25: =SUM(500*E8) -> 9000 | F25: =SUM(500*F8) -> 9000 | G25: =SUM(500*G8) -> 9000 | H25: =SUM(500*H8) -> 12000 | I25: =SUM(500*I8) -> 12000 | J25: =SUM(500*J8) -> 12000 | K25: =SUM(500*K8) -> 12000 | ... M25: =SUM(500*M8) -> 12000 | N25: =SUM(B25:M25) -> 109600
A26: CRM | B26: =39*B10+39 -> 741 | C26: =39*C10 -> 1326 | D26: =39*D10 -> 1326 | E26: =39*E10 -> 1326 | F26: =39*F10 -> 1326 | G26: =39*G10 -> 1326 | H26: =39*H10 -> 1755 | I26: =39*I10 -> 1755 | J26: =39*J10 -> 1755 | ... M26: =39*M10 -> 1755 | N26: =SUM(B26:M26) -> 17901
A27: Phone (Phone, Voicemail, Video) | B27: =SUM(28*B6)+(52*B7)+52 -> 460 | C27: =SUM(28*C6)+(52*C7)+52 -> 460 | D27: =SUM(28*D6)+(52*D7)+52 -> 460 | E27: =SUM(28*E6)+(52*E7)+52 -> 460 | F27: =SUM(28*F6)+(52*F7)+52 -> 460 | G27: =SUM(28*G6)+(52*G7)+52 -> 460 | H27: =SUM(28*H6)+(52*H7)+52 -> 596 | I27: =SUM(28*I6)+(52*I7)+52 -> 596 | ... M27: =SUM(28*M6)+(52*M7)+52 -> 596 | N27: =SUM(B27:M27) -> 6336
A28: Recruiting Ads | B28: 850 | C28: 850 | D28: 850 | E28: 850 | F28: 850 | G28: 850 | H28: 850 | I28: 850 | J28: 850 | K28: 850 | L28: 850 | M28: 850 | N28: =SUM(B28:M28) -> 10200
A29: TSR Field Training | B29: =SUM(B8*500) -> 3000 | C29: 1800 | D29: 1800 | E29: =SUM(E8*750) -> 13500 | F29: =SUM(F8*750) -> 13500 | G29: =SUM(G8*750) -> 13500 | H29: =SUM(H8*750) -> 18000 | I29: =SUM(I8*750) -> 18000 | J29: =SUM(J8*750) -> 18000 | K29: =SUM(K8*750) -> 18000 | L29: =SUM(L8*750) -> 18000 | M29: =SUM(M8*750) -> 18000 | N29: =SUM(B29:M29) -> 155100
A30: TSR Per Diem | B30: =500*B8 -> 3000 | C30: =500*C8 -> 9000 | D30: =500*D8 -> 9000 | E30: =500*E8 -> 9000 | F30: =500*F8 -> 9000 | G30: =500*G8 -> 9000 | H30: =500*H8 -> 12000 | I30: =500*I8 -> 12000 | ... M30: =500*M8 -> 12000 | N30: =SUM(B30:M30) -> 120000
A31: TSR Car/Fuel Allowance | B31: =600*B8 -> 3600 | C31: =600*C8 -> 10800 | D31: =600*D8 -> 10800 | E31: =600*E8 -> 10800 | F31: =600*F8 -> 10800 | G31: =600*G8 -> 10800 | H31: =600*H8 -> 14400 | I31: =600*I8 -> 14400 | ... M31: =600*M8 -> 14400 | N31: =SUM(B31:M31) -> 144000
A32: TSR Phone Allowance | B32: =25*B8 -> 150 | C32: =25*C8 -> 450 | D32: =25*D8 -> 450 | E32: =25*E8 -> 450 | F32: =25*F8 -> 450 | G32: =25*G8 -> 450 | H32: =25*H8 -> 600 | I32: =25*I8 -> 600 | ... M32: =25*M8 -> 600 | N32: =SUM(B32:M32) -> 6000
A33: TSR Hotel-2wk/mo travel | B33: =1800*B8 -> 10800 | C33: =1800*C8 -> 32400 | D33: =1800*D8 -> 32400 | E33: =1800*E8 -> 32400 | F33: =1800*F8 -> 32400 | G33: =1800*G8 -> 32400 | H33: =1800*H8 -> 43200 | I33: =1800*I8 -> 43200 | ... M33: =1800*M8 -> 43200 | N33: =SUM(B33:M33) -> 432000
A34: CC Fees (Square/In-Field) | B34: =SUM(B13*4%) -> 1194 | C34: =SUM(C13*4%) -> 3582 | D34: =SUM(D13*4%) -> 3582 | E34: =SUM(E13*4%) -> 3582 | F34: =SUM(F13*4%) -> 3582 | G34: =SUM(G13*4%) -> 3582 | H34: =SUM(H13*4%) -> 4059.6 | I34: =SUM(I13*4%) -> 4298.4 | ... M34: =SUM(M13*4%) -> 4776 | N34: =SUM(B34:M34) -> 46566
A35: Printing
A36: Brochures (Leave Behinds) | B36: 500 | C36: =SUM(C8)*50 -> 900 | D36: =SUM(D8)*50 -> 900 | E36: =SUM(E8)*50 -> 900 | F36: =SUM(F8)*50 -> 900 | G36: =SUM(G8)*50 -> 900 | H36: =SUM(H8)*50 -> 1200 | I36: =SUM(I8)*50 -> 1200 | J36: =SUM(J8)*50 -> 1200 | ... M36: =SUM(M8)*50 -> 1200 | N36: =SUM(B36:M36) -> 12200
A37: Agreements (2-part) | C37: 0 | D37: 0 | E37: 0 | F37: 0 | G37: 0 | H37: 1000 | I37: 0 | J37: 0 | K37: 0 | N37: =SUM(B37:M37) -> 1000
A38: Business Cards: TSR | C38: =SUM(C8*105) -> 1890 | D38: 0 | E38: 0 | F38: 0 | G38: 0 | H38: =SUM(H8*105) -> 2520 | I38: 0 | J38: 0 | K38: 0 | L38: 0 | M38: 0 | N38: =SUM(B38:M38) -> 4410
A39: Business Cards: RSM | B39: =SUM(B9*56) -> 0 | H39: =SUM(H9*105) -> 420 | I39: 0 | J39: 0 | K39: 0 | L39: 0 | M39: 0 | N39: =SUM(B39:M39) -> 420
A40: Business Cards: CSO | B40: =SUM(B5*105) -> 0 | C40: 0 | D40: 0 | E40: 0 | F40: 0 | G40: 0 | H40: 0 | I40: 0 | J40: 0 | K40: 0 | L40: 0 | M40: 0 | N40: =SUM(B40:M40) -> 0
A41: TOTAL | B41: =SUM(B18:B34) -> 112996.22 | C41: =SUM(C18:C34) -> 245546.39 | D41: =SUM(D18:D34) -> 253746.39 | E41: =SUM(E18:E34) -> 265446.39 | F41: =SUM(F18:F34) -> 265446.39 | G41: =SUM(G18:G34) -> 265446.39 | H41: =SUM(H18:H34) -> 333555.49 | I41: =SUM(I18:I34) -> 340164.17 | ... M41: =SUM(M18:M34) -> 353381.52 | N41: =SUM(N21:N34) -> 2212442.4
A43: GROSS SALES PROFIT/(LOSS) | B43: =B15-B41 -> 624853.78 | C43: =C15-C41 -> 1968003.6 | D43: =D15-D41 -> 1959803.6 | E43: =E15-E41 -> 1948103.6 | F43: =F15-F41 -> 1948103.6 | G43: =G15-G41 -> 1948103.6 | H43: =H15-H41 -> 2175134.5 | I43: =I15-I41 -> 2316095.8 | ... M43: =M15-M41 -> 2598018.5 | N43: =SUM(B43:M43) -> 25280276
A46: CASH FLOW
A47: Balance Fwd | B47: =SUM('FE Sales YR 3'!M51) -> 9130214.6 | C47: =B51 -> 9327115.4 | D47: =C51 -> 10256806 | E47: =D51 -> 11186497 | F47: =E51 -> 11456034 | G47: =F51 -> 12385725 | H47: =G51 -> 13315416 | I47: =H51 -> 14369066 | J47: =I51 -> 15484695 | ... M47: =L51 -> 19203459
A48: Ending Balance | B48: =B43+B47 -> 9755068.4 | C48: =C15+C47 -> 11540665 | D48: =D15+D47 -> 12470356 | E48: =E15+E47 -> 13400047 | F48: =F15+F47 -> 13669584 | G48: =G15+G47 -> 14599275 | H48: =H15+H47 -> 15824106 | I48: =I15+I47 -> 17025326 | J48: =J15+J47 -> 18436095 | ... M48: =M15+M47 -> 22154859
A49: (-) Estimated Company | B49: =SUM(B76:B80) -> 427953 | C49: =SUM(C76:C80) -> 1283859 | D49: =SUM(D76:D80) -> 1283859 | E49: =SUM(E76:E80) -> 1283859 | F49: =SUM(F76:F80) -> 1283859 | G49: =SUM(G76:G80) -> 1283859 | H49: =SUM(H76:H80) -> 1455040.2 | I49: =SUM(I76:I80) -> 1540630.8 | ... M49: =SUM(M76:M80) -> 1711812
A50: (-) Ownership Options % | B50: 0 | C50: 0 | D50: 0 | E50: =SUM('FE Sales YR 3'!S75) -> 660154.68 | F50: 0 | G50: 0 | H50: 0 | I50: 0 | J50: 0 | K50: 0 | L50: 0 | M50: 0 | Q50: 12 Month Avg | R50: Benefits | S50: 401K Match | T50: Monthly Avg
A51: (-) Estimated Retained | B51: =SUM(B48)-B49-B50 -> 9327115.4 | C51: =SUM(C48)-C49-C50 -> 10256806 | D51: =SUM(D48)-D49-D50 -> 11186497 | E51: =SUM(E48)-E49-E50 -> 11456034 | F51: =SUM(F48)-F49-F50 -> 12385725 | G51: =SUM(G48)-G49-G50 -> 13315416 | H51: =SUM(H48)-H49-H50 -> 14369066 | I51: =SUM(I48)-I49-I50 -> 15484695 | ... M51: =SUM(M48)-M49-M50 -> 20443047 | P51: CSO | Q51: =SUM(N65)/N5 -> 503582.62 | R51: 8400 | S51: =SUM(N65*3%)/N5 -> 15107.479 | T51: =SUM(Q51:S51)/12 -> 43924.175
P52: BC | Q52: =SUM(N66)/10.5 -> 64257.321 | R52: 8400 | S52: =SUM(N66*3%)/N6 -> 1686.7547 | T52: =SUM(Q52:S52)/12 -> 6195.3397
P53: TMM | Q53: =SUM(N67)/3.5 -> 82217.571 | R53: 8400 | S53: =SUM(N67*3%)/N7 -> 2158.2112 | T53: =SUM(Q53:S53)/12 -> 7731.3152
P54: TSR | Q54: =SUM(N68)/21 -> 103169.29 | R54: 8400 | S54: =SUM(N68*3%)/N8 -> 2708.1937 | T54: =SUM(Q54:S54)/12 -> 9523.1233
A55: Payroll As Percent | P55: RSM | Q55: =SUM(N69)/3.5 -> 154690.71 | R55: 8400 | S55: =SUM(N69*3%)/N9 -> 4060.6312 | T55: =SUM(Q55:S55)/12 -> 13929.279
A56: CSO | B56: =SUM(B65)/B15 -> 0.0175 | C56: =SUM(C65)/C15 -> 0.0175 | D56: =SUM(D65)/D15 -> 0.0175 | E56: =SUM(E65)/E15 -> 0.0175 | F56: =SUM(F65)/F15 -> 0.0175 | G56: =SUM(G65)/G15 -> 0.0175 | H56: =SUM(H65)/H15 -> 0.0175 | I56: =SUM(I65)/I15 -> 0.0175 | ... M56: =SUM(M65)/M15 -> 0.0175
A57: BC | B57: =SUM(B66)/B15 -> 0.042994003 | C57: =SUM(C66)/C15 -> 0.022664668 | D57: =SUM(D66)/D15 -> 0.022664668 | E57: =SUM(E66)/E15 -> 0.022664668 | F57: =SUM(F66)/F15 -> 0.022664668 | G57: =SUM(G66)/G15 -> 0.022664668 | H57: =SUM(H66)/H15 -> 0.024458432 | I57: =SUM(I66)/I15 -> 0.023794075 | ... M57: =SUM(M66)/M15 -> 0.022664668
A58: TMM | B58: =SUM(B67)/B$15 -> 0.01 | C58: =SUM(C67)/C$15 -> 0.01 | D58: =SUM(D67)/D$15 -> 0.01 | E58: =SUM(E67)/E$15 -> 0.01 | F58: =SUM(F67)/F$15 -> 0.01 | G58: =SUM(G67)/G$15 -> 0.01 | H58: =SUM(H67)/H$15 -> 0.01 | I58: =SUM(I67)/I$15 -> 0.01 | ... M58: =SUM(M67)/M$15 -> 0.01
A59: TSR | B59: =SUM(B68)/B$15 -> 0.074872942 | C59: =SUM(C68)/C$15 -> 0.074872942 | D59: =SUM(D68)/D$15 -> 0.074872942 | E59: =SUM(E68)/E$15 -> 0.074872942 | F59: =SUM(F68)/F$15 -> 0.074872942 | G59: =SUM(G68)/G$15 -> 0.074872942 | H59: =SUM(H68)/H$15 -> 0.077742965 | I59: =SUM(I68)/I$15 -> 0.076679994 | ... M59: =SUM(M68)/M$15 -> 0.074872942
A60: RSM | B60: =SUM(B69)/B$15 -> 0.0188148 | C60: =SUM(C69)/C$15 -> 0.0188148 | D60: =SUM(D69)/D$15 -> 0.0188148 | E60: =SUM(E69)/E$15 -> 0.0188148 | F60: =SUM(F69)/F$15 -> 0.0188148 | G60: =SUM(G69)/G$15 -> 0.0188148 | H60: =SUM(H69)/H$15 -> 0.0188148 | I60: =SUM(I69)/I$15 -> 0.0188148 | ... M60: =SUM(M69)/M$15 -> 0.0188148
A61: TOTAL | B61: =SUM(B56:B60) -> 0.16418174 | C61: =SUM(C56:C60) -> 0.14385241 | D61: =SUM(D56:D60) -> 0.14385241 | E61: =SUM(E56:E60) -> 0.14385241 | F61: =SUM(F56:F60) -> 0.14385241 | G61: =SUM(G56:G60) -> 0.14385241 | H61: =SUM(H56:H60) -> 0.1485162 | I61: =SUM(I56:I60) -> 0.14678887 | ... M61: =SUM(M56:M60) -> 0.14385241
A64: Headcount Earnings
A65: CSO | B65: =SUM(B5*$Q5)+(B14*$R5)+(B13*$S5) -> 12912.375 | C65: =SUM(C5*$Q5)+(C14*$R5)+(C13*$S5) -> 38737.125 | D65: =SUM(D5*$Q5)+(D14*$R5)+(D13*$S5) -> 38737.125 | E65: =SUM(E5*$Q5)+(E14*$R5)+(E13*$S5) -> 38737.125 | F65: =SUM(F5*$Q5)+(F14*$R5)+(F13*$S5) -> 38737.125 | G65: =SUM(G5*$Q5)+(G14*$R5)+(G13*$S5) -> 38737.125 | H65: =SUM(H5*$Q5)+(H14*$R5)+(H13*$S5) -> 43902.075 | I65: =SUM(I5*$Q5)+(I14*$R5)+(I13*$S5) -> 46484.55 | ... M65: =SUM(M5*$Q5)+(M14*$R5)+(M13*$S5) -> 51649.5 | N65: =SUM(B65:M65) -> 503582.62
A66: BC | B66: =SUM(B6*$Q6)+(B$13*$S6)+(B$14*$R6) -> 31723.125 | C66: =SUM(C6*$Q6)+(C$13*$S6)+(C$14*$R6) -> 50169.375 | D66: =SUM(D6*$Q6)+(D$13*$S6)+(D$14*$R6) -> 50169.375 | E66: =SUM(E6*$Q6)+(E$13*$S6)+(E$14*$R6) -> 50169.375 | F66: =SUM(F6*$Q6)+(F$13*$S6)+(F$14*$R6) -> 50169.375 | G66: =SUM(G6*$Q6)+(G$13*$S6)+(G$14*$R6) -> 50169.375 | H66: =SUM(H6*$Q6)+(H$13*$S6)+(H$14*$R6) -> 61358.625 | I66: =SUM(I6*$Q6)+(I$13*$S6)+(I$14*$R6) -> 63203.25 | ... M66: =SUM(M6*$Q6)+(M$13*$S6)+(M$14*$R6) -> 66892.5 | N66: =SUM(B66:M66) -> 674701.88
A67: TMM | B67: =SUM(B7*$Q7)+(B$13*$S7)+(B$14*$R7) -> 7378.5 | C67: =SUM(C7*$Q7)+(C$13*$S7)+(C$14*$R7) -> 22135.5 | D67: =SUM(D7*$Q7)+(D$13*$S7)+(D$14*$R7) -> 22135.5 | E67: =SUM(E7*$Q7)+(E$13*$S7)+(E$14*$R7) -> 22135.5 | F67: =SUM(F7*$Q7)+(F$13*$S7)+(F$14*$R7) -> 22135.5 | G67: =SUM(G7*$Q7)+(G$13*$S7)+(G$14*$R7) -> 22135.5 | H67: =SUM(H7*$Q7)+(H$13*$S7)+(H$14*$R7) -> 25086.9 | I67: =SUM(I7*$Q7)+(I$13*$S7)+(I$14*$R7) -> 26562.6 | ... M67: =SUM(M7*$Q7)+(M$13*$S7)+(M$14*$R7) -> 29514 | N67: =SUM(B67:M67) -> 287761.5
A68: TSR | B68: =SUM(B8*$Q8)+(B$13*$S8)+(B$14*$R8) -> 55245 | C68: =SUM(C8*$Q8)+(C$13*$S8)+(C$14*$R8) -> 165735 | D68: =SUM(D8*$Q8)+(D$13*$S8)+(D$14*$R8) -> 165735 | E68: =SUM(E8*$Q8)+(E$13*$S8)+(E$14*$R8) -> 165735 | F68: =SUM(F8*$Q8)+(F$13*$S8)+(F$14*$R8) -> 165735 | G68: =SUM(G8*$Q8)+(G$13*$S8)+(G$14*$R8) -> 165735 | H68: =SUM(H8*$Q8)+(H$13*$S8)+(H$14*$R8) -> 195033 | I68: =SUM(I8*$Q8)+(I$13*$S8)+(I$14*$R8) -> 203682 | ... M68: =SUM(M8*$Q8)+(M$13*$S8)+(M$14*$R8) -> 220980 | N68: =SUM(B68:M68) -> 2166555
A69: RSM | B69: =SUM(B9*$Q9)+(B$13*$S9)+(B$14*$R9) -> 13882.5 | C69: =SUM(C9*$Q9)+(C$13*$S9)+(C$14*$R9) -> 41647.5 | D69: =SUM(D9*$Q9)+(D$13*$S9)+(D$14*$R9) -> 41647.5 | E69: =SUM(E9*$Q9)+(E$13*$S9)+(E$14*$R9) -> 41647.5 | F69: =SUM(F9*$Q9)+(F$13*$S9)+(F$14*$R9) -> 41647.5 | G69: =SUM(G9*$Q9)+(G$13*$S9)+(G$14*$R9) -> 41647.5 | H69: =SUM(H9*$Q9)+(H$13*$S9)+(H$14*$R9) -> 47200.5 | I69: =SUM(I9*$Q9)+(I$13*$S9)+(I$14*$R9) -> 49977 | ... M69: =SUM(M9*$Q9)+(M$13*$S9)+(M$14*$R9) -> 55530 | N69: =SUM(B69:M69) -> 541417.5
A70: Payroll Burden | B70: =SUM(B22:B24) -> 18678.22 | C70: =SUM(C22:C24) -> 35573.89 | D70: =SUM(D22:D24) -> 35573.89 | E70: =SUM(E22:E24) -> 35573.89 | F70: =SUM(F22:F24) -> 35573.89 | G70: =SUM(G22:G24) -> 35573.89 | H70: =SUM(H22:H24) -> 46089.792 | I70: =SUM(I22:I24) -> 46459.368 | ... M70: =SUM(M22:M24) -> 47198.52 | N70: =SUM(B70:M70) -> 477890.91
A71: TOTAL | B71: =SUM(B65:B70) -> 139819.72 | C71: =SUM(C65:C70) -> 353998.39 | D71: =SUM(D65:D70) -> 353998.39 | E71: =SUM(E65:E70) -> 353998.39 | F71: =SUM(F65:F70) -> 353998.39 | G71: =SUM(G65:G70) -> 353998.39 | H71: =SUM(H65:H70) -> 418670.89 | I71: =SUM(I65:I70) -> 436368.77 | ... M71: =SUM(M65:M70) -> 471764.52 | N71: =SUM(B71:M71) -> 4651909.4 | P71: =SUM(100%-O81) -> 0.29788832 | Q71: Net
P72: =SUM(N15)*P71 -> 8572079.1 | Q72: $ Net
A74: Budget Snapshot (Estimated Company) | O74: % | Q74: Ownership Options | R74: % | S74: $ Annual
A75: Sales (includes Travel 25%) | B75: =SUM(B18:B40) -> 113496.22 | C75: =SUM(C18:C40) -> 248336.39 | D75: =SUM(D18:D40) -> 254646.39 | E75: =SUM(E18:E40) -> 266346.39 | F75: =SUM(F18:F40) -> 266346.39 | G75: =SUM(G18:G40) -> 266346.39 | H75: =SUM(H18:H40) -> 338695.49 | I75: =SUM(I18:I40) -> 341364.17 | ... M75: =SUM(M18:M40) -> 354581.52 | N75: =SUM(B75:M75) -> 3513903.9 | O75: =SUM(N75)/N15 -> 0.12211168 | Q75: Total | R75: =SUM(P71) -> 0.29788832 | S75: =SUM(P72)*R75 -> 2553522.3
A76: Survey (includes Travel 25%) | B76: =SUM(B15)*25% -> 184462.5 | C76: =SUM(C15)*25% -> 553387.5 | D76: =SUM(D15)*25% -> 553387.5 | E76: =SUM(E15)*25% -> 553387.5 | F76: =SUM(F15)*25% -> 553387.5 | G76: =SUM(G15)*25% -> 553387.5 | H76: =SUM(H15)*25% -> 627172.5 | I76: =SUM(I15)*25% -> 664065 | ... M76: =SUM(M15)*25% -> 737850 | N76: =SUM(B76:M76) -> 7194037.5 | O76: =SUM(N76)/N15 -> 0.25
A77: Consulting (25%) | B77: =SUM(B15)*25% -> 184462.5 | C77: =SUM(C15)*25% -> 553387.5 | D77: =SUM(D15)*25% -> 553387.5 | E77: =SUM(E15)*25% -> 553387.5 | F77: =SUM(F15)*25% -> 553387.5 | G77: =SUM(G15)*25% -> 553387.5 | H77: =SUM(H15)*25% -> 627172.5 | I77: =SUM(I15)*25% -> 664065 | ... M77: =SUM(M15)*25% -> 737850 | N77: =SUM(B77:M77) -> 7194037.5 | O77: =SUM(N77)/N15 -> 0.25 | Q77: Retained Belfield | R77: % | S77: $ Annual
A78: Admin/Operations (5%) | B78: =SUM(B15)*5% -> 36892.5 | C78: =SUM(C15)*5% -> 110677.5 | D78: =SUM(D15)*5% -> 110677.5 | E78: =SUM(E15)*5% -> 110677.5 | F78: =SUM(F15)*5% -> 110677.5 | G78: =SUM(G15)*5% -> 110677.5 | H78: =SUM(H15)*5% -> 125434.5 | I78: =SUM(I15)*5% -> 132813 | ... M78: =SUM(M15)*5% -> 147570 | N78: =SUM(B78:M78) -> 1438807.5 | O78: =SUM(N78)/N15 -> 0.05 | Q78: Total | R78: =100%-R75 -> 0.70211168 | S78: =SUM(P72)*R78 -> 6018556.8
A79: President Salary (2.25%) | B79: =SUM(B15)*2.25% -> 16601.625 | C79: =SUM(C15)*2.25% -> 49804.875 | D79: =SUM(D15)*2.25% -> 49804.875 | E79: =SUM(E15)*2.25% -> 49804.875 | F79: =SUM(F15)*2.25% -> 49804.875 | G79: =SUM(G15)*2.25% -> 49804.875 | H79: =SUM(H15)*2.25% -> 56445.525 | I79: =SUM(I15)*2.25% -> 59765.85 | ... M79: =SUM(M15)*2.25% -> 66406.5 | N79: =SUM(B79:M79) -> 647463.38 | O79: =SUM(N79)/N15 -> 0.0225
A80: CFO Salary (.75%) | B80: =SUM(B15)*0.0075 -> 5533.875 | C80: =SUM(C15)*0.0075 -> 16601.625 | D80: =SUM(D15)*0.0075 -> 16601.625 | E80: =SUM(E15)*0.0075 -> 16601.625 | F80: =SUM(F15)*0.0075 -> 16601.625 | G80: =SUM(G15)*0.0075 -> 16601.625 | H80: =SUM(H15)*0.0075 -> 18815.175 | I80: =SUM(I15)*0.0075 -> 19921.95 | ... M80: =SUM(M15)*0.0075 -> 22135.5 | N80: =SUM(B80:M80) -> 215821.12 | O80: =SUM(N80)/N15 -> 0.0075
A81: TOTAL | B81: =SUM(B75:B80) -> 541449.22 | C81: =SUM(C75:C80) -> 1532195.4 | D81: =SUM(D75:D80) -> 1538505.4 | E81: =SUM(E75:E80) -> 1550205.4 | F81: =SUM(F75:F80) -> 1550205.4 | G81: =SUM(G75:G80) -> 1550205.4 | H81: =SUM(H75:H80) -> 1793735.7 | I81: =SUM(I75:I80) -> 1881995 | ... O81: =SUM(O75:O80) -> 0.70211168

Sheet FE Sales YR 5
B1: FRONT END SALES FORECAST (YR 5 Maintaining) | P1: **Green boxes can be changed to modify forecast
B2: 44551 | C2: 44582 | D2: 44613 | E2: 44641 | F2: 44672 | G2: 44702 | H2: 44733 | I2: 44763 | J2: 44794 | K2: 44825 | L2: 44855 | M2: 44886
A3: Month # | B3: 1 | C3: 2 | D3: 3 | E3: 4 | F3: 5 | G3: 6 | H3: 7 | I3: 8 | J3: 9 | K3: 10 | L3: 11 | M3: 12 | N3: TOTAL | P3: SALES TEAM
A4: FE SALES HEAD COUNT | P4: Position | Q4: Salary | R4: Comm %* | S4: Survey Fee%
A5: CSO | B5: =SUM('FE Sales YR 4'!M5) -> 1 | C5: 1 | D5: 1 | E5: 1 | F5: 1 | G5: 1 | H5: 1 | I5: 1 | J5: 1 | K5: 1 | L5: 1 | M5: 1 | N5: =SUM(M5) -> 1 | P5: CSO | Q5: 0 | R5: 0.015 | S5: 0.015
A6: BC | B6: =SUM('FE Sales YR 4'!M6) -> 12 | C6: 12 | D6: 12 | E6: 12 | F6: 12 | G6: 12 | H6: 12 | I6: 12 | J6: 12 | K6: 12 | L6: 12 | M6: 12 | N6: =SUM(M6) -> 12 | P6: BC | Q6: 2500 | R6: 0.0125 | S6: 0.0125
A7: TMM | B7: =SUM('FE Sales YR 4'!M7) -> 4 | C7: 4 | D7: 4 | E7: 4 | F7: 4 | G7: 4 | H7: 4 | I7: 4 | J7: 4 | K7: 4 | L7: 4 | M7: 4 | N7: =SUM(M7) -> 4 | P7: TMM | Q7: 0 | R7: 0.01 | S7: 0.01
A8: TSR | B8: =SUM('FE Sales YR 4'!M8) -> 24 | C8: 24 | D8: 24 | E8: 24 | F8: 24 | G8: 24 | H8: 24 | I8: 24 | J8: 24 | K8: 24 | L8: 24 | M8: 24 | N8: =SUM(M8) -> 24 | P8: TSR | Q8: 2000 | R8: 0.04 | S8: 0.5
A9: RSM | B9: =SUM('FE Sales YR 4'!M9) -> 4 | C9: 4 | D9: 4 | E9: 4 | F9: 4 | G9: 4 | H9: 4 | I9: 4 | J9: 4 | K9: 4 | L9: 4 | M9: 4 | N9: =SUM(M9) -> 4 | P9: RSM | Q9: 0 | R9: 0.0175 | S9: 0.05
A10: TOTAL | B10: =SUM(B5:B9) -> 45 | C10: =SUM(C5:C9) -> 45 | D10: =SUM(D5:D9) -> 45 | E10: =SUM(E5:E9) -> 45 | F10: =SUM(F5:F9) -> 45 | G10: =SUM(G5:G9) -> 45 | H10: =SUM(H5:H9) -> 45 | I10: =SUM(I5:I9) -> 45 | ... N10: =SUM(N5:N9) -> 45 | R10: =SUM(R5:R9) -> 0.095 | S10: =SUM(S5:S9) -> 0.5875
A12: REVENUE | P12: ASSUMPTIONS
A13: Survey Fees | B13: =B8*$Q$13*$Q$14 -> 119400 | C13: =C8*$Q$13*$Q$14 -> 119400 | D13: =D8*$Q$13*$Q$14 -> 119400 | E13: =E8*$Q$13*$Q$14 -> 119400 | F13: =F8*$Q$13*$Q$14 -> 119400 | G13: =G8*$Q$13*$Q$14 -> 119400 | H13: =H8*$Q$13*$Q$14 -> 119400 | I13: =I8*$Q$13*$Q$14 -> 119400 | ... M13: =M8*$Q$13*$Q$14 -> 119400 | N13: =SUM(B13:M13) -> 1432800 | P13: # Mo Sales per TSR | Q13: 5
A14: Cash Collect | B14: =B8*$Q$13*$Q$15*$Q$16*$Q$17 -> 2832000 | C14: =C8*$Q$13*$Q$15*$Q$16*$Q$17 -> 2832000 | D14: =D8*$Q$13*$Q$15*$Q$16*$Q$17 -> 2832000 | E14: =E8*$Q$13*$Q$15*$Q$16*$Q$17 -> 2832000 | F14: =F8*$Q$13*$Q$15*$Q$16*$Q$17 -> 2832000 | G14: =G8*$Q$13*$Q$15*$Q$16*$Q$17 -> 2832000 | H14: =H8*$Q$13*$Q$15*$Q$16*$Q$17 -> 2832000 | I14: =I8*$Q$13*$Q$15*$Q$16*$Q$17 -> 2832000 | ... M14: =M8*$Q$13*$Q$15*$Q$16*$Q$17 -> 2832000 | N14: =SUM(B14:M14) -> 33984000 | P14: Avg Survey Fee | Q14: 995
A15: TOTAL | B15: =SUM(B13:B14) -> 2951400 | C15: =SUM(C13:C14) -> 2951400 | D15: =SUM(D13:D14) -> 2951400 | E15: =SUM(E13:E14) -> 2951400 | F15: =SUM(F13:F14) -> 2951400 | G15: =SUM(G13:G14) -> 2951400 | H15: =SUM(H13:H14) -> 2951400 | I15: =SUM(I13:I14) -> 2951400 | ... N15: =SUM(N13:N14) -> 35416800 | P15: Survey Closing % | Q15: 0.5
P16: Avg Hrs per Go | Q16: 160
A17: COST OF SALES | P17: Avg Rate per Hr | Q17: 295
A18: Salaries | B18: =B5*$Q$5+B6*$Q$6+C7*$Q$7+B8*$Q$8+B9*$Q$9+B13*S5+B13*S6+B13*S7+B13*S8+B13*S9 -> 148147.5 | C18: =C5*$Q$5+C6*$Q$6+D7*$Q$7+C8*$Q$8+C9*$Q$9+C13*T5+C13*T6+C13*T7+C13*T8+C13*T9 -> 78000 | D18: =D5*$Q$5+D6*$Q$6+E7*$Q$7+D8*$Q$8+D9*$Q$9+D13*U5+D13*U6+D13*U7+D13*U8+D13*U9 -> 78000 | E18: =E5*$Q$5+E6*$Q$6+F7*$Q$7+E8*$Q$8+E9*$Q$9+E13*V5+E13*V6+E13*V7+E13*V8+E13*V9 -> 78000 | F18: =F5*$Q$5+F6*$Q$6+G7*$Q$7+F8*$Q$8+F9*$Q$9+F13*W5+F13*W6+F13*W7+F13*W8+F13*W9 -> 78000 | G18: =G5*$Q$5+G6*$Q$6+H7*$Q$7+G8*$Q$8+G9*$Q$9+G13*X5+G13*X6+G13*X7+G13*X8+G13*X9 -> 78000 | H18: =H5*$Q$5+H6*$Q$6+I7*$Q$7+H8*$Q$8+H9*$Q$9+H13*Y5+H13*Y6+H13*Y7+H13*Y8+H13*Y9 -> 78000 | I18: =I5*$Q$5+I6*$Q$6+J7*$Q$7+I8*$Q$8+I9*$Q$9+I13*Z5+I13*Z6+I13*Z7+I13*Z8+I13*Z9 -> 78000 | ... M18: =M5*$Q$5+M6*$Q$6+N7*$Q$7+M8*$Q$8+M9*$Q$9+M13*AD5+M13*AD6+M13*AD7+M13*AD8+M13*AD9 -> 78000 | N18: =SUM(B18:M18) -> 1006147.5 | P18: Est. Sale Bonuses | Q18: =IF(Q13>5,(Q13-4)*300,0) -> 0
A19: Commission | B19: =IF(B5>0,$R$5*B$14,0) -> 42480 | C19: =IF(C5>0,$R$5*C$14,0) -> 42480 | D19: =IF(D5>0,$R$5*D$14,0) -> 42480 | E19: =IF(E5>0,$R$5*E$14,0) -> 42480 | F19: =IF(F5>0,$R$5*F$14,0) -> 42480 | G19: =IF(G5>0,$R$5*G$14,0) -> 42480 | H19: =IF(H5>0,$R$5*H$14,0) -> 42480 | I19: =IF(I5>0,$R$5*I$14,0) -> 42480 | ... M19: =IF(M5>0,$R$5*M$14,0) -> 42480 | N19: =SUM(B19:M19) -> 509760 | P19: Est. Srvy Fee Bonus | Q19: =IF($Q$14>995,($Q$14-995)*0.5*$Q$13,0) -> 0
A20: Bonus | B20: =IF(B8>0,B8*$Q$18+B8*$Q$19,0) -> 0 | C20: =IF(C8>0,C8*$Q$18+C8*$Q$19,0) -> 0 | D20: =IF(D8>0,D8*$Q$18+D8*$Q$19,0) -> 0 | E20: =IF(E8>0,E8*$Q$18+E8*$Q$19,0) -> 0 | F20: =IF(F8>0,F8*$Q$18+F8*$Q$19,0) -> 0 | G20: =IF(G8>0,G8*$Q$18+G8*$Q$19,0) -> 0 | H20: =IF(H8>0,H8*$Q$18+H8*$Q$19,0) -> 0 | I20: =IF(I8>0,I8*$Q$18+I8*$Q$19,0) -> 0 | ... M20: =IF(M8>0,M8*$Q$18+M8*$Q$19,0) -> 0 | N20: =SUM(B20:M20) -> 0
A21: FE Sales (Survey Fee %) | B21: =SUM(B13)*$S10 -> 70147.5 | C21: =SUM(C13)*$S10 -> 70147.5 | D21: =SUM(D13)*$S10 -> 70147.5 | E21: =SUM(E13)*$S10 -> 70147.5 | F21: =SUM(F13)*$S10 -> 70147.5 | G21: =SUM(G13)*$S10 -> 70147.5 | H21: =SUM(H13)*$S10 -> 70147.5 | I21: =SUM(I13)*$S10 -> 70147.5 | ... M21: =SUM(M13)*$S10 -> 70147.5 | N21: =SUM(B21:M21) -> 841770
A22: Payroll Burden (7.65%) | B22: =(B18+B19+B20)*0.0765 -> 14583.004 | C22: =(C18+C19+C20)*0.0765 -> 9216.72 | D22: =(D18+D19+D20)*0.0765 -> 9216.72 | E22: =(E18+E19+E20)*0.0765 -> 9216.72 | F22: =(F18+F19+F20)*0.0765 -> 9216.72 | G22: =(G18+G19+G20)*0.0765 -> 9216.72 | H22: =(H18+H19+H20)*0.0765 -> 9216.72 | I22: =(I18+I19+I20)*0.0765 -> 9216.72 | ... M22: =(M18+M19+M20)*0.0765 -> 9216.72 | N22: =SUM(B22:M22) -> 115966.92
A23: Benefit Pkg. ($700/emp) | B23: =SUM(B10)*700 -> 31500 | C23: =SUM(C10)*700 -> 31500 | D23: =SUM(D10)*700 -> 31500 | E23: =SUM(E10)*700 -> 31500 | F23: =SUM(F10)*700 -> 31500 | G23: =SUM(G10)*700 -> 31500 | H23: =SUM(H10)*700 -> 31500 | I23: =SUM(I10)*700 -> 31500 | ... M23: =SUM(M10)*700 -> 31500 | N23: =SUM(B23:M23) -> 378000
A24: 401 K (Matching 3%) | B24: =SUM(B18:B21)*3% -> 7823.25 | C24: =SUM(C18:C21)*3% -> 5718.825 | D24: =SUM(D18:D21)*3% -> 5718.825 | E24: =SUM(E18:E21)*3% -> 5718.825 | F24: =SUM(F18:F21)*3% -> 5718.825 | G24: =SUM(G18:G21)*3% -> 5718.825 | H24: =SUM(H18:H21)*3% -> 5718.825 | I24: =SUM(I18:I21)*3% -> 5718.825 | ... M24: =SUM(M18:M21)*3% -> 5718.825 | N24: =SUM(B24:M24) -> 70730.325
A25: Leads | B25: 800 | C25: 800 | D25: =SUM(500*D8) -> 12000 | E25: =SUM(500*E8) -> 12000 | F25: =SUM(500*F8) -> 12000 | G25: =SUM(500*G8) -> 12000 | H25: =SUM(500*H8) -> 12000 | I25: =SUM(500*I8) -> 12000 | J25: =SUM(500*J8) -> 12000 | K25: =SUM(500*K8) -> 12000 | ... M25: =SUM(500*M8) -> 12000 | N25: =SUM(B25:M25) -> 121600
A26: CRM | B26: =39*B10+39 -> 1794 | C26: =39*C10 -> 1755 | D26: =39*D10 -> 1755 | E26: =39*E10 -> 1755 | F26: =39*F10 -> 1755 | G26: =39*G10 -> 1755 | H26: =39*H10 -> 1755 | I26: =39*I10 -> 1755 | J26: =39*J10 -> 1755 | ... M26: =39*M10 -> 1755 | N26: =SUM(B26:M26) -> 21099
A27: Phone (Phone, Voicemail, Video) | B27: =SUM(28*B6)+(52*B7)+52 -> 596 | C27: =SUM(28*C6)+(52*C7)+52 -> 596 | D27: =SUM(28*D6)+(52*D7)+52 -> 596 | E27: =SUM(28*E6)+(52*E7)+52 -> 596 | F27: =SUM(28*F6)+(52*F7)+52 -> 596 | G27: =SUM(28*G6)+(52*G7)+52 -> 596 | H27: =SUM(28*H6)+(52*H7)+52 -> 596 | I27: =SUM(28*I6)+(52*I7)+52 -> 596 | ... M27: =SUM(28*M6)+(52*M7)+52 -> 596 | N27: =SUM(B27:M27) -> 7152
A28: Recruiting Ads | B28: 850 | C28: 850 | D28: 850 | E28: 850 | F28: 850 | G28: 850 | H28: 850 | I28: 850 | J28: 850 | K28: 850 | L28: 850 | M28: 850 | N28: =SUM(B28:M28) -> 10200
A29: TSR Field Training | B29: =SUM(B8*500) -> 12000 | C29: 1800 | D29: 1800 | E29: =SUM(E8*750) -> 18000 | F29: =SUM(F8*750) -> 18000 | G29: =SUM(G8*750) -> 18000 | H29: =SUM(H8*750) -> 18000 | I29: =SUM(I8*750) -> 18000 | J29: =SUM(J8*750) -> 18000 | K29: =SUM(K8*750) -> 18000 | L29: =SUM(L8*750) -> 18000 | M29: =SUM(M8*750) -> 18000 | N29: =SUM(B29:M29) -> 177600
A30: TSR Per Diem | B30: =500*B8 -> 12000 | C30: =500*C8 -> 12000 | D30: =500*D8 -> 12000 | E30: =500*E8 -> 12000 | F30: =500*F8 -> 12000 | G30: =500*G8 -> 12000 | H30: =500*H8 -> 12000 | I30: =500*I8 -> 12000 | ... M30: =500*M8 -> 12000 | N30: =SUM(B30:M30) -> 144000
A31: TSR Car/Fuel Allowance | B31: =600*B8 -> 14400 | C31: =600*C8 -> 14400 | D31: =600*D8 -> 14400 | E31: =600*E8 -> 14400 | F31: =600*F8 -> 14400 | G31: =600*G8 -> 14400 | H31: =600*H8 -> 14400 | I31: =600*I8 -> 14400 | ... M31: =600*M8 -> 14400 | N31: =SUM(B31:M31) -> 172800
A32: TSR Phone Allowance | B32: =25*B8 -> 600 | C32: =25*C8 -> 600 | D32: =25*D8 -> 600 | E32: =25*E8 -> 600 | F32: =25*F8 -> 600 | G32: =25*G8 -> 600 | H32: =25*H8 -> 600 | I32: =25*I8 -> 600 | ... M32: =25*M8 -> 600 | N32: =SUM(B32:M32) -> 7200
A33: TSR Hotel-2wk/mo travel | B33: =1800*B8 -> 43200 | C33: =1800*C8 -> 43200 | D33: =1800*D8 -> 43200 | E33: =1800*E8 -> 43200 | F33: =1800*F8 -> 43200 | G33: =1800*G8 -> 43200 | H33: =1800*H8 -> 43200 | I33: =1800*I8 -> 43200 | ... M33: =1800*M8 -> 43200 | N33: =SUM(B33:M33) -> 518400
A34: CC Fees (Square/In-Field) | B34: =SUM(B13*4%) -> 4776 | C34: =SUM(C13*4%) -> 4776 | D34: =SUM(D13*4%) -> 4776 | E34: =SUM(E13*4%) -> 4776 | F34: =SUM(F13*4%) -> 4776 | G34: =SUM(G13*4%) -> 4776 | H34: =SUM(H13*4%) -> 4776 | I34: =SUM(I13*4%) -> 4776 | ... M34: =SUM(M13*4%) -> 4776 | N34: =SUM(B34:M34) -> 57312
A35: Printing
A36: Brochures (Leave Behinds) | B36: 500 | C36: =SUM(C8)*50 -> 1200 | D36: =SUM(D8)*50 -> 1200 | E36: =SUM(E8)*50 -> 1200 | F36: =SUM(F8)*50 -> 1200 | G36: =SUM(G8)*50 -> 1200 | H36: =SUM(H8)*50 -> 1200 | I36: =SUM(I8)*50 -> 1200 | J36: =SUM(J8)*50 -> 1200 | ... M36: =SUM(M8)*50 -> 1200 | N36: =SUM(B36:M36) -> 13700
A37: Agreements (2-part) | C37: 0 | D37: 0 | E37: 0 | F37: 0 | G37: 0 | H37: 1250 | I37: 0 | J37: 0 | K37: 0 | N37: =SUM(B37:M37) -> 1250
A38: Business Cards: TSR | C38: =SUM(C8*105) -> 2520 | D38: 0 | E38: 0 | F38: 0 | G38: 0 | H38: =SUM(H8*105) -> 2520 | I38: 0 | J38: 0 | K38: 0 | L38: 0 | M38: 0 | N38: =SUM(B38:M38) -> 5040
A39: Business Cards: RSM | B39: =SUM(B9*56) -> 224 | H39: =SUM(H9*105) -> 420 | I39: 0 | J39: 0 | K39: 0 | L39: 0 | M39: 0 | N39: =SUM(B39:M39) -> 644
A40: Business Cards: CSO | B40: =SUM(B5*105) -> 105 | C40: 0 | D40: 0 | E40: 0 | F40: 0 | G40: 0 | H40: 0 | I40: 0 | J40: 0 | K40: 0 | L40: 0 | M40: 0 | N40: =SUM(B40:M40) -> 105
A41: TOTAL | B41: =SUM(B18:B34) -> 405697.25 | C41: =SUM(C18:C34) -> 317840.05 | D41: =SUM(D18:D34) -> 329040.05 | E41: =SUM(E18:E34) -> 345240.05 | F41: =SUM(F18:F34) -> 345240.05 | G41: =SUM(G18:G34) -> 345240.05 | H41: =SUM(H18:H34) -> 345240.05 | I41: =SUM(I18:I34) -> 345240.05 | ... N41: =SUM(N18:N34) -> 4159737.7
A43: GROSS SALES PROFIT/(LOSS) | B43: =B15-B41 -> 2545702.7 | C43: =C15-C41 -> 2633560 | D43: =D15-D41 -> 2622360 | E43: =E15-E41 -> 2606160 | F43: =F15-F41 -> 2606160 | G43: =G15-G41 -> 2606160 | H43: =H15-H41 -> 2606160 | I43: =I15-I41 -> 2606160 | ... N43: =N15-N41 -> 31257062
A46: CASH FLOW
A47: Balance Fwd | B47: =SUM('FE Sales YR 4'!M51) -> 20443047 | C47: =B51 -> 21682635 | D47: =C48 -> 24634035 | E47: =D48 -> 27585435 | F47: =E48 -> 30536835 | G47: =F48 -> 33488235 | H47: =G48 -> 36439635 | I47: =H48 -> 39391035 | J47: =I48 -> 42342435 | K47: =J48 -> 45293835 | ... M47: =L48 -> 51196635
A48: Ending Balance | B48: =B15+B47 -> 23394447 | C48: =C15+C47 -> 24634035 | D48: =D15+D47 -> 27585435 | E48: =E15+E47 -> 30536835 | F48: =F15+F47 -> 33488235 | G48: =G15+G47 -> 36439635 | H48: =H15+H47 -> 39391035 | I48: =I15+I47 -> 42342435 | ... M48: =M15+M47 -> 54148035
A49: (-) Estimated Company | B49: =SUM(B77:B81) -> 1711812 | C49: =SUM(C77:C81) -> 1711812 | D49: =SUM(D77:D81) -> 1711812 | E49: =SUM(E77:E81) -> 1711812 | F49: =SUM(F77:F81) -> 1711812 | G49: =SUM(G77:G81) -> 1711812 | H49: =SUM(H77:H81) -> 1711812 | I49: =SUM(I77:I81) -> 1711812 | ... M49: =SUM(M77:M81) -> 1711812
A50: (-) Ownership Options % | C50: 0 | E50: =SUM('FE Sales YR 4'!S75) -> 2553522.3
A51: (-) Estimated Retained | B51: =SUM(B48)-B49-B50 -> 21682635 | C51: =SUM(C48)-C49-C50 -> 22922223 | D51: =SUM(D48)-D49-D50 -> 25873623 | E51: =SUM(E48)-E49-E50 -> 26271500 | F51: =SUM(F48)-F49-F50 -> 31776423 | G51: =SUM(G48)-G49-G50 -> 34727823 | H51: =SUM(H48)-H49-H50 -> 37679223 | I51: =SUM(I48)-I49-I50 -> 40630623 | ... M51: =SUM(M48)-M49-M50 -> 52436223 | Q51: 12 Month Avg | R51: Benefits | S51: 401K Match | T51: Monthly Avg
P52: CSO | Q52: =SUM(N66)/N5 -> 531252 | R52: 8400 | S52: =SUM(N66*3%)/N5 -> 15937.56 | T52: =SUM(Q52:S52)/12 -> 46299.13
P53: BC | Q53: =SUM(N67)/N6 -> 66892.5 | R53: 8400 | S53: =SUM(N67*3%)/N6 -> 2006.775 | T53: =SUM(Q53:S53)/12 -> 6441.6062
P54: TMM | Q54: =SUM(N68)/N7 -> 88542 | R54: 8400 | S54: =SUM(N68*3%)/N7 -> 2656.26 | T54: =SUM(Q54:S54)/12 -> 8299.855
P55: TSR | Q55: =SUM(N69)/N8 -> 110490 | R55: 8400 | S55: =SUM(N69*3%)/N8 -> 3314.7 | T55: =SUM(Q55:S55)/12 -> 10183.725
A56: Payroll As Percent | P56: RSM | Q56: =SUM(N70)/N9 -> 166590 | R56: 8400 | S56: =SUM(N70*3%)/N9 -> 4997.7 | T56: =SUM(Q56:S56)/12 -> 14998.975
A57: CSO | B57: =SUM(B66)/B15 -> 0.015 | C57: =SUM(C66)/C15 -> 0.015 | D57: =SUM(D66)/D15 -> 0.015 | E57: =SUM(E66)/E15 -> 0.015 | F57: =SUM(F66)/F15 -> 0.015 | G57: =SUM(G66)/G15 -> 0.015 | H57: =SUM(H66)/H15 -> 0.015 | I57: =SUM(I66)/I15 -> 0.015 | ... M57: =SUM(M66)/M15 -> 0.015
A58: BC | B58: =SUM(B67)/B15 -> 0.022664668 | C58: =SUM(C67)/C15 -> 0.022664668 | D58: =SUM(D67)/D15 -> 0.022664668 | E58: =SUM(E67)/E15 -> 0.022664668 | F58: =SUM(F67)/F15 -> 0.022664668 | G58: =SUM(G67)/G15 -> 0.022664668 | H58: =SUM(H67)/H15 -> 0.022664668 | I58: =SUM(I67)/I15 -> 0.022664668 | ... M58: =SUM(M67)/M15 -> 0.022664668
A59: TMM | B59: =SUM(B68)/B$15 -> 0.01 | C59: =SUM(C68)/C$15 -> 0.01 | D59: =SUM(D68)/D$15 -> 0.01 | E59: =SUM(E68)/E$15 -> 0.01 | F59: =SUM(F68)/F$15 -> 0.01 | G59: =SUM(G68)/G$15 -> 0.01 | H59: =SUM(H68)/H$15 -> 0.01 | I59: =SUM(I68)/I$15 -> 0.01 | ... M59: =SUM(M68)/M$15 -> 0.01
A60: TSR | B60: =SUM(B69)/B$15 -> 0.074872942 | C60: =SUM(C69)/C$15 -> 0.074872942 | D60: =SUM(D69)/D$15 -> 0.074872942 | E60: =SUM(E69)/E$15 -> 0.074872942 | F60: =SUM(F69)/F$15 -> 0.074872942 | G60: =SUM(G69)/G$15 -> 0.074872942 | H60: =SUM(H69)/H$15 -> 0.074872942 | I60: =SUM(I69)/I$15 -> 0.074872942 | ... M60: =SUM(M69)/M$15 -> 0.074872942
A61: RSM | B61: =SUM(B70)/B$15 -> 0.0188148 | C61: =SUM(C70)/C$15 -> 0.0188148 | D61: =SUM(D70)/D$15 -> 0.0188148 | E61: =SUM(E70)/E$15 -> 0.0188148 | F61: =SUM(F70)/F$15 -> 0.0188148 | G61: =SUM(G70)/G$15 -> 0.0188148 | H61: =SUM(H70)/H$15 -> 0.0188148 | I61: =SUM(I70)/I$15 -> 0.0188148 | ... M61: =SUM(M70)/M$15 -> 0.0188148
A62: TOTAL | B62: =SUM(B57:B61) -> 0.14135241 | C62: =SUM(C57:C61) -> 0.14135241 | D62: =SUM(D57:D61) -> 0.14135241 | E62: =SUM(E57:E61) -> 0.14135241 | F62: =SUM(F57:F61) -> 0.14135241 | G62: =SUM(G57:G61) -> 0.14135241 | H62: =SUM(H57:H61) -> 0.14135241 | I62: =SUM(I57:I61) -> 0.14135241 | ... M62: =SUM(M57:M61) -> 0.14135241
A65: Headcount Earnings
A66: CSO | B66: =SUM(B5*$Q5)+(B14*$R5)+(B13*$S5) -> 44271 | C66: =SUM(C5*$Q5)+(C14*$R5)+(C13*$S5) -> 44271 | D66: =SUM(D5*$Q5)+(D14*$R5)+(D13*$S5) -> 44271 | E66: =SUM(E5*$Q5)+(E14*$R5)+(E13*$S5) -> 44271 | F66: =SUM(F5*$Q5)+(F14*$R5)+(F13*$S5) -> 44271 | G66: =SUM(G5*$Q5)+(G14*$R5)+(G13*$S5) -> 44271 | H66: =SUM(H5*$Q5)+(H14*$R5)+(H13*$S5) -> 44271 | I66: =SUM(I5*$Q5)+(I14*$R5)+(I13*$S5) -> 44271 | ... M66: =SUM(M5*$Q5)+(M14*$R5)+(M13*$S5) -> 44271 | N66: =SUM(B66:M66) -> 531252
A67: BC | B67: =SUM(B6*$Q6)+(B$13*$S6)+(B$14*$R6) -> 66892.5 | C67: =SUM(C6*$Q6)+(C$13*$S6)+(C$14*$R6) -> 66892.5 | D67: =SUM(D6*$Q6)+(D$13*$S6)+(D$14*$R6) -> 66892.5 | E67: =SUM(E6*$Q6)+(E$13*$S6)+(E$14*$R6) -> 66892.5 | F67: =SUM(F6*$Q6)+(F$13*$S6)+(F$14*$R6) -> 66892.5 | G67: =SUM(G6*$Q6)+(G$13*$S6)+(G$14*$R6) -> 66892.5 | H67: =SUM(H6*$Q6)+(H$13*$S6)+(H$14*$R6) -> 66892.5 | I67: =SUM(I6*$Q6)+(I$13*$S6)+(I$14*$R6) -> 66892.5 | ... M67: =SUM(M6*$Q6)+(M$13*$S6)+(M$14*$R6) -> 66892.5 | N67: =SUM(B67:M67) -> 802710
A68: TMM | B68: =SUM(B7*$Q7)+(B$13*$S7)+(B$14*$R7) -> 29514 | C68: =SUM(C7*$Q7)+(C$13*$S7)+(C$14*$R7) -> 29514 | D68: =SUM(D7*$Q7)+(D$13*$S7)+(D$14*$R7) -> 29514 | E68: =SUM(E7*$Q7)+(E$13*$S7)+(E$14*$R7) -> 29514 | F68: =SUM(F7*$Q7)+(F$13*$S7)+(F$14*$R7) -> 29514 | G68: =SUM(G7*$Q7)+(G$13*$S7)+(G$14*$R7) -> 29514 | H68: =SUM(H7*$Q7)+(H$13*$S7)+(H$14*$R7) -> 29514 | I68: =SUM(I7*$Q7)+(I$13*$S7)+(I$14*$R7) -> 29514 | ... M68: =SUM(M7*$Q7)+(M$13*$S7)+(M$14*$R7) -> 29514 | N68: =SUM(B68:M68) -> 354168
A69: TSR | B69: =SUM(B8*$Q8)+(B$13*$S8)+(B$14*$R8) -> 220980 | C69: =SUM(C8*$Q8)+(C$13*$S8)+(C$14*$R8) -> 220980 | D69: =SUM(D8*$Q8)+(D$13*$S8)+(D$14*$R8) -> 220980 | E69: =SUM(E8*$Q8)+(E$13*$S8)+(E$14*$R8) -> 220980 | F69: =SUM(F8*$Q8)+(F$13*$S8)+(F$14*$R8) -> 220980 | G69: =SUM(G8*$Q8)+(G$13*$S8)+(G$14*$R8) -> 220980 | H69: =SUM(H8*$Q8)+(H$13*$S8)+(H$14*$R8) -> 220980 | I69: =SUM(I8*$Q8)+(I$13*$S8)+(I$14*$R8) -> 220980 | ... M69: =SUM(M8*$Q8)+(M$13*$S8)+(M$14*$R8) -> 220980 | N69: =SUM(B69:M69) -> 2651760
A70: RSM | B70: =SUM(B9*$Q9)+(B$13*$S9)+(B$14*$R9) -> 55530 | C70: =SUM(C9*$Q9)+(C$13*$S9)+(C$14*$R9) -> 55530 | D70: =SUM(D9*$Q9)+(D$13*$S9)+(D$14*$R9) -> 55530 | E70: =SUM(E9*$Q9)+(E$13*$S9)+(E$14*$R9) -> 55530 | F70: =SUM(F9*$Q9)+(F$13*$S9)+(F$14*$R9) -> 55530 | G70: =SUM(G9*$Q9)+(G$13*$S9)+(G$14*$R9) -> 55530 | H70: =SUM(H9*$Q9)+(H$13*$S9)+(H$14*$R9) -> 55530 | I70: =SUM(I9*$Q9)+(I$13*$S9)+(I$14*$R9) -> 55530 | ... M70: =SUM(M9*$Q9)+(M$13*$S9)+(M$14*$R9) -> 55530 | N70: =SUM(B70:M70) -> 666360
A71: Payroll Burden | B71: =SUM(B22:B24) -> 53906.254 | C71: =SUM(C22:C24) -> 46435.545 | D71: =SUM(D22:D24) -> 46435.545 | E71: =SUM(E22:E24) -> 46435.545 | F71: =SUM(F22:F24) -> 46435.545 | G71: =SUM(G22:G24) -> 46435.545 | H71: =SUM(H22:H24) -> 46435.545 | I71: =SUM(I22:I24) -> 46435.545 | ... M71: =SUM(M22:M24) -> 46435.545 | N71: =SUM(B71:M71) -> 564697.25
A72: TOTAL | B72: =SUM(B66:B71) -> 471093.75 | C72: =SUM(C66:C71) -> 463623.04 | D72: =SUM(D66:D71) -> 463623.04 | E72: =SUM(E66:E71) -> 463623.04 | F72: =SUM(F66:F71) -> 463623.04 | G72: =SUM(G66:G71) -> 463623.04 | H72: =SUM(H66:H71) -> 463623.04 | I72: =SUM(I66:I71) -> 463623.04 | ... M72: =SUM(M66:M71) -> 463623.04 | N72: =SUM(B72:M72) -> 5570947.2 | P72: =SUM(100%-O82) -> 0.30196345 | Q72: Net
P73: =SUM(N15)*P72 -> 10694579 | Q73: $ Net
A75: Budget Snapshot (Estimated Company) | O75: % | Q75: Ownership Options | R75: % | S75: $ Annual
A76: Sales (includes Travel 25%) | B76: =SUM(B18:B40) -> 406526.25 | C76: =SUM(C18:C40) -> 321560.05 | D76: =SUM(D18:D40) -> 330240.05 | E76: =SUM(E18:E40) -> 346440.05 | F76: =SUM(F18:F40) -> 346440.05 | G76: =SUM(G18:G40) -> 346440.05 | H76: =SUM(H18:H40) -> 350630.05 | I76: =SUM(I18:I40) -> 346440.05 | ... M76: =SUM(M18:M40) -> 346440.05 | N76: =SUM(B76:M76) -> 4180476.7 | O76: =SUM(N76)/N15 -> 0.11803655 | Q76: Total | R76: =SUM(P72) -> 0.30196345 | S76: =SUM(P73)*R76 -> 3229372.1
A77: Survey (includes Travel 25%) | B77: =SUM(B15)*25% -> 737850 | C77: =SUM(C15)*25% -> 737850 | D77: =SUM(D15)*25% -> 737850 | E77: =SUM(E15)*25% -> 737850 | F77: =SUM(F15)*25% -> 737850 | G77: =SUM(G15)*25% -> 737850 | H77: =SUM(H15)*25% -> 737850 | I77: =SUM(I15)*25% -> 737850 | ... M77: =SUM(M15)*25% -> 737850 | N77: =SUM(B77:M77) -> 8854200 | O77: =SUM(N77)/N15 -> 0.25
A78: Consulting (25%) | B78: =SUM(B15)*25% -> 737850 | C78: =SUM(C15)*25% -> 737850 | D78: =SUM(D15)*25% -> 737850 | E78: =SUM(E15)*25% -> 737850 | F78: =SUM(F15)*25% -> 737850 | G78: =SUM(G15)*25% -> 737850 | H78: =SUM(H15)*25% -> 737850 | I78: =SUM(I15)*25% -> 737850 | ... M78: =SUM(M15)*25% -> 737850 | N78: =SUM(B78:M78) -> 8854200 | O78: =SUM(N78)/N15 -> 0.25 | Q78: Retained Belfield | R78: % | S78: $ Annual
A79: Admin/Operations (5%) | B79: =SUM(B15)*5% -> 147570 | C79: =SUM(C15)*5% -> 147570 | D79: =SUM(D15)*5% -> 147570 | E79: =SUM(E15)*5% -> 147570 | F79: =SUM(F15)*5% -> 147570 | G79: =SUM(G15)*5% -> 147570 | H79: =SUM(H15)*5% -> 147570 | I79: =SUM(I15)*5% -> 147570 | ... N79: =SUM(N15)*5% -> 1770840 | O79: =SUM(N79)/N15 -> 0.05 | Q79: Total | R79: =100%-R76 -> 0.69803655 | S79: =SUM(P73)*R79 -> 7465207.2
A80: President Salary (2.25%) | B80: =SUM(B15)*2.25% -> 66406.5 | C80: =SUM(C15)*2.25% -> 66406.5 | D80: =SUM(D15)*2.25% -> 66406.5 | E80: =SUM(E15)*2.25% -> 66406.5 | F80: =SUM(F15)*2.25% -> 66406.5 | G80: =SUM(G15)*2.25% -> 66406.5 | H80: =SUM(H15)*2.25% -> 66406.5 | I80: =SUM(I15)*2.25% -> 66406.5 | ... M80: =SUM(M15)*2.25% -> 66406.5 | N80: =SUM(B80:M80) -> 796878 | O80: =SUM(N80)/N15 -> 0.0225
A81: CFO Salary (.75%) | B81: =SUM(B15)*0.0075 -> 22135.5 | C81: =SUM(C15)*0.0075 -> 22135.5 | D81: =SUM(D15)*0.0075 -> 22135.5 | E81: =SUM(E15)*0.0075 -> 22135.5 | F81: =SUM(F15)*0.0075 -> 22135.5 | G81: =SUM(G15)*0.0075 -> 22135.5 | H81: =SUM(H15)*0.0075 -> 22135.5 | I81: =SUM(I15)*0.0075 -> 22135.5 | ... M81: =SUM(M15)*0.0075 -> 22135.5 | N81: =SUM(B81:M81) -> 265626 | O81: =SUM(N81)/N15 -> 0.0075
A82: TOTAL | B82: =SUM(B76:B81) -> 2118338.3 | C82: =SUM(C76:C81) -> 2033372 | D82: =SUM(D76:D81) -> 2042052 | E82: =SUM(E76:E81) -> 2058252 | F82: =SUM(F76:F81) -> 2058252 | G82: =SUM(G76:G81) -> 2058252 | H82: =SUM(H76:H81) -> 2062442 | I82: =SUM(I76:I81) -> 2058252 | ... O82: =SUM(O76:O81) -> 0.69803655
