Workbook

Sheet BE Worksheet
B4: Client: | C4: Sample Company Name
B5: Job #: | C5: Sample Job #
B6: Date: | C6: 40922
A7: BREAK-EVEN ANALYSIS
B8: CURRENT 2011 | E8: PROJECTED 2012
A9: SALES | B9: 1917512 | C9: =SUM(B9/B$9) -> 1 | E9: SALES | F9: =SUM(B9) -> 1917512 | G9: =SUM(F10/F$10) -> 1
A10: Profit | B10: -10000 | C10: =SUM(B10/B9) -> -0.0052150912 | E10: Profit | F10: =SUM(F9*G10) -> 241606.51 | G10: 0.126
A11: Total All Expenses | B11: =SUM(B9-B10) -> 1927512 | C11: =SUM(B11/B$9) -> 1.0052151 | E11: Total All Expenses | F11: =SUM(F9-F10) -> 1675905.5 | G11: =SUM(F11/F$9) -> 0.874
A13: FIXED EXPENSE | E13: FIXED EXPENSE
A14: Rent | B14: 48000 | C14: =SUM(B14/B$9) -> 0.025032438 | E14: Rent | G14: =SUM(F14/F$10) -> 0
A15: Insurance | B15: 2816 | C15: =SUM(B15/B$9) -> 0.0014685697 | E15: Insurance | G15: =SUM(F15/F$10) -> 0
A16: Officers | B16: 31000 | C16: =SUM(B16/B$9) -> 0.016166783 | E16: Officers | G16: =SUM(F16/F$10) -> 0
A17: Depreciation | B17: 45446 | C17: =SUM(B17/B$9) -> 0.023700504 | E17: Depreciation | G17: =SUM(F17/F$10) -> 0
A18: Interest | B18: 8462 | C18: =SUM(B18/B$9) -> 0.0044130102 | E18: Interest | G18: =SUM(F18/F$10) -> 0
A19: Taxes | B19: 11760 | C19: =SUM(B19/B$9) -> 0.0061329473 | E19: Taxes | G19: =SUM(F19/F$10) -> 0
A20: Total Fixed Expenses | B20: =SUM(B14:B19) -> 147484 | C20: =SUM(B20/B$9) -> 0.076914251 | E20: Total Fixed Expenses | F20: =SUM(B20) -> 147484 | G20: =SUM(F20/F$9) -> 0.076914251
A22: VARIABLE EXPENSES | E22: VARIABLE EXPENSES
A23: COGS | B23: 1520312 | C23: =SUM(B23/B$9) -> 0.79285658 | E23: COGS
A24: Labor | B24: 93576 | C24: =SUM(B24/B$9) -> 0.048800738 | E24: Labor
A25: Total Variable Expenses | B25: =SUM(B23:B24) -> 1613888 | C25: =SUM(B25/B$9) -> 0.84165731 | E25: Total Variable Expenses | F25: =SUM(F9*G25) -> 1386361.2 | G25: 0.723
A27: Total Other Costs | B27: =SUM(B11-B20-B25) -> 166140 | C27: =SUM(B27/B$9) -> 0.086643526 | E27: Total Other Costs | F27: =SUM(F11-F20-F25) -> 142060.31 | G27: =SUM(F27/F$9) -> 0.074085749
A29: Total Var/Other | B29: =SUM(B27/2)+B25 -> 1696958 | C29: =SUM(B29/B$9) -> 0.88497908 | E29: Total Var/Other | F29: =SUM(F27/2)+F25 -> 1457391.3 | G29: =SUM(F29/F$9) -> 0.76004287
A30: Total Fix/Other | B30: =SUM(B27/2)+B20 -> 230554 | C30: =SUM(B30/B$9) -> 0.12023601 | E30: Total Fix/Other | F30: =SUM(F27/2)+F20 -> 218514.16 | G30: =SUM(F30/F$9) -> 0.11395713
A31: Fix/Profit | B31: =SUM(B30+B10) -> 220554 | C31: =SUM(B31/B$9) -> 0.11502092 | E31: Fix/Profit | F31: =SUM(F30+F10) -> 460120.67 | G31: =SUM(F31/F$9) -> 0.23995713
A33: BREAK-EVEN POINT % | B33: =SUM(B30/B31) -> 1.0453404 | E33: BREAK-EVEN POINT % | F33: =SUM(F30/F31) -> 0.4749062
A34: BREAK-EVEN POINT DOLLARS | B34: =SUM(B9*B33) -> 2004452.7 | C34: =SUM(B34/B$9) -> 1.0453404 | E34: BREAK-EVEN POINT DOLLARS | F34: =SUM(F10*F33) -> 114740.43 | G34: =SUM(F34/F$10) -> 0.4749062
A35: BREAK-EVEN DAYS | B35: =SUM(365*B33) -> 381.54924 | E35: BREAK-EVEN DAYS | F35: =SUM(365*F33) -> 173.34076

Sheet CURRENT
B5: Client: | C5: Sample Company Name | I5: Client: | J5: Sample Company Name
B6: Job #: | C6: Sample Job # | I6: Job #: | J6: Sample Job #
B7: Date: | I7: Date:
B9: =SUM('BE Worksheet'!C20) -> 0.076914251 | C9: =SUM(#REF!) -> #REF!
B10: =SUM('BE Worksheet'!C25) -> 0.84165731 | C10: =SUM(#REF!) -> #REF!
B11: =SUM('BE Worksheet'!C27) -> 0.086643526 | C11: =SUM(#REF!) -> #REF!
B12: =SUM('BE Worksheet'!C10) -> -0.0052150912 | C12: =SUM(#REF!) -> #REF!
B30: GREEN: | C30: PROFIT | I30: GREEN: | J30: PROFIT
B31: BLUE: | C31: FIXED EXPENSE | I31: BLUE: | J31: FIXED EXPENSE
B32: RED: | C32: VARIABLE EXPENSE | I32: RED: | J32: VARIABLE EXPENSE
B33: YELLOW: | C33: SEM-VARIABLE EXPENSE | I33: YELLOW: | J33: SEM-VARIABLE EXPENSE

Sheet PROJECTED
B5: Client: | C5: Sample Company Name | I5: Client: | J5: Sample Company Name
B6: Job #: | C6: Sample Job # | I6: Job #: | J6: Sample Job #
B7: Date: | C7: 40922 | I7: Date: | J7: 40922
B9: =SUM('BE Worksheet'!G10) -> 0.126 | C9: =SUM(#REF!) -> #REF!
B10: =SUM('BE Worksheet'!G20) -> 0.076914251 | C10: =SUM(#REF!) -> #REF!
B11: =SUM('BE Worksheet'!G25) -> 0.723 | C11: =SUM(#REF!) -> #REF!
B12: =SUM('BE Worksheet'!G27) -> 0.074085749 | C12: =SUM(#REF!) -> #REF!
B30: GREEN: | C30: PROFIT | I30: GREEN: | J30: PROFIT
B31: BLUE: | C31: FIXED EXPENSE | I31: BLUE: | J31: FIXED EXPENSE
B32: RED: | C32: VARIABLE EXPENSE | I32: RED: | J32: VARIABLE EXPENSE
B33: YELLOW: | C33: SEM-VARIABLE EXPENSE | I33: YELLOW: | J33: SEM-VARIABLE EXPENSE
